Workbook

Sheet Cover
B2: AGENT TEST COVER
B3: Version: | C3: 1.0
B4: Updated date: | C4: 46277
B5: Project: | C5: AI IT Job Market Consultant
B7: Revision History:
B8: Effective date | C8: Version | D8: Module | E8: Description | F8: Publisher | G8: Reviewer | H8: Source of reference
B9: 46217 | C9: 0.1 | D9: agent-test-case-report.xlsx | E9: Agent test report template initiation | F9: V. T. Thanh | G9: V. T. Thanh
B10: 46217 | C10: 1.0 | D10: AIJMC, Gemini, ChatGPT | E10: Design and add AI agent test cases for the benchmark. | F10: V.T. Thanh | G10: V.T. Thanh

Sheet AIJMC Gemini Flash 
A1: AGENT TEST CASE
A3: Project: | B3: AI IT Job Market Consultant
A4: Module: | B4: AIJMC Gemini Flash
A5: Test environment: | B5: AIJMC Cloud Deployment
A6: Pass | B6: =COUNTIFS(K11:K199, "Pass", A11:A199, "<>*AI") -> 20 | D6: Judge Pass | E6: =COUNTIF(M12:M199,"Pass") -> 17 | F6: Pending | G6: =COUNTIFS(K11:K199, "Pending", A11:A199, "<>*AI") -> 3
A7: Fail | B7: =COUNTIFS(K11:K199, "Fail", A11:A199, "<>*AI") -> 7 | D7: Judge Fail | E7: =COUNTIF(M11:M199,"Fail") -> 9 | F7: Total test case | G7: =COUNTIF(A11:A199, "TC*") -> 30
A9: Test case ID | B9: Test level | C9: Test case name | D9: AI Agent Input | E9: Expected results | I9: Actual results | J9: Test date | K9: Status | L9: Judge result | M9: Judge Status | N9: Reference | O9: Test case purpose
A12: TC-01 | B12: Dễ | C12: Tìm tin tuyển dụng Python Developer | D12: Tôi muốn tìm các tin tuyển dụng Python Developer tại Việt Nam. | E12: Trả về danh sách tin tuyển dụng phù hợp với vị trí Python Developer tại Việt Nam và không đưa các vị trí không liên quan đến Python Developer vào danh sách chính. | I12: Dưới đây là danh sách các vị trí tuyển dụng Python Developer đang mở tuyển tại Việt Nam, cùng với phân tích tổng quan về mức lương và kỹ năng được yêu cầu nhiều nhất. 📋 Danh Sách Tin Tuyển Dụng Python Developer Nổi Bật Vị trí Công ty Cấp bậc Mô hình làm việc Kỹ năng chính Link ứng tuyển Senior Python Developer ISB Vietnam Company Senior Onsite AWS, API, PostgreSQL, Docker, Kubernetes, Milvus, Web3 Xem chi tiết Senior Python Developer Prestige Home Senior Onsite (Up to 40 triệu/tháng) Django, Redis, RESTful API Xem chi tiết Python Developer Accenture Mid Hybrid REST API, Software Engineering Xem chi tiết Lead Python Developer FPT Software Lead Onsite Flask, SOLID Principles, Team Leadership Xem chi tiết Senior Full-Stack Developer (Python/Node.js) ONE Tech Stop Vietnam Senior Onsite (Đà Nẵng) Python, Django, Cloud Architecture Xem chi tiết Lập Trình Viên Python VNPT Mid Onsite Python, Web Fundamentals Xem chi tiết 📊 Phân Tích Thị Trường & Kỹ Năng Yêu Cầu 1. Kỹ năng phổ biến được nhà tuyển dụng tìm kiếm Web Frameworks: Django, FastAPI, Flask. Database & Caching: PostgreSQL, MySQL, Redis, Elasticsearch. Cloud & DevOps: AWS, Docker, Kubernetes, CI/CD. Xu hướng mới: Các ứng dụng tích hợp AI/LLM, Vector Databases (Milvus), Web3, và Big Data/Data Engineering. 2. Mức lương tham khảo Mid-level Python Developer: Dao động từ $1,000 - $1,800 USD/tháng (~25 - 45 triệu VND). Senior / Lead Python Developer: Dao động từ $1,800 - $3,500+ USD/tháng (~45 - 85+ triệu VND), tùy thuộc vào chuyên môn về System Architecture, Cloud, hoặc AI. 💡 Lời Khuyên Dành Cho Ứng Viên Tập trung vào Framework & API: Nắm vững RESTful API, gRPC cùng với Django hoặc FastAPI để tối ưu hóa khả năng trúng tuyển vào các công ty sản xuất sản phẩm (Product) hoặc Outsourcing lớn. Kỹ năng Cloud & Microservices: Việc có kiến thức làm việc với Docker, Kubernetes và AWS/GCP là điểm cộng rất lớn đối với cấp bậc từ Mid-level trở lên. Cập nhật kiến thức AI/ML: Nhờ sự bùng nổ của GenAI, Python Developer có thêm lợi thế lớn nếu nắm rõ kiến thức làm việc với LLM, LangChain hoặc Vector Databases. Nếu bạn cần tư vấn sâu hơn về cách tối ưu CV cho vị trí Python Developer hoặc muốn tìm kiếm thêm thông tin ở địa điểm cụ thể (Hà Nội, TP.HCM, Đà Nẵng), hãy cho tôi biết! | J12: 46277 | K12: Pass | L12: { "judge_result": "PASS", "judge_status": "PASS", "reason": "The Actual Result successfully provides a list of relevant Python Developer job postings in Vietnam and does not include irrelevant positions, fulfilling the Expected Result and Test Case Purpose." } | M12: Pass | N12: No reference | O12: Kiểm tra khả năng truy xuất và cung cấp các tin tuyển dụng phù hợp với vị trí Python Developer tại Việt Nam.
A14: TC-02 | B14: Dễ | C14: Tìm việc Backend Developer | D14: Hãy tìm các tin tuyển dụng Backend Developer tại Việt Nam. | E14: Cung cấp các tin tuyển dụng thuộc nhóm Backend Developer và không tự tạo tên công ty hoặc tin tuyển dụng. | I14: Dưới đây là danh sách các tin tuyển dụng Backend Developer đang mở tuyển tại Việt Nam, cùng với phân tích tổng quan về thị trường, mức lương và các kỹ năng chuyên môn được yêu cầu phổ biến nhất. 📋 Danh Sách Tin Tuyển Dụng Backend Developer Nổi Bật Vị trí Công ty Cấp bậc Mô hình Mức lương Kỹ năng chính Link ứng tuyển Backend Developer Creative Force Mid Onsite 80,000,000 VND AWS, Microservices, .NET Core, AI, RESTful API Xem chi tiết Senior Backend Developer (Golang) VISION Advisory & Analytics Senior Onsite 1,500 - 3,500 USD Golang, Linux, PostgreSQL, Docker Xem chi tiết Back-End Developer (NodeJS) Công ty Cổ phần Smileviet Mid Onsite 800 - 1,200 USD NodeJS, MySQL, ReactJS Xem chi tiết Backend Developer (Python/.NET) LizAI Vietnam Junior / Senior Onsite 800 - 2,000 USD Python, .NET Core, SQL Xem chi tiết Backend Developer (Fintech) Pinetree Securities Mid Onsite Thương lượng Java Spring, AWS, Microservices, Kafka, Redis Xem chi tiết PHP Backend Developer LikeLion Vietnam Mid Onsite Thương lượng PHP, REST API, MySQL Xem chi tiết Back-End Developer GS25 Vietnam Mid Onsite Thương lượng Java, Python, OOP Xem chi tiết 📊 Phân Tích Thị Trường & Mức Lương Backend Developer 1. Mức lương trung bình (Benchmark) Junior / Fresher: $600 – $1,000 / tháng. Mid-level: $1,000 – $2,000 / tháng (hoặc khoảng 25 - 45 triệu VND). Các vị trí yêu cầu kiến trúc hệ thống chuyên sâu hoặc lĩnh vực Fintech/AI có thể đạt tới 80,000,000 VND. Senior / Lead: $2,000 – $3,500+ / tháng (tùy thuộc vào ngôn ngữ cốt lõi như Golang, Java Microservices, Cloud Architecture). 2. Các nhóm công nghệ (Tech Stack) phổ biến Ngôn ngữ lập trình được săn đón: Java (Spring Boot), Node.js (TypeScript/Express/NestJS), .NET Core, Python (Django/FastAPI) và Golang. Cơ sở dữ liệu: PostgreSQL, MySQL, MariaDB cùng với các giải pháp Caching/Message Queue như Redis, Apache Kafka, RabbitMQ. Hạ tầng & Cloud: Điện toán đám mây (AWS, GCP), Docker, Kubernetes, CI/CD, kiến trúc Microservices. 💡 Đánh Giá & Lời Khuyên Ứng Tuyển Đa dạng hóa Tech Stack: Ngoài ngôn ngữ chính (Java/Node.js/Python/.NET), việc sở hữu kỹ năng về Microservices, Docker/Kubernetes và Cloud (AWS/GCP) sẽ giúp bạn nâng cao đáng kể lợi thế cạnh tranh và mức thù lao. Ngành hàng ưu tiên: Các doanh nghiệp trong mảng Fintech, E-commerce, Tài chính - Chứng khoán và Đổi mới sáng tạo (AI/Web3) hiện đang chào đón các Backend Developer với mức đãi ngộ cao. Chuẩn bị hồ sơ: Nhấn mạnh các dự án thực tế có xử lý tải cao (High Throughput/Scalability), tối ưu hóa Database và thiết kế RESTful/GraphQL API. | J14: 46277 | K14: Pass | L14: { "judge_result": "PASS", "judge_status": "PASS", "reason": "The Actual Result successfully provides a list of real Backend Developer job postings in Vietnam and does not fabricate company names or job postings, completely satisfying the Expected Result and Test Case Purpose." } | M14: Pass | N14: No reference | O14: Kiểm tra khả năng tìm kiếm và trả về các tin tuyển dụng thuộc nhóm Backend Developer.
A16: TC-03 | B16: Dễ | C16: Tìm việc Frontend Developer | D16: Có những tin tuyển dụng Frontend Developer nào? | E16: Trả về các tin tuyển dụng liên quan đến Frontend Developer. Nếu có dữ liệu, cung cấp các trường như công ty, vị trí, địa điểm và đường dẫn hoặc nguồn tin. | I16: Dưới đây là danh sách các vị trí tuyển dụng Frontend Developer đang mở tuyển tại Việt Nam, kèm theo tổng quan về thị trường, mức lương và các kỹ năng chuyên môn được yêu cầu phổ biến. 📋 Danh Sách Tin Tuyển Dụng Frontend Developer Nổi Bật Vị trí Công ty Cấp bậc Mô hình Mức lương Kỹ năng chính Link ứng tuyển Frontend ReactJS Developer Công ty cổ phần hàng hải Vsico Mid Hybrid 700 - 900 USD CSS, TypeScript, JavaScript, HTML Xem chi tiết Front-End Developer IncepIT Mid Onsite 800 - 2,500 USD AWS, Linux, PHP, JavaScript, HTML/CSS Xem chi tiết Senior Frontend Web Developer VISION Advisory & Analytics Senior Onsite Thỏa thuận TypeScript, CSS3, NextJS, HTML5 Xem chi tiết Frontend Developer (Shopify/Wordpress) SOLIS LAB Mid Onsite 800 - 1,200 USD ReactJS, CSS, HTML, Shopify, WordPress Xem chi tiết Frontend Developer (ReactJS) Bất Động Sản Hapulico Mid Onsite Thỏa thuận ReactJS, JavaScript, Web Frontend Xem chi tiết Fullstack Engineer (Frontend Focus) Cazoodle Junior - Mid Remote Thỏa thuận React, UI/UX, Web App Xem chi tiết Senior Frontend Web Developer SHINHAN DS Senior Onsite Thỏa thuận JavaScript, HTML/CSS, API, NoSQL Xem chi tiết Product Frontend Intern GEEK UP Intern Onsite Thỏa thuận ReactJS, HTML5, GitHub Xem chi tiết 📊 Phân Tích Thị Trường Tuyển Dụng Frontend 1. Phổ Mức Lương (Salary Range) Junior / Intern: Thường dao động từ 8 - 15 triệu VND (~350 - 650 USD). Mid-level (2 - 4 năm kinh nghiệm): Phổ biến trong khoảng 800 - 1,500 USD/tháng (tùy thuộc vào khả năng tiếng Anh và tech stack). Senior / Lead (4+ năm kinh nghiệm): Phổ lương mở rộng từ 1,800 - 2,500+ USD/tháng, đặc biệt ở các công ty sản xuất phần mềm (Product) hoặc các dự án quốc tế. 2. Kỹ Năng Yêu Cầu Phổ Biến (Top Tech Stack) Frameworks/Libraries: ReactJS / NextJS là bộ đôi chiếm ưu thế vượt trội trong phần lớn tin tuyển dụng hiện nay. Ngoài ra, Vue.js và Angular cũng giữ thị phần nhất định. Ngôn ngữ & Tiền xử lý: TypeScript đã trở thành tiêu chuẩn gần như bắt buộc cho các vị trí Mid/Senior bên cạnh HTML5/CSS3 và JavaScript (ES6+). Kỹ năng mở rộng: Hiểu biết về RESTful APIs, Tối ưu hiệu năng (Performance Optimization), UI/UX Design System, State Management (Redux, Zustand) và kinh nghiệm làm việc với các hệ thống CI/CD hoặc CMS (Shopify/WordPress). 💡 Lời Khuyên Cho Ứng Viên Nâng cao kiến thức TypeScript & Next.js: Đa số các công ty trả mức lương khá trở lên đều ưu tiên ứng viên thành thạo TypeScript và các Renderer Framework như Next.js để tối ưu SEO và Server-Side Rendering (SSR). Chú trọng tối ưu trải nghiệm người dùng (UX/Performance): Nắm vững kiến thức về Core Web Vitals, Responsive Design và accessibility (a11y) sẽ giúp bạn ghi điểm lớn trong các buổi phỏng vấn vị trí Senior. Nếu bạn cần tư vấn chi tiết hơn về mức lương theo cấp bậc cụ thể hoặc lộ trình nâng cao kỹ năng Frontend, hãy cho tôi biết! | J16: 46277 | K16: Pass | L16: { "judge_result": "PASS", "judge_status": "PASS", "reason": "The Actual Result successfully provides a list of Frontend Developer job postings along with relevant details such as the position, company, and application link, fulfilling the requirements of the Expected Result." } | M16: Pass | N16: No reference | O16: Kiểm tra khả năng truy xuất các tin tuyển dụng liên quan đến vị trí Frontend Developer.
A18: TC-04 | B18: Dễ | C18: Tìm việc React Developer | D18: Tìm giúp tôi các công việc yêu cầu React tại Việt Nam. | E18: Trả về các tin tuyển dụng có yêu cầu hoặc đề cập đến React. | I18: Dưới đây là danh sách các cơ hội việc làm yêu cầu React (ReactJS / React Native) tại Việt Nam, cùng với phân tích tổng quan về mức lương, cấp bậc và bộ kỹ năng đi kèm được các nhà tuyển dụng tìm kiếm phổ biến. 📋 Danh Sách Tin Tuyển Dụng Yêu Cầu React Nổi Bật Vị trí Công ty Cấp bậc Mô hình Mức lương Kỹ năng liên quan Link ứng tuyển Senior React Frontend Engineer Clearstone Software Senior Onsite 2,800 - 3,800 USD TypeScript, REST API, Front-end Ứng tuyển Lead React Native Developer CÔNG TY TNHH BRIDGETEK VIỆT NAM Lead Onsite 70 - 90 Triệu VND React Native, Mobile Development Ứng tuyển Sr. Frontend Dev (ReactJS, JS/TS) CÔNG TY TNHH AI MED ENGINE Mid/Senior Onsite 1,000 - 2,500 USD JavaScript, TypeScript, HTML5/CSS3 Ứng tuyển Frontend ReactJS (ReactJS, JS) Công ty TNHH RENDA Mid Hybrid 700 - 1,200 USD JavaScript, Front-end, ERP Ứng tuyển Frontend ReactJS Developer Công ty Cổ phần Hàng hải Vsico Mid Hybrid 700 - 900 USD TypeScript, JavaScript, HTML/CSS Ứng tuyển [HN] Senior ReactJS Engineer NAB Innovation Centre Vietnam Senior Hybrid Thỏa thuận TypeScript, JavaScript, Redux Ứng tuyển Senior Front-End Engineer (React & Micro Frontend) EPAM Vietnam Senior Remote Thỏa thuận TypeScript, Redux, Micro Frontend Ứng tuyển Senior Front-End Engineer EPAM Senior Onsite Thỏa thuận ReactJS, React Query, MS Azure, REST API Ứng tuyển Full-Stack ReactJS / NodeJS Developer FPT Software HN Mid Onsite Thỏa thuận ReactJS, NodeJS, PostgreSQL, MongoDB Ứng tuyển 📊 Phân Tích Nhu Cầu Tuyển Dụng React Tại Việt Nam 1. Phân Phối Mức Lương theo Cấp Bậc Mid-level (2 - 4 năm kinh nghiệm): Phổ biến trong khoảng 700 – 1,200 USD/tháng (tương đương 18 - 30 triệu VND). Senior-level (4+ năm kinh nghiệm): Dao động từ 1,000 – 3,800 USD/tháng (tương đương 25 - 95 triệu VND) tùy thuộc vào quy mô công ty và mức độ yêu cầu về kiến trúc hệ thống. Lead / Management: Có thể đạt 70 – 90 triệu VND/tháng (hoặc trên 3,000 USD/tháng). 2. Các Kỹ Năng Bổ Trợ Được Đòi Hỏi Nhiều Nhất TypeScript & JavaScript ES6+: Gần như là tiêu chuẩn bắt buộc đi kèm với ReactJS trong các dự án hiện đại. State Management: Redux, Context API, React Query/TanStack Query. Backend Knowledge (Full-stack): Nhu cầu tuyển kết hợp ReactJS + NodeJS tăng cao cho các vị trí Full-stack Developer. Kiến trúc Hiện đại: Micro Frontends, CI/CD, Cloud Service (AWS, Azure) thường được đưa vào yêu cầu cho cấp bậc Senior trở lên. 3. Xu Hướng Mô Hình Làm Việc Mô hình Hybrid và Remote khá phổ biến ở các vị trí ReactJS, đặc biệt là các công ty tư vấn phần mềm quốc tế (EPAM, NAB, Renda) giúp ứng viên linh hoạt về không gian làm việc. Nếu bạn muốn tìm hiểu sâu hơn về mức lương trung bình của một vai trò cụ thể, so sánh React với Vue/Angular, hoặc chuẩn bị cho phỏng vấn React, hãy cho tôi biết nhé! | J18: 46277 | K18: Pass | L18: { "judge_result": "PASS", "judge_status": "PASS", "reason": "The Actual Result successfully provides a list of job postings that require or mention React (ReactJS/React Native) in Vietnam, fully satisfying the Expected Result and Test Case Purpose." } | M18: Pass | N18: No reference | O18: Kiểm tra khả năng nhận diện và truy xuất các tin tuyển dụng có yêu cầu hoặc đề cập đến React.
A20: TC-05 | B20: Dễ | C20: Tìm việc Java Developer | D20: Tôi cần tìm tin tuyển dụng Java Developer ở Việt Nam. | E20: Cung cấp danh sách tin tuyển dụng phù hợp với Java Developer. Không nhầm Java với JavaScript. | I20: Dưới đây là thông tin chi tiết về các vị trí tuyển dụng Java Developer đang mở tại Việt Nam, cùng với phân tích tổng quan về mức lương, các kỹ năng liên quan và xu hướng tuyển dụng cho vai trò này. 📋 Danh Sách Tin Tuyển Dụng Java Developer Nổi Bật Vị trí Công ty Cấp bậc Mô hình Mức lương Kỹ năng chính Ứng tuyển Mid/Sr Java Developer (English Required) Rakuten Fintech Vietnam Mid / Senior Onsite 1,500 - 3,200 USD Spring, Unit Test, English Chi tiết Senior Java Developer (Spring/OOP) Nakivo Senior Onsite 2,000 - 2,500 USD Spring Framework, OOP Chi tiết Mid/Sr Java Developer Rakuten Fintech Vietnam Mid / Senior Onsite Lên đến 3,200 USD Microservices, API, JUnit, JavaEE Chi tiết Java Developer DTN E-Commerce Software Mid Onsite 15 - 25 Triệu VND Java, SQL, Database Chi tiết Java Developers DXC Vietnam Mid Hybrid Thỏa thuận Spring Boot, English, Japanese Chi tiết Java Developer GPBank Mid Onsite Thỏa thuận AWS, CI/CD, Docker Chi tiết Java Developer (Middle) Shinhan Vietnam Finance Mid Onsite Thỏa thuận Java, AngularJS, Front-End Chi tiết Java Developer Ngân Hàng Woori Việt Nam Mid Onsite Thỏa thuận Java Backend, Banking System Chi tiết 📊 Phân Tích Thị Trường Tuyển Dụng Java Tại Việt Nam 1. Nhu cầu & Lĩnh vực hoạt động Tài chính - Ngân hàng (Fintech & Banking): Nhóm ngành này (Shinhan Finance, Woori Bank, GPBank, Rakuten Fintech...) chiếm tỷ lệ tuyển dụng Java lớn nhất do tính bảo mật, ổn định và khả năng xử lý giao dịch quy mô lớn của Java ecosystem. Outsourcing & Product MNCs: Các tập đoàn như DXC, Nakivo liên tục tuyển dụng lập trình viên Java cho các dự án quy mô toàn cầu. 2. Dải lương tham khảo Mid-level (2 - 4 năm kinh nghiệm): ~15,000,000 – 35,000,000 VND (tương đương 700 – 1,500 USD). Senior / Lead (4+ năm kinh nghiệm): ~1,800 – 3,200 USD (tùy thuộc vào khả năng ngoại ngữ và kiến thức chuyên sâu về kiến trúc hệ thống). 3. Kỹ năng được yêu cầu nhiều nhất Framework & Core: Spring Boot, Spring MVC, JavaEE, Hibernate/JPA, OOP. Architecture & Cloud: Microservices, Restful API, Docker, CI/CD, AWS. Database: Oracle DB, PostgreSQL, MySQL. Ngoại ngữ: Tiếng Anh giao tiếp công việc là lợi thế lớn giúp đạt các mức lương >2,000 USD; một số công ty hỗ trợ thêm cho nhân sự biết tiếng Nhật (như DXC). 💡 Lời khuyên cho ứng viên: Nếu bạn muốn ứng tuyển các vị trí Java mức lương cao, hãy tập trung chuẩn bị kỹ về kiến thức Microservices Architecture, Unit Testing / Integration Testing, cùng kỹ năng đọc hiểu và giao tiếp bằng Tiếng Anh. | J20: 46277 | K20: Pass | L20: { "judge_result": "PASS", "judge_status": "PASS", "reason": "The Actual Result successfully provides a list of valid Java Developer job postings in Vietnam and correctly identifies Java-related skills (like Spring Boot, JavaEE, OOP) without confusing Java with JavaScript, fully satisfying the Expected Result." } | M20: Pass | N20: No reference | O20: Kiểm tra khả năng tìm kiếm chính xác các tin tuyển dụng Java Developer và phân biệt Java với JavaScript.
A22: TC-06 | B22: Dễ | C22: Tìm việc cho sinh viên mới tốt nghiệp | D22: Tôi mới tốt nghiệp CNTT. Hãy tìm các tin tuyển dụng phù hợp với người chưa có nhiều kinh nghiệm. | E22: Trả về các tin có yêu cầu kinh nghiệm phù hợp với người mới tốt nghiệp, fresher, trainee nếu có. | I22: Chúc mừng bạn đã hoàn thành chương trình đại học ngành Công nghệ Thông tin (CNTT)! Thị trường IT hiện nay đang có nhiều chương trình Internship, Fresher và Junior dành riêng cho các bạn sinh viên mới tốt nghiệp hoặc chuẩn bị ra trường để tích lũy kinh nghiệm thực tế. Dưới đây là danh sách các cơ hội việc làm phù hợp cùng với phân tích tổng quan về thị trường dành cho ứng viên mới bắt đầu sự nghiệp IT. 📋 Danh Sách Tin Tuyển Dụng Dành Cho Fresher / Intern / Junior Vị trí Công ty Cấp bậc Mô hình Mức trợ cấp / Lương Kỹ năng chính Link ứng tuyển Software Developer (Fresher/Junior) Netcompany Fresher Onsite Thỏa thuận Java, English Ứng tuyển Internship/ Fresher Web Developer ZIGExN VeNtura Intern / Fresher Onsite 130 - 150 USD (~3 - 3.8tr) PHP, ReactJS, CSS Ứng tuyển Junior Web Developer Motorist Pte Ltd Junior Onsite Thỏa thuận Ruby on Rails, ReactJS, VueJS Ứng tuyển Intern Fullstack (AI & Automation) IVC (ISB Vietnam) Intern Onsite 150 - 400 USD (~3.8 - 10tr) Node.js, AI, English Ứng tuyển AI-Native Full-Stack Developer Intern Icon Consulting Group Intern Hybrid 200 - 250 USD (~5 - 6.3tr) Node.js, MongoDB, AI Ứng tuyển Java Developer Intern 8Seneca Intern Onsite 3,000,000 VND Java, MySQL, Git Ứng tuyển Full-stack Developer Intern (AI Prompting) Innotech Vietnam Intern Onsite Thỏa thuận TypeScript, HTML, English Ứng tuyển [Internship] Dev, QA, BA, UI/UX APA Tech Intern Onsite Thỏa thuận Dev/QA/BA/UI-UX, English Ứng tuyển Intern IT Help Desk / IT System Mercatus Intern Onsite 100 - 200 USD (~2.5 - 5tr) System Admin, Network Ứng tuyển 📊 Phân Tích Thị Trường Tuyển Dụng Cho Người Mới Bắt Đầu 1. Mức Trợ Cấp & Lương Khởi Điểm Thực tập sinh (Internship): Trợ cấp phổ biến dao động từ 3,000,000 - 10,000,000 VND/tháng (tương đương 130 - 400 USD), tùy thuộc vào năng lực tiếng Anh và mảng công nghệ. Mới tốt nghiệp / Fresher: Mức lương khởi điểm phổ biến ở mức 8,000,000 - 15,000,000 VND/tháng đối với các công ty trong nước và doanh nghiệp Outsource/Product nước ngoài. Lập trình viên Junior (0 - 2 năm kinh nghiệm): Mức lương trung bình từ 12,000,000 - 22,000,000 VND/tháng (tương đương 500 - 900 USD). 2. Các Xu Hướng & Kỹ Năng Được Tìm Kiếm Nhiều Nhất Ngôn ngữ cốt lõi: Java, JavaScript/TypeScript (Node.js, ReactJS/VueJS), Python và PHP vẫn giữ vị trí chủ đạo trong các bài test tuyển dụng Fresher. Tích hợp AI & Automation: Ngày càng nhiều doanh nghiệp tuyển chọn Intern/Fresher có hiểu biết cơ bản về ứng dụng AI (AI Prompting, LLM APIs, Automation Workflow). Ngoại ngữ (Tiếng Anh / Tiếng Pháp): Là lợi thế cạnh tranh hàng đầu. Các công ty như Netcompany, ISB Vietnam hay Capgemini thường ưu tiên tuyển chọn ứng viên giao tiếp tiếng Anh tốt hoặc biết thêm ngoại ngữ thứ hai. 💡 Lời Khuyên Ứng Tuyển Dành Cho Lập Trình Viên Mới Ra Trường Chuẩn bị Portfolio / Project cá nhân: Nhà tuyển dụng rất chú trọng vào sản phẩm thực tế (đồ án tốt nghiệp, pet projects trên GitHub). Hãy chuẩn bị kỹ giải thích về kiến trúc project và công nghệ bạn đã sử dụng. Nắm chắc nền tảng (Computer Science Fundamentals): Với vị trí Fresher/Junior, các câu hỏi phỏng vấn thường tập trung vào Cấu trúc dữ liệu & Giải thuật, OOP, Cơ sở dữ liệu (SQL), Git và HTTP/RESTful APIs. Tự tin ứng tuyển vị trí đòi hỏi 1 năm kinh nghiệm: Nhiều vị trí ghi "Junior" hoặc yêu cầu 1 năm kinh nghiệm nhưng vẫn cởi mở đón nhận ứng viên Fresher xuất sắc có đồ án ấn tượng và khả năng tư duy logic tốt. | J22: 46277 | K22: Pass | L22: { "judge_result": "PASS", "judge_status": "PASS", "reason": "The Actual Result successfully provides a list of job postings specifically tailored for recent graduates, including Intern, Fresher, and Junior positions, fully satisfying the Expected Result and the purpose of the test case." } | M22: Pass | N22: No reference | O22: Kiểm tra khả năng tìm kiếm các tin tuyển dụng phù hợp với ứng viên mới tốt nghiệp hoặc có ít kinh nghiệm.
A24: TC-07 | B24: Dễ | C24: Xác định công nghệ trong tin tuyển dụng | D24: Trong các tin tuyển dụng Backend Developer, những công nghệ nào thường được yêu cầu? | E24: Tổng hợp các công nghệ được đề cập trong những tin tuyển dụng được truy xuất. Phân biệt công nghệ, ngôn ngữ lập trình và công cụ nếu có thể. Không khẳng định “phổ biến nhất” nếu không có đủ dữ liệu thống kê. | I24: Dựa trên dữ liệu phân tích từ thị trường tuyển dụng CNTT hiện tại, các yêu cầu kỹ thuật đối với vị trí Backend Developer thường tập trung vào các nhóm công nghệ cốt lõi dưới đây: 📊 Tổng Quan Các Kỹ Năng & Công Nghệ Được Yêu Cầu Nhiều Nhất Phân loại Công nghệ / Kỹ năng phổ biến Tỷ lệ / Mức độ phổ biến Ngôn ngữ lập trình Backend Java, Python, Node.js (JavaScript/TypeScript), .NET Core, Go (Golang), PHP Rất cao Cơ sở dữ liệu (Database) SQL (PostgreSQL, MySQL, MariaDB), Redis (Cache) Phổ biến nhất (~9.4%) Kiến trúc hệ thống Microservices Architecture, RESTful API, GraphQL, Design Patterns Rất cao (~8.4%) Cloud & DevOps AWS, Docker, CI/CD (Jenkins, GitLab CI) Tăng trưởng mạnh (~8.4%) Message Queue / Event Stream Apache Kafka, RabbitMQ, Pub/Sub Trung bình - Cao Ngoại ngữ & Ngoại vi Tiếng Anh giao tiếp/đọc tài liệu Cao (~8.9%) 🛠 Chi Tiết Phân Loại Công Nghệ 1. Ngôn ngữ lập trình & Framework chính Thị trường Backend Việt Nam hiện đang chia thành một số Stack công nghệ chính: Java Stack: Java đi kèm Spring Boot / Spring MVC, phù hợp cho các hệ thống lớn như ngân hàng, Fintech, eCommerce. JavaScript / TypeScript Stack: Node.js (ExpressJS, NestJS), phù hợp cho ứng dụng thời gian thực (real-time), khởi nghiệp và dự án có quy mô mở rộng linh hoạt. Python Stack: Python (Django, FastAPI), được ưu chuộng mạnh mẽ trong các hệ thống xử lý dữ liệu, tích hợp AI/ML và sản phẩm SaaS. .NET Stack: C# / .NET Core, được các tập đoàn và doanh nghiệp sử dụng phổ biến cho các hệ thống doanh nghiệp vừa và lớn. Go (Golang): Thường được yêu cầu ở các vị trí Senior cho các hệ thống Microservices đòi hỏi hiệu năng cực cao và khả năng xử lý đồng thời lớn. 2. Quản trị Cơ sở dữ liệu (Database & Caching) Relational Database (RDBMS): PostgreSQL và MySQL là 2 cơ sở dữ liệu quan hệ được yêu cầu nhiều nhất. Kỹ năng viết và tối ưu hóa truy vấn SQL là bắt buộc đối với mọi Backend Developer. NoSQL & Cache: Redis thường xuyên xuất hiện trong các tin tuyển dụng để xử lý bộ nhớ đệm (caching), quản lý session và tối ưu tốc độ phản hồi. 3. Kiến trúc Hệ thống & API Design RESTful API & GraphQL: Kỹ năng thiết kế, phát triển và chuẩn hóa API để tích hợp với Frontend và ứng dụng Mobile. Microservices Architecture: Xây dựng hệ thống phân tán thay cho kiến trúc Monolithic truyền thống. Nguyên lý thiết kế: Áp dụng OOP, SOLID, Design Patterns để đảm bảo mã nguồn dễ bảo trì và mở rộng. 4. Cloud, Containerization & DevOps Containerization: Docker là kỹ năng gần như bắt buộc để chuẩn hóa môi trường phát triển và triển khai. Nền tảng Cloud: AWS (Amazon Web Services) là đám mây được yêu cầu phổ biến nhất. CI/CD & Automation: Sử dụng Jenkins, GitLab CI để tự động hóa quy trình kiểm thử và triển khai ứng dụng. Message Queue: Apache Kafka, RabbitMQ xử lý giao tiếp bất đồng bộ giữa các dịch vụ trong kiến trúc Microservices. 💡 Lời Khuyên Định Hướng Cho Lập Trình Viên Backend Nắm vững 1 Ngôn ngữ cốt lõi + Framework đi kèm: Hãy làm chủ hoàn toàn một trong các Stack chính (như Java + Spring Boot hoặc Node.js/TypeScript hoặc Python + FastAPI). Thành thạo SQL & Thiết kế CSDL: Hiểu rõ cách đánh Index, tối ưu Query và thiết kế Data Model chuẩn. Trang bị kiến thức căn bản về DevOps: Đừng bỏ qua kiến thức về Docker, khái niệm CI/CD và hạ tầng Cloud cơ bản (AWS). Nâng cao Ngoại ngữ: Tiếng Anh là lợi thế lớn giúp bạn tiếp cận các mức lương cao hơn (Senior/Lead) và làm việc trong các công ty Outsourcing/Product quốc tế. | J24: 46277 | K24: Pass | L24: { "judge_result": "FAIL", "judge_status": "FAIL", "reason": "The Actual Result violates the negative constraint by explicitly claiming certain technologies are the 'most popular' (phổ biến nhất) and providing specific percentages (e.g., ~9.4%, ~8.4%) without sufficient statistical data or context, indicating hallucinated statistics." } | M24: Fail | N24: No reference | O24: Kiểm tra khả năng trích xuất và tổng hợp các công nghệ được yêu cầu trong các tin tuyển dụng Backend Developer. | P24: Để hạn chế tràn context ra màn hình User. AIJMC chỉ tính toán và trả về kết quả % thay vì giải thích chi tiết lý do và liệt kê danh sách đính kèm
A26: TC-08 | B26: Dễ | C26: Tìm tin tuyển dụng tại Thành phố Hồ Chí Minh | D26: Hãy tìm các tin tuyển dụng CNTT tại Thành phố Hồ Chí Minh. | E26: Trả về các tin có địa điểm làm việc tại Thành phố Hồ Chí Minh hoặc được xác định rõ là tuyển dụng tại khu vực này | I26: Dưới đây là danh sách các cơ hội việc làm CNTT đang tuyển dụng tại Thành phố Hồ Chí Minh, kèm phân tích tổng quan về nhu cầu tuyển dụng và kỹ năng phổ biến tại thị trường này. 📋 Danh Sách Tin Tuyển Dụng IT Tại TP. Hồ Chí Minh Vị trí tuyển dụng Công ty Trình độ (Seniority) Kỹ năng yêu cầu Hình thức Chi tiết / Ứng tuyển DevOps Engineer Central Retail Mid Python, PHP, AWS, GCP, MySQL, Redis, CI/CD, Jenkins, Nginx, Kibana Onsite Xem chi tiết Business Analyst Officer Motorist Pte Ltd Mid Business Analysis, UI/UX, Jira, Trello, Lucidchart, Mock-up Onsite Xem chi tiết QC Lead SSTech Lead Test Case, Acceptance Testing, Security Testing, QA/QC, Postman, Jira Onsite Xem chi tiết Software Project Manager (Japanese/Chinese) Bosch Global Software Technologies Manager Software Architecture, Embedded C, Ngoại ngữ (Tiếng Trung/Nhật) Onsite Xem chi tiết Odoo Developer ILA Vietnam Mid JavaScript, Odoo ERP Onsite Xem chi tiết Chuyên viên Phân tích Nghiệp vụ (BA - CTS) CC1 - Holdings Mid Business Analysis, Figma, Phân tích quy trình Onsite Xem chi tiết Business Analyst (Inventory Forecasting) Chi Doanh Mid Business Analysis, Dự báo hàng tồn kho Onsite Xem chi tiết Test Engineer Ashley GCC VN Mid Automation Testing, SQL Query Writing Onsite Xem chi tiết Nhân viên Kỹ thuật Triển khai & Bảo trì Mạng FPT Telecom Mid (10 - 20 USD/ngày) Hạ tầng viễn thông, Hỗ trợ kỹ thuật, Customer Service Onsite Xem chi tiết Technical Project Manager Hella Vietnam Manager Project Management, Technical Leadership Onsite Xem chi tiết 📊 Phân Tích Nhu Cầu Tuyển Dụng IT Tại TP.HCM Thị trường IT tại TP. Hồ Chí Minh hiện có những đặc điểm nổi bật sau: Đa dạng về vai trò: Nhu cầu tuyển dụng không chỉ tập trung vào lập trình viên (Software Developer) mà mở rộng mạnh mẽ sang các vị trí như Business Analyst (BA), DevOps/Cloud Engineer, Software QA/QC/Testing, và Quản lý dự án (Project Management). Yêu cầu kỹ năng công nghệ cốt lõi: Lập trình & Hạ tầng: Python, JavaScript, SQL, AWS, GCP, Docker/CI-CD. Quản lý & Nghiệp vụ: Jira, Figma, Trello, UI/UX, phân tích quy trình nghiệp vụ (Business Analysis). Ngoại ngữ: Các vị trí quản lý hoặc làm việc cho tập đoàn đa quốc gia (như Bosch, Hella) ưu tiên ứng viên có thêm ngoại ngữ thứ 2 (Tiếng Anh, Tiếng Nhật, Tiếng Trung). Mức độ kinh nghiệm: Phổ biến nhất là cấp độ Mid-level (2-4 năm kinh nghiệm) và các vị trí cấp quản lý (Lead/Manager). Nếu bạn cần tư vấn chi tiết hơn về một vị trí cụ thể hoặc mức lương trung bình cho từng vị trí tại TP.HCM, hãy cho tôi biết! | J26: 46277 | K26: Pass | L26: { "judge_result": "PASS", "judge_status": "PASS", "reason": "The Actual Result successfully provides a list of IT job postings located in Ho Chi Minh City, satisfying all essential requirements of the Expected Result." } | M26: Pass | N26: No reference | O26: Kiểm tra khả năng lọc và truy xuất các tin tuyển dụng CNTT theo địa điểm Thành phố Hồ Chí Minh.
A28: TC-09 | B28: Dễ | C28: Tìm tin tuyển dụng có mức lương | D28: Tìm các tin tuyển dụng CNTT có thông tin về mức lương. | E28: Trả về các tin có mức lương được công bố. Nếu có thể, trình bày mức lương và đơn vị tiền tệ đúng theo dữ liệu. | I28: Sorry, need more steps to process this request. | J28: 46277 | K28: Fail | L28: Bỏ qua Judge Result vì lỗi hiện rõ rệt. Lý do cho việc này là SQL tools trong backend hiện tại chỉ mở rộng cho tìm kiếm kỹ năng | M28: Fail | N28: No reference | O28: Kiểm tra khả năng nhận diện các tin tuyển dụng có công bố thông tin về mức lương và trình bày đúng dữ liệu.
A30: TC-10 | B30: Dễ | C30: Tóm tắt một tin tuyển dụng | D30: Hãy tóm tắt thông tin chính của tin tuyển dụng được cung cấp hoặc truy xuất. | E30: Bản tóm tắt cần nêu được vị trí, công ty, địa điểm, yêu cầu chính, mức lương nếu có và cách ứng tuyển nếu dữ liệu có sẵn. | I30: Dưới đây là tóm tắt tổng hợp các tin tuyển dụng CNTT công khai hạn mức lương (không ở dạng thỏa thuận) được truy xuất từ dữ liệu thị trường mới nhất. 1. Danh sách các vị trí tuyển dụng có thông tin mức lương minh bạch STT Vị trí công việc Công ty Cấp bậc Mức lương Hình thức Kỹ năng yêu cầu chính 1 Lead React Native Developer CÔNG TY TNHH BRIDGETEK VIỆT NAM Lead 70,000,000 - 90,000,000 VND / tháng Onsite React Native, Mobile Architecture 2 Senior Fullstack Developer (AI/Java/Kotlin) CÔNG TY TNHH AU PROFESSIONAL VIETNAM Senior $1,500 - $3,000 USD / tháng Onsite AI, Kotlin, Java, Spring Boot, SQL 3 Middle/Senior Back End Developer (Java) Persol Career Tech Studio Vietnam Senior $1,000 - $1,750 USD / tháng Hybrid Java, Spring, SQL 4 Software Engineer (Java/MongoDB) B2B Commerce (M) Sdn. Bhd. Mid $1,200 USD / tháng Onsite Java, Spring, JSON, MongoDB 5 Optimization Engineer / Data Analyst Công ty Cổ phần Hàng hải Vsico Mid $600 - $1,000 USD / tháng Hybrid Python, C++, Data Analysis 6 Senior Fullstack Dev (Java/Python) ANVUI Senior $30 - $50 USD / giờ Onsite Java, JavaScript, Python, OOP, SQL 2. Chi tiết các cơ hội việc làm nổi bật 🔴 Cấp quản lý / Dẫn dắt kỹ thuật (Lead Level) Vị trí: Lead React Native Developer Doanh nghiệp: CÔNG TY TNHH BRIDGETEK VIỆT NAM Mức lương: 70.000.000 - 90.000.000 VNĐ/tháng Mô hình làm việc: Onsite Đặc điểm: Đòi hỏi năng lực dẫn dắt team, tối ưu hóa ứng dụng di động đa nền tảng với React Native. 🟡 Cấp cao (Senior Level) Vị trí: Senior Fullstack Developer (AI/Java/Kotlin/Spring Boot) Doanh nghiệp: CÔNG TY TNHH AU PROFESSIONAL VIETNAM Mức lương: 1.500 USD - 3.000 USD/tháng (~37.5 - 75 triệu VNĐ) Mô hình làm việc: Onsite Đặc điểm: Kết hợp kỹ năng Fullstack truyền thống (Java/Spring Boot) với ứng dụng Trí tuệ nhân tạo (AI). Vị trí: Middle/Senior Back End Developer (Java) Doanh nghiệp: Persol Career Tech Studio Vietnam Mức lương: 1.000 USD - 1.750 USD/tháng (~25 - 43.7 triệu VNĐ) Mô hình làm việc: Hybrid (Linh hoạt) Đặc điểm: Tập trung phát triển hệ thống Back-end vững chắc với Java Framework và quản trị cơ sở dữ liệu relational SQL. 🟢 Cấp trung (Mid Level) Vị trí: Software Engineer (Java, Spring, JSON, MongoDB) Doanh nghiệp: B2B Commerce (M) Sdn. Bhd. Mức lương: 1.200 USD/tháng (~30 triệu VNĐ) Mô hình làm việc: Onsite Đặc điểm: Yêu cầu kiến thức về MongoDB (NoSQL) và hệ sinh thái Java Spring. Vị trí: Optimization Engineer / Data Analyst (Python/C++) Doanh nghiệp: Công ty cổ phần hàng hải Vsico Mức lương: 600 USD - 1.000 USD/tháng (~15 - 25 triệu VNĐ) Mô hình làm việc: Hybrid Đặc điểm: Thích hợp cho nhân sự định hướng Phân tích dữ liệu & Tối ưu hóa thuật toán bằng Python/C++. 3. Phân tích & Nhận định thị trường Phân bố mức lương theo cấp bậc: Lead / Technical Lead: Dao động từ 3.000 USD - 3.800 USD (70 - 90 triệu VNĐ/tháng). Senior Level: Dao động từ 1.500 USD - 3.000 USD (37.5 - 75 triệu VNĐ/tháng). Mid Level: Dao động từ 600 USD - 1.200 USD (15 - 30 triệu VNĐ/tháng). Xu hướng công nghệ được trả lương cao: AI & Machine Learning Integration: Các vị trí Fullstack hoặc Backend kết hợp năng lực ứng dụng AI/LLM có mức lương nhỉnh hơn rõ rệt (lên tới $3,000/tháng). React Native / Cross-platform Mobile: Vẫn giữ độ hot cao cho cấp bậc Tech Lead. Hệ sinh thái Java (Spring Boot, Microservices): Là khung kỹ thuật nền tảng phổ biến nhất có khoảng lương rõ ràng trên các sàn tuyển dụng. Mô hình làm việc: Các vị trí công khai mức lương hấp dẫn hiện chủ yếu tập trung ở mô hình Onsite và Hybrid. Nếu bạn cần tư vấn sâu hơn về chuẩn bị hồ sơ cho một vị trí cụ thể hoặc so sánh thêm về dải lương của các công nghệ khác (Node.js, DevOps, Data Engineer,...), hãy cho tôi biết! | J30: 46277 | K30: Pass | L30: { "judge_result": "PASS", "judge_status": "PASS", "reason": "The Actual Result satisfies the essential requirements of the Expected Result. Although the AI Agent retrieved and summarized multiple job postings instead of a single one, it successfully extracted the required fields for each posting, including position, company, salary, work model (representing location), and main requirements, without distorting the information." } | M30: Pass | N30: No reference | O30: Kiểm tra khả năng tóm tắt các thông tin chính của một tin tuyển dụng mà không làm sai lệch nội dung nguồn.
A32: TC-11 | B32: Trung bình | C32: Lọc Backend theo Python và Django | D32: Tìm các tin tuyển dụng Backend Developer tại Việt Nam yêu cầu Python và Django. | E32: Chỉ trả về các tin phù hợp với nhóm Backend Developer và có đề cập cả Python lẫn Django trong yêu cầu hoặc mô tả công việc. | I32: Dưới đây là danh sách các cơ hội tuyển dụng Backend Developer (Python/Django) tại thị trường Việt Nam được ghi nhận từ dữ liệu tuyển dụng CNTT mới nhất. 1. Danh sách tin tuyển dụng Python / Django Backend Developer 📌 Các vị trí yêu cầu trực tiếp Django Framework STT Vị trí tuyển dụng Công ty Cấp bậc Mức lương Hình thức Kỹ năng chính Chi tiết / Link 1 Senior Python Developer Prestige Home Senior 30 - 40 triệu VND/tháng Onsite Python, Django, Redis, RESTful API Xem JD 2 Backend Technical Lead (Python/Django & AWS) LHV Software Lead Thỏa thuận Hybrid Python, Django, AWS, SQL, DevOps Xem JD 3 [Đà Nẵng] Senior Full-Stack Developer ONE Tech Stop Vietnam Senior Thỏa thuận Onsite Python, Django, Node.js, Cloud Xem JD 📌 Các vị trí Backend Python liên quan (Flask, FastAPI, Python General) STT Vị trí tuyển dụng Công ty Cấp bậc Mức lương Hình thức Kỹ năng chính Chi tiết / Link 1 Backend Developer (Python / .NET) LizAI Vietnam Junior / Senior $800 - $2,000 Onsite Python, SQL, RESTful API, .NET Xem JD 2 Backend Developer (PHP / Python / SQL) SkyLabVN Mid-level $800 - $1,500 Onsite Python, PHP, SQL, API Xem JD 3 Backend Python Developer GLOBALTECH Mid-level Thỏa thuận Onsite Python, Flask, FastAPI, SQL, Docker Xem JD 4 Lead Python Developer FPT Software Lead Thỏa thuận Onsite Python, Flask, SOLID Principles, Leadership Xem JD 2. Đánh giá nhu cầu thị trường đối với Python Backend Developer Về Framework: Django vẫn là framework phổ biến cho các hệ thống quy mô lớn, ERP, hoặc dự án E-commerce/Real-estate đòi hỏi kiến trúc chuẩn chỉnh và ORM mạnh mẽ. Tuy nhiên, các vị trí mới xuất hiện xu hướng kết hợp hoặc chuyển sang FastAPI và Flask cho kiến trúc Microservices. Mức lương tham chiếu: Junior / Mid-level: Mức phổ biến rơi vào tầm $800 - $1,500/tháng (khoảng 20 - 38 triệu VND). Senior / Tech Lead: Mức lương dao động từ 30 - 40+ triệu VND/tháng ($1,500 - $2,500+ tùy năng lực và khả năng tiếng Anh/Cloud). Kỹ năng bổ trợ thường đi kèm: Database & Cache: PostgreSQL, MySQL, Redis. Cloud & DevOps: AWS, Docker, CI/CD pipeline. API Architecture: RESTful API, GraphQL. Nếu bạn muốn tham khảo thêm về định hướng lộ trình kỹ năng (Career Roadmap) hay chuẩn bị phỏng vấn cho vị trí Python/Django Developer, hãy cho tôi biết nhé! | J32: 46277 | K32: Fail | L32: { "judge_result": "FAIL", "judge_status": "FAIL", "reason": "The Actual Result violates the constraint in the Expected Result which explicitly requires returning ONLY ('Chỉ trả về') jobs that mention BOTH Python and Django. The AI Agent included a section of related Python jobs (using Flask, FastAPI, .NET, PHP) that do not require Django, failing the strict filtering condition." } | M32: Fail | N32: No reference | O32: Kiểm tra khả năng lọc tin tuyển dụng Backend Developer theo đồng thời hai công nghệ Python và Django.
A34: TC-12 | B34: Trung bình | C34: Lọc việc theo địa điểm và hình thức làm việc | D34: Tìm các vị trí Software Engineer tại Thành phố Hồ Chí Minh có hình thức làm việc remote hoặc hybrid. | E34: Trả về các tin phù hợp với vị trí Software Engineer, địa điểm Thành phố Hồ Chí Minh và có hình thức remote hoặc hybrid được nêu rõ. | I34: Dưới đây là danh sách các cơ hội tuyển dụng Software Engineer / Developer tại khu vực Thành phố Hồ Chí Minh (và làm việc từ xa trên toàn quốc) có hình thức làm việc Hybrid (kết hợp) hoặc Remote (từ xa) được tổng hợp từ dữ liệu tuyển dụng CNTT mới nhất. 1. Danh sách vị trí Software Engineer (Remote / Hybrid) STT Vị trí tuyển dụng Công ty Cấp bậc Hình thức Mức lương Kỹ năng trọng tâm Chi tiết / Đăng ký 1 Software Engineer Deliveree On-Demand Logistics Mid Hybrid Thỏa thuận AWS, Prompt Engineering, Cloud Xem chi tiết 2 Remote AI Full-Stack Eng Xenia Tech Mid Remote Lên đến $4,500 USD ReactJS, AI Integration, MongoDB Xem chi tiết 3 Backend Technical Lead (Python/Django & AWS) LHV Software Lead Hybrid Thỏa thuận Python, Django, AWS, DevOps, SQL Xem chi tiết 4 Remote - AI/NLP Engineer / Algorithm Engineer Cazoodle Mid Remote Thỏa thuận Machine Learning, NLP, Algorithm Xem chi tiết 5 Frontend Developer (Angular) Oivan Mid Hybrid Thỏa thuận Angular, CSS/CSS3, English Xem chi tiết 6 Full-Stack Developer (React/Next.js + AI) Nex Consulting Group Mid Remote / Hybrid Thỏa thuận React, Next.js, AI Features Xem chi tiết 2. Điểm nổi bật & Phân tích cơ hội tuyển dụng 🔹 1. Xu hướng tích hợp AI (AI-Enabled Software Engineer) Các vị trí Remote/Hybrid hiện nay ưu tiên tuyển dụng các kỹ sư có năng lực tích hợp AI / LLM / Prompt Engineering (ví dụ: Xenia Tech, Deliveree, Cazoodle). Mức lương cho các vị trí Remote chất lượng cao có tích hợp công nghệ AI có thể đạt tới $4,500 USD/tháng. 🔹 2. Yêu cầu Tiếng Anh tốt Hầu hết các vị trí làm việc Remote hoặc Hybrid xuất phát từ các công ty đa quốc gia hoặc công ty phát triển sản phẩm toàn cầu (như Deliveree, Xenia Tech, Oivan), đòi hỏi ứng viên giao tiếp Tiếng Anh thành thạo (trình độ C1 hoặc tương đương). 🔹 3. Tech Stack phổ biến Backend: Python (Django), Node.js, Java, Cloud (AWS/GCP), Database (MongoDB/PostgreSQL). Frontend: ReactJS, Next.js, Angular, TypeScript. 3. Lời khuyên cho Ứng viên Chuẩn bị Hồ sơ & GitHub / Portfolio: Khi ứng tuyển Remote, hồ sơ thể hiện khả năng tự quản lý công việc (Self-management) và sản phẩm thực tế (Portfolio/GitHub) là yếu tố quyết định. Nâng cao năng lực Tiếng Anh giao tiếp: Đảm bảo bạn có khả năng trao đổi công việc, tham gia Daily Standup bằng tiếng Anh tốt. Cập nhật công cụ AI: Làm quen với các AI Coding Assistants (GitHub Copilot, Cursor) và tích hợp API của các mô hình AI lớn vào dự án. | J34: 46277 | K34: Pass | L34: { "judge_result": "PASS", "judge_status": "PASS", "reason": "The Actual Result successfully provides a list of Software Engineer (and related developer) positions that explicitly mention 'Remote' or 'Hybrid' work models. It correctly filters the jobs for candidates in Ho Chi Minh City, noting that remote roles are available nationwide, which fulfills the expected constraints." } | M34: Pass | N34: No reference | O34: Kiểm tra khả năng xử lý đồng thời các điều kiện về vị trí, địa điểm và hình thức làm việc remote hoặc hybrid.
A36: TC-13 | B36: Trung bình | C36: So sánh hai tin tuyển dụng | D36: So sánh hai tin tuyển dụng Backend Developer mà bạn tìm được về công nghệ, kinh nghiệm, địa điểm và mức lương. | E36: Lập bảng hoặc trình bày so sánh theo cùng các tiêu chí. Chỉ sử dụng thông tin có trong hai tin. | I36: Dưới đây là bảng và phân tích so sánh chi tiết giữa 2 vị trí tuyển dụng Backend Developer (Python/Django) đại diện từ thị trường tuyển dụng CNTT tại Việt Nam: 📊 Bảng so sánh tổng quan Tiêu chí Vị trí 1: Senior Python Developer Vị trí 2: Backend Technical Lead (Python/Django & AWS) Công ty Prestige Home LHV Software Cấp bậc (Seniority) Senior Lead / Technical Lead Kỹ năng & Công nghệ Python, Django, RESTful API, Redis Python, Django, AWS, Cloud Architecture, SQL, DevOps Hình thức làm việc Onsite (Tại văn phòng) Hybrid (Kết hợp Remote & Văn phòng) Kinh nghiệm yêu cầu 3 – 5 năm kinh nghiệm về Python/Django 5+ năm kinh nghiệm, kỹ năng Leadership & System Design Mức lương 30 – 40 triệu VNĐ/tháng Thỏa thuận theo năng lực (Benchmark: 45 – 70+ triệu VNĐ) 🔍 Phân tích chi tiết các tiêu chí 1. Kỹ năng & Công nghệ (Tech Stack) Senior Python Developer (Prestige Home): Trọng tâm: Phát triển ứng dụng Web Backend chuyên sâu với Python & Django Framework. Công nghệ kèm theo: Thiết kế & tối ưu hóa RESTful API, sử dụng Redis để lưu trữ cache và tối ưu hiệu năng xử lý dữ liệu. Phạm vi công việc: Tập trung vào viết mã nguồn chất lượng (clean code), xây dựng các tính năng mới và tối ưu hóa truy vấn cơ sở dữ liệu. Backend Technical Lead (LHV Software): Trọng tâm: Không chỉ dừng lại ở code với Python/Django, mà mở rộng sang AWS Cloud Architecture và DevOps. Công nghệ kèm theo: Quản trị cơ sở dữ liệu SQL, hạ tầng điện toán đám mây AWS (EC2, S3, RDS, Lambda), thiết lập đường ống CI/CD. Phạm vi công việc: Quyết định kiến trúc hệ thống (System Architecture), đảm bảo tính mở rộng (Scalability), bảo mật và định hướng kỹ thuật cho toàn nhóm. 2. Cấp bậc & Yêu cầu kinh nghiệm Vị trí Senior (Prestige Home): Yêu cầu từ 3 – 5 năm kinh nghiệm thực chiến làm Backend với Python. Đòi hỏi khả năng làm việc độc lập cao, giải quyết các sự cố kỹ thuật phức tạp trong module phụ trách. Vị trí Technical Lead (LHV Software): Yêu cầu từ 5+ năm kinh nghiệm, trong đó có kinh nghiệm quản lý nhóm kỹ thuật hoặc làm Trưởng nhóm (Tech Lead). Yêu cầu kỹ năng mềm cao: Quản lý dự án, phân chia công việc, review code, đào tạo/mentoring cho lập trình viên Junior/Mid-level. 3. Hình thức làm việc & Địa điểm Prestige Home (Onsite): Làm việc trực tiếp tại văn phòng công ty. Phù hợp với nhân sự thích môi trường tương tác trực tiếp, trao đổi nhanh chóng với team product và vận hành. LHV Software (Hybrid): Mô hình linh hoạt giữa làm việc từ xa (Remote) và lên văn phòng định kỳ. Phù hợp với nhân sự ưu tiên sự linh hoạt về thời gian và môi trường làm việc cân bằng (Work-Life Balance). 4. Mức lương & Đãi ngộ Senior Level (30 - 40M VNĐ/tháng): Mức lương định giá rõ ràng, thuộc khung thu nhập cạnh tranh cho cấp bậc Senior Developer tại thị trường Việt Nam (tương đương khoảng $1,200 - $1,600 USD/tháng). Tech Lead Level (Lương thỏa thuận): Mức lương linh hoạt dựa trên năng lực quản lý và quy mô hệ thống từng đảm nhiệm. Thông thường, vị trí Lead Python/AWS có dải lương từ 45 – 70+ triệu VNĐ/tháng ($1,800 - $3,000 USD/tháng). 💡 Nhận xét & Lời khuyên cho Ứng viên Nếu bạn muốn tập trung phát triển chuyên môn kỹ thuật (Individual Contributor): Vị trí Senior Python Developer tại Prestige Home là lựa chọn phù hợp để rèn luyện chuyên sâu về Django, tối ưu API và caching. Nếu bạn hướng tới định hướng quản lý kỹ thuật & kiến trúc hệ thống: Vị trí Backend Technical Lead tại LHV Software giúp bạn mở rộng năng lực sang Cloud (AWS), DevOps và kỹ năng lãnh đạo team, đồng thời hưởng chính sách làm việc Hybrid linh hoạt. | J36: 46277 | K36: Pass | L36: { "judge_result": "FAIL", "judge_status": "FAIL", "reason": "The Actual Result violates the strict constraint in the Expected Result which requires using ONLY information present in the two job postings ('Chỉ sử dụng thông tin có trong hai tin'). The AI Agent introduced external knowledge by providing a market salary benchmark ('Benchmark: 45 – 70+ triệu VNĐ') for a position where the salary was listed as negotiable." } | M36: Fail | N36: No reference | O36: Kiểm tra khả năng đối chiếu và tổng hợp thông tin từ hai tin tuyển dụng theo các tiêu chí được yêu cầu. | P36: Về bản chất là AIJMC định hướng là trả về thông tin bổ trợ từ yêu cầu gốc. Ví dụ: Trả lời câu hỏi người dùng ---> Bổ trợ chứ không đi lạc so với yêu cầu.
A38: TC-14 | B38: Trung bình | C38: Lọc theo mức kinh nghiệm và công nghệ | D38: Tìm các tin tuyển dụng Junior Backend Developer yêu cầu Python, có kinh nghiệm không quá 2 năm. | E38: Trả về các tin đáp ứng đồng thời cấp độ Junior, công nghệ Python và điều kiện kinh nghiệm không quá 2 năm. | I38: Dưới đây là danh sách các vị trí tuyển dụng Junior Backend Developer yêu cầu Python (phù hợp với ứng viên có dưới 2 năm kinh nghiệm) cùng thông tin chi tiết và bức tranh tổng quan về thị trường. 📋 Danh sách cơ hội tuyển dụng Junior Python Backend Developer STT Vị trí tuyển dụng Công ty Cấp bậc Hình thức Mức lương Kỹ năng chính Chi tiết / Ứng tuyển 1 Junior Backend Developer (Python / APIs) QualityRealty Junior Hybrid Thỏa thuận Python, APIs, PostgreSQL, Git Link ứng tuyển 2 Backend Developer (Python / .NET) LizAI Vietnam Junior / Mid Onsite $800 - $2,000 Python, .NET, SQL, REST API Link ứng tuyển 3 Backend Python Internship / Fresher LizAI Vietnam Intern / Fresher Onsite Thỏa thuận Python, SQL, Basic Backend Link ứng tuyển 🔍 Chi tiết các vị trí nổi bật 1. Junior Backend Developer (Python / APIs) – QualityRealty Công ty: QualityRealty Hình thức làm việc: Hybrid (Kết hợp làm tại văn phòng & từ xa) Yêu cầu kinh nghiệm: < 2 năm (Cấp bậc Junior) Kỹ năng cốt lõi: Lập trình Python backend (Django / FastAPI / Flask). Thiết kế & phát triển RESTful APIs. Quản trị và tối ưu cơ sở dữ liệu relational (PostgreSQL). Quản lý mã nguồn với Git. 2. Backend Developer (Python / .NET) – LizAI Vietnam Công ty: LizAI Vietnam Hình thức làm việc: Onsite (Làm việc trực tiếp tại văn phòng) Mức lương: $800 - $2,000 USD/tháng Yêu cầu kinh nghiệm: Chấp nhận Junior có nền tảng vững chắc đến Mid-level. Kỹ năng cốt lõi: Nền tảng Python và/hoặc C# (.NET Core). Làm việc với SQL, cơ sở dữ liệu quan hệ và kiến trúc dịch vụ microservices. 📊 Tham chiếu mức lương & Yêu cầu kỹ năng cho vị trí Junior Python Dựa trên dữ liệu phân tích thị trường CNTT hiện tại cho cấp bậc Junior Python Developer: Khung lương phổ biến: $500 – $1,200 USD/tháng (tương đương ~12 - 30 triệu VND/tháng) tùy thuộc vào năng lực thực tế và quy mô doanh nghiệp. Các kỹ năng được tuyển dụng phổ biến nhất: Framework Backend: FastAPI, Django, Flask. Database: PostgreSQL, MySQL, Redis. Công cụ & Quy trình: Git, Docker, RESTful API design. Tiếng Anh: Tiếng Anh giao tiếp hoặc đọc hiểu tài liệu chuyên ngành tốt là lợi thế lớn giúp đạt mức lương $1,000+. 💡 Lời khuyên cho ứng viên Junior (< 2 năm kinh nghiệm): Tập trung vào Project thực tế: Chuẩn bị sẵn các dự án cá nhân hoặc sản phẩm đã hoàn thành có sử dụng FastAPI/Django và deploy lên các nền tảng cloud (như AWS, Heroku, Render) kèm tài liệu API (Swagger/OpenAPI). Nắm chắc cơ sở dữ liệu: Hiểu rõ cách tối ưu truy vấn SQL, indexing và thiết kế DB schema cho ứng dụng Python. | J38: 46277 | K38: Pass | L38: { "judge_result": "PASS", "judge_status": "PASS", "reason": "The Actual Result successfully filtered and returned job postings that meet the specified conditions: targeting the Junior level, requiring Python technology, and fitting the constraint of having no more than 2 years of experience." } | M38: Pass | N38: No reference | O38: Kiểm tra khả năng lọc tin tuyển dụng theo cấp độ Junior, công nghệ Python và giới hạn kinh nghiệm.
A40: TC-15 | B40: Trung bình | C40: Tổng hợp kỹ năng theo vị trí | D40: Dựa trên các tin tuyển dụng Frontend Developer, hãy tổng hợp các kỹ năng kỹ thuật được yêu cầu và số lượng tin đề cập đến từng kỹ năng. | E40: Tổng hợp được các kỹ năng từ tập tin tuyển dụng được sử dụng. Số lượng phải có căn cứ từ dữ liệu thực tế, không tự tạo số liệu. | I40: Dựa trên dữ liệu tổng hợp từ thị trường tuyển dụng CNTT đối với vị trí Frontend Developer, dưới đây là bảng thống kê chi tiết các kỹ năng kỹ thuật được yêu cầu phổ biến nhất và tỷ lệ xuất hiện của chúng trong các tin tuyển dụng. 📊 Bảng tổng hợp Kỹ năng Kỹ thuật Frontend được yêu cầu nhiều nhất STT Kỹ năng / Công nghệ Phân loại Số lượng tin đề cập Tỷ lệ xuất hiện (%) 1 ReactJS Framework / Library 18 20.45% 2 TypeScript Programming Language 16 18.18% 3 NextJS Framework (Fullstack/SSR) 11 12.50% 4 CI/CD Methodology / DevOps 11 12.50% 5 JavaScript Programming Language 10 11.36% 6 PostgreSQL Database 9 10.23% 7 Microservices Architecture 9 10.23% 8 Git / GitHub Version Control 7 7.95% 9 AWS Cloud Platform 7 7.95% 10 CSS / CSS3 Core Web Technology 7 7.95% 11 HTML5 Core Web Technology 6 6.82% 12 NodeJS Backend / Runtime 6 6.82% 13 MySQL Database 6 6.82% 14 AI Integration Data & Emerging Tech 6 6.82% 🔍 Phân tích chi tiết theo nhóm công nghệ 1. Thư viện & Framework Frontend (UI Libraries & Frameworks) ReactJS (20.45%): Đứng đầu danh sách yêu cầu. Phụ thuộc lớn nhất của các doanh nghiệp hiện nay khi xây dựng Single Page Applications (SPA). NextJS (12.50%): Sự gia tăng mạnh mẽ của Server-Side Rendering (SSR) và Static Site Generation (SSG) giúp NextJS trở thành kỹ năng mở rộng bắt buộc với các React Developer muốn tiến xa hơn. 2. Ngôn ngữ lập trình (Programming Languages) TypeScript (18.18%): Đã trở thành tiêu chuẩn công nghiệp (Industry Standard) đối với hầu hết các dự án Frontend quy mô vừa và lớn nhờ khả năng kiểm soát kiểu dữ liệu mạnh mẽ, giảm thiểu lỗi runtime. JavaScript (11.36%): Nền tảng cốt lõi luôn được kiểm tra trong các buổi phỏng vấn kỹ thuật (ES6+, Asynchronous IO, Closures, Event Loop...). 3. Kỹ năng Web cơ bản & Quản lý nguồn mã (Core Web & Version Control) HTML5 & CSS/CSS3 (6.82% – 7.95%): Yêu cầu nền tảng cho việc tạo giao diện responsive, tối ưu giao diện UI/UX và tương thích đa trình duyệt. Git/GitHub (7.95%): Công cụ quản lý mã nguồn không thể thiếu trong quy trình làm việc nhóm chuyên nghiệp. 4. Xu hướng "Fullstack Expansion" & Infrastructure NodeJS (6.82%) & REST API: Tuyển dụng Frontend hiện đại thường đòi hỏi ứng viên hiểu về cách tích hợp API, hiểu cơ chế hoạt động của Backend Server hoặc viết được BFF (Backend-For-Frontend). CI/CD (12.50%) & AWS (7.95%): Doanh nghiệp kỳ vọng Lập trình viên Frontend tự động hóa được quy trình build, test và triển khai ứng dụng lên nền tảng đám mây. AI Integration (6.82%): Xu hướng tích hợp các tính năng AI (LLM APIs, Generative UI, Chatbot) vào ứng dụng Frontend đang tăng nhanh. 💡 Đánh giá & Lời khuyên định hướng sự nghiệp Bộ kỹ năng cốt lõi (Must-Have Stack): HTML/CSS + JavaScript (ES6+) + ReactJS + TypeScript + Git. Đây là gói kỹ năng tối thiểu để đáp ứng >70% cơ hội việc làm thị trường hiện tại. Điểm cộng tạo thế mạnh cạnh tranh (Differentiators): Trang bị thêm NextJS, kiến thức CI/CD cơ bản, và khả năng làm việc với REST APIs / Node.js sẽ giúp bạn ứng tuyển thành công vào các vị trí Senior hoặc các công ty Product/Outsourcing trả mức lương cao. | J40: 46277 | K40: Fail | L40: { "judge_result": "FAIL", "judge_status": "FAIL", "reason": "The Actual Result violates the constraint 'không tự tạo số liệu' (do not fabricate data) in the Expected Result. Since no job postings were provided in the input, the AI Agent invented the statistics (e.g., ReactJS 18 postings, TypeScript 16 postings) instead of acknowledging the lack of data." } | M40: Fail | N40: No reference | O40: Kiểm tra khả năng tổng hợp và thống kê tần suất xuất hiện của các kỹ năng kỹ thuật trong tập tin tuyển dụng.
A42: TC-16 | B42: Trung bình | C42: Tìm việc theo nhiều công nghệ | D42: Tìm các tin tuyển dụng yêu cầu React ở Frontend và Node.js ở Backend. | E42: Trả về các tin phù hợp với điều kiện công nghệ. Cần phân biệt tin yêu cầu cả React và Node.js với tin chỉ yêu cầu một trong hai công nghệ. | I42: Dưới đây là danh sách các tin tuyển dụng Full-Stack / Software Developer yêu cầu kết hợp bộ đôi kỹ năng React (Frontend) và Node.js (Backend) đang có nhu cầu tuyển dụng trên thị trường. 📋 Danh sách vị trí tuyển dụng React + Node.js STT Vị trí tuyển dụng Công ty Cấp bậc Hình thức Mức lương Kỹ năng chính Chi tiết / Ứng tuyển 1 Senior Full-stack Developer (NodeJS, ReactJS, .NET) Restaff – House Of Norway Senior Hybrid 1,300 - 2,200 USD NodeJS, ReactJS, JavaScript, MongoDB Xem chi tiết 2 FULL-STACK DEVELOPER (NodeJS/NextJS) Công ty Cổ phần Smileviet Mid Onsite 1,500 - 2,000 USD ReactJS, NodeJS, NextJS, GraphQL, AI Xem chi tiết 3 NodeJS Dev (+ ReactJS/NestJS/NextJS) Offspring Digital Viet Nam Mid Onsite 1,100 - 2,000 USD NodeJS, ReactJS, NestJS, NextJS Xem chi tiết 4 Full-Stack ReactJS / NodeJS Developer FPT Software HN Mid Onsite Thỏa thuận ReactJS, NodeJS, PostgreSQL, MongoDB, Microservices Xem chi tiết 5 Full-Stack ReactJS / NodeJS Developer FPT Software Mid Onsite Thỏa thuận ReactJS, NodeJS, PostgreSQL, Microservices Xem chi tiết 6 Fullstack Developer (NodeJS/ReactJS) SOFTFLEX LLC CO.,LTD Mid Onsite Thỏa thuận ReactJS, NodeJS, PostgreSQL, Google Cloud Xem chi tiết 7 Senior Fullstack Engineer CADDi Vietnam Senior Onsite Thỏa thuận NodeJS, NextJS/React, PostgreSQL, Rust, Microservices Xem chi tiết 💡 Phân tích & Nhận xét về yêu cầu kỹ thuật bộ đôi React + Node.js Xu hướng Fullstack JavaScript / TypeScript (MERN / PERN Stack): Sự kết hợp giữa React ở Frontend và Node.js ở Backend là một trong những hệ sinh thái phổ biến nhất hiện nay nhờ tính nhất quán về ngôn ngữ (JavaScript/TypeScript) trên cả hai phía. Các framework nâng cao đi kèm thường được đề cập bao gồm Next.js (Frontend / SSR) và NestJS (Backend architecture). Cơ sở dữ liệu & Công nghệ phụ trợ đi kèm: Database: PostgreSQL và MongoDB là hai hệ quản trị dữ liệu xuất hiện nhiều nhất cùng bộ kỹ năng này. Architecture: Kiến thức về Microservices, GraphQL, và RESTful APIs là các điểm cộng quan trọng cho cấp bậc Mid/Senior. Phân khúc Mức lương: Cấp bậc Mid-level (2-4 năm kinh nghiệm) dao động phổ biến từ 1,100 – 2,000 USD/tháng. Cấp bậc Senior-level (từ 4-5 năm kinh nghiệm trở lên) đạt ngưỡng từ 1,300 – 2,200+ USD/tháng. | J42: 46277 | K42: Fail | L42: { "judge_result": "FAIL", "judge_status": "FAIL", "reason": "The Actual Result fails to satisfy the Expected Result because it only lists job postings requiring both React and Node.js, completely missing the requirement to distinguish between postings requiring both technologies and postings requiring only one of the two." } | M42: Fail | N42: No reference | O42: Kiểm tra khả năng xử lý yêu cầu tìm kiếm dựa trên nhiều công nghệ thuộc các nhóm Frontend và Backend.
A44: TC-17 | B44: Trung bình | C44: Phân tích mức lương theo vị trí | D44: Hãy tổng hợp khoảng lương được công bố cho vị trí Backend Developer trong các tin tuyển dụng đã tìm được. | E44: Trình bày các khoảng lương có trong dữ liệu, nêu số lượng tin được sử dụng nếu xác định được và không gộp các đơn vị tiền tệ hoặc khoảng lương không tương đồng một cách sai lệch. Nếu dữ liệu ít, phải nêu rõ giới hạn. | I44: Dựa trên dữ liệu thu thập từ các tin tuyển dụng cho vị trí Backend Developer trên thị trường CNTT Việt Nam, dưới đây là tổng hợp chi tiết về khoảng lương được công bố phân theo từng tin tuyển dụng, cấp bậc chuyên môn và công nghệ yêu cầu. 📊 Bảng tổng hợp Mức lương theo Tin tuyển dụng Backend Developer STT Vị trí tuyển dụng Công ty Cấp bậc Công nghệ chính Khoảng lương công bố Đơn vị 1 Senior Backend Developer (Golang) VISION Advisory & Analytics Senior Golang, PostgreSQL, Docker, Linux 1,600 – 3,500 USD/tháng 2 Backend Developer (Python/.Net) LizAI Vietnam Junior - Senior Python, .NET, SQL 800 – 2,000 USD/tháng 3 Back-End Developer (NodeJS) Công ty Cổ phần Smileviet Mid NodeJS, MySQL 800 – 1,200 USD/tháng 4 Backend Developer Creative Force Mid .NET Core, Microservices, AWS, AI 80,000,000 VND/tháng 5 DB2402 - PHP Backend Developer LikeLion Vietnam Mid PHP, MySQL, API 17 USD/giờ 6 Backend Developer Pinetree Securities Corporation Mid Java, Spring, Microservices, Kafka Thỏa thuận (0) VND 7 Back-end Developer CÔNG TY TNHH PHẦN MỀM NAM LONG Mid OOP, Backend Thỏa thuận (0) VND 8 Back-end Developer CÔNG TY TNHH GS 25 VIETNAM Mid Python, Java Thỏa thuận (0) VND 📈 Phân tích & Tổng hợp Khoảng lương theo Cấp bậc & Công nghệ 1. Phân theo Đơn vị Tiền tệ & Cấp bậc Mức lương USD (Các công ty nước ngoài / Sản phẩm quốc tế): Junior / Early Mid: $800 – $1,200 USD/tháng (tương đương ~20 – 30 triệu VND/tháng). Mid-level: $1,200 – $2,000 USD/tháng (tương đương ~30 – 50 triệu VND/tháng). Senior Level: $1,600 – $3,500 USD/tháng (tương đương ~40 – 88 triệu VND/tháng). Mức lương VND (Doanh nghiệp nội địa / Tập đoàn lớn): Mid - Senior: Ghi nhận mức lương công bố lên tới 80.000.000 VND/tháng đối với các vị trí yêu cầu chuyên sâu về kiến trúc phần mềm, AWS cloud, microservices và AI tích hợp. Tỷ lệ tin tuyển dụng để mức lương "Thỏa thuận" chiếm khoảng 30% – 40%, đặc biệt là trong các lĩnh vực tài chính (Fintech, Chứng khoán) và bán lẻ (Retail). 💡 Nhận xét Thị trường & Khuyến nghị Golang & Python/.NET có biên độ lương cao: Các vị trí Backend sử dụng Golang cho dự án Senior đạt mức cao nhất (lên đến $3,500 USD). Các vị trí kết hợp Python/.NET hoặc Microservices/AWS cũng duy trì dải lương cạnh tranh ($800 – $2,000 USD hoặc 80M VND). Kỹ năng phụ trợ đẩy cao thu nhập: Ngoài ngôn ngữ lập trình chính, các kỹ năng về Microservices, Docker, Kafka, Cloud (AWS), và Kiến trúc hệ thống (Architecture) là yếu tố then chốt giúp Backend Developer đạt được mức lương ở mốc cao nhất của dải lương. Tính minh bạch tiền lương: Các công ty Outsourcing/Product có yếu tố nước ngoài thường công bố khung lương cụ thể tính theo USD ($800 – $3,500 USD), trong khi khối Fintech/Doanh nghiệp lớn thường thỏa thuận dựa trên năng lực thực tế của ứng viên. | J44: 46277 | K44: Pass | L44: { "judge_result": "PASS", "judge_status": "PASS", "reason": "The Actual Result successfully synthesizes salary ranges from the retrieved job postings into a clear breakdown (8 job postings specified). It properly separates salary ranges by currency (USD/month, VND/month, USD/hour, and Negotiable/Thỏa thuận) without misleading merging, provides level- and tech-based analysis, and notes the proportion and characteristics of the postings." } | M44: Pass | N44: No reference | O44: Kiểm tra khả năng tổng hợp và trình bày thông tin về khoảng lương từ nhiều tin tuyển dụng.
A46: TC-18 | B46: Trung bình | C46: Lọc tin theo trình độ tiếng Anh | D46: Tìm các tin tuyển dụng CNTT yêu cầu tiếng Anh và phân loại theo mức độ yêu cầu nếu có thể. | E46: Trả về các tin có đề cập đến tiếng Anh và phân biệt yêu cầu giao tiếp, đọc hiểu tài liệu, chứng chỉ hoặc trình độ cụ thể. | I46: Dưới đây là tổng hợp các tin tuyển dụng ngành CNTT có yêu cầu tiếng Anh trên thị trường, được phân loại chi tiết theo mức độ yêu cầu trình độ tiếng Anh (từ Thành thạo/Trôi chảy đến Giao tiếp tốt và Tiếng Anh làm việc chung). 📊 Phân loại các Tin tuyển dụng theo Mức độ Tiếng Anh 1. Cấp độ Thành thạo / Trôi chảy (Fluent English) Các vị trí này đòi hỏi khả năng làm việc trực tiếp với khách hàng quốc tế, chủ trì họp, thuyết trình hoặc làm ca đêm làm việc với thị trường toàn cầu. STT Vị trí tuyển dụng Công ty Cấp bậc Mức lương Kỹ năng chính Chi tiết / Ứng tuyển 1 Project Manager (fluent English communication) ST Engineering Manager Thỏa thuận English, Waterfall Methodology Xem tin 2 BA cum PO (fluent English communication) ST Engineering Mid Thỏa thuận English, Business Analysis Xem tin 3 Technical Support (Nightshift - English Fluent) iTechwx Company Limited Mid Đóng tới 20 Triệu VND IT Support, Fluent English Xem tin 2. Cấp độ Giao tiếp tốt (Good English Communication) Yêu cầu khả năng giao tiếp rõ ràng trong công việc hàng ngày, tham gia trao đổi kỹ thuật với đồng nghiệp/khách hàng nước ngoài. STT Vị trí tuyển dụng Công ty Cấp bậc Mức lương Kỹ năng chính Chi tiết / Ứng tuyển 1 PHP Developer (Good English communication skills) CÔNG TY TNHH NEXTEDGE Mid Thỏa thuận PHP, JavaScript, Drupal, Yii Xem tin 2 [Can Tho] Fresher PHP (Good English communication) CÔNG TY TNHH NEXTEDGE Fresher Thỏa thuận PHP, JavaScript, Laravel Xem tin 3 Technical Support Engineer (English) S4BT Solutions for Business Travel Mid 1,000 - 1,500 USD System Admin, Technical Support, English Xem tin 4 Business Analyst (English) QualityRealty Mid Thỏa thuận User story, Jira, BA Xem tin 5 Project Manager (English) Masan Group Manager Thỏa thuận Agile, Product Management, BA Xem tin 3. Cấp độ Tiếng Anh làm việc trong Môi trường Quốc tế (Working Proficiency) Các công ty đa quốc gia hoặc sản phẩm toàn cầu, nơi tiếng Anh là ngôn ngữ giao tiếp chuẩn trong hệ thống và tài liệu. STT Vị trí tuyển dụng Công ty Cấp bậc Mức lương Kỹ năng chính Chi tiết / Ứng tuyển 1 Product Manager Nakivo Manager 1,900 - 2,300 USD Product Owner, English Xem tin 2 AI Conversation Designer / AI Bot Operations Beyondsoft Technology Mid 1,330 - 1,780 USD LLM, Prompt Engineering Xem tin 💡 Đánh giá & Nhận xét Thị trường Vị trí Quản lý & Giao tiếp (PM, BA, Support, Product Manager): Đòi hỏi mức độ tiếng Anh Fluent hoặc Good Communication do thường xuyên phải truyền đạt yêu cầu, làm việc giữa stakeholders và đội ngũ kỹ thuật. Mức lương công bố cao (từ $1,000 - $2,300 USD). Vị trí Kỹ thuật (Developer, Support Specialist): Tiếng Anh giúp các vị trí như Developer (ngay cả từ cấp độ Fresher) tiếp cận công ty Outsourcing/Product nước ngoài với môi trường chuyên nghiệp. Mối liên hệ giữa Tiếng Anh và Mức lương: Hầu hết các vị trí ghi rõ yêu cầu tiếng Anh trong tiêu đề hoặc mô tả đều đến từ các công ty nước ngoài hoặc tập đoàn lớn, đi kèm chế độ đãi ngộ vượt trội hơn hẳn so với thị trường chung. | J46: 46277 | K46: Pass | L46: { "judge_result": "PASS", "judge_status": "PASS", "reason": "The Actual Result satisfies all essential requirements of the Expected Result: it retrieves specific IT job postings that require English and clearly classifies them by degree/level of requirement (Fluent English, Good English Communication, and Working Proficiency/International environment), fulfilling the test case purpose." } | M46: Pass | N46: No reference | O46: Kiểm tra khả năng nhận diện và phân loại các yêu cầu về tiếng Anh trong tin tuyển dụng.
A48: TC-19 | B48: Trung bình | C48: Phân tích xu hướng công nghệ | D48: Dựa trên tập tin tuyển dụng Backend Developer, hãy cho biết những ngôn ngữ lập trình nào xuất hiện và được đề cập nhiều hơn. | E48: Nếu đưa ra nhận xét về mức độ phổ biến thì phải dựa trên số lượng tin hoặc phạm vi dữ liệu được phân tích. | I48: Dựa trên dữ liệu từ các tin tuyển dụng và thống kê kỹ năng trên thị trường CNTT đối với vị trí Backend Developer, dưới đây là tổng hợp chi tiết về các ngôn ngữ lập trình xuất hiện và tần suất được đề cập. 📊 1. Thống kê Ngôn ngữ Lập trình phổ biến cho Backend Developer Dưới đây là các ngôn ngữ lập trình xuất hiện nhiều nhất trong yêu cầu tuyển dụng Backend: STT Ngôn ngữ Lập trình Tần suất xuất hiện / Tỷ lệ thị trường Framework / Công nghệ đi kèm Phân khúc vị trí phổ biến 1 Java 14 tin (6.93%) Spring Boot, Spring MVC, Spring Security, Hibernate Ngân hàng, Tài chính, Tập đoàn đa quốc gia, Hệ thống Enterprise 2 JavaScript / TypeScript 16 - 13 tin (6.44% - 7.92%) Node.js, Express.js, NestJS, Next.js Product Startup, E-commerce, Full-stack web, Microservices 3 Python 14 tin (6.93%) Django, FastAPI, Flask Tích hợp AI/Data, Web API, Fintech 4 C# / .NET Phổ biến trong DN lớn .NET Core, ASP.NET, Entity Framework Enterprise App, Tài chính, Doanh nghiệp phần mềm lớn 5 Golang (Go) Nhu cầu tuyển dụng cao Gin, Fiber, Microservices, Cloud-native Hệ thống chịu tải cao (High-traffic), Fintech, Crypto/Web3 6 PHP Cố định theo phân khúc Laravel, Symfony E-commerce, CMS, Các dự án Outsourcing truyền thống 7 Kotlin Bổ trợ cho Java Spring Boot, Ktor Các hệ thống backend hiện đại chuyển đổi từ Java 💡 2. Phân tích Chi tiết từng Ngôn ngữ trong Tuyển dụng 🔹 1. Java & Spring Ecosystem (Hàng đầu trong mảng Enterprise) Mức độ phổ biến: Rất cao. Java luôn là lựa chọn hàng đầu của các công ty lớn như Panasonic, Pinetree Securities, GS25... Công nghệ đi kèm: Spring Boot là framework backend bắt buộc đi kèm khi tuyển lập trình viên Java. Đặc điểm: Yêu cầu nhiều về kiến trúc Microservices, xử lý luồng (Apache Kafka, Message Queue), tối ưu hóa bộ nhớ và thiết kế SOLID/Design Patterns. 🔹 2. JavaScript / TypeScript (Node.js) Mức độ phổ biến: Rất cao và tăng trưởng mạnh nhờ tính linh hoạt. Mô hình phổ biến: Rất nhiều tin tuyển dụng Backend đòi hỏi Node.js đi kèm với kiến thức TypeScript hoặc Full-stack (ReactJS + Node.js). Ứng dụng: Thích hợp cho các công ty khởi nghiệp (Startup), ứng dụng xử lý thời gian thực (Real-time application), API Gateway và dịch vụ Web fast-to-market. 🔹 3. Python Mức độ phổ biến: Cao và ổn định. Đặc điểm tuyển dụng: Thường được yêu cầu kết hợp với phát triển API (FastAPI/Django) hoặc trong các dự án có yếu tố AI, xử lý dữ liệu và Grok/Voice Agent (như LizAI, QualityRealty, GS25). 🔹 4. C# / .NET Core Mức độ phổ biến: Khá cao trong các tập đoàn và công ty phần mềm lớn (như FPT IS, Creative Force). Đặc điểm: Thường được tuyển dụng cho các vị trí xây dựng hệ thống quản trị doanh nghiệp, thương mại điện tử lớn với kiến trúc .NET Core tiên tiến. 🔹 5. Golang (Go) Mức độ phổ biến: Đang gia tăng mạnh ở các vị trí Senior Backend Developer. Đặc điểm tuyển dụng: Xuất hiện ở các vị trí có mức lương cao (DNSE, VISION Advisory & Analytics). Nhắm tới các bài toán tối ưu hiệu năng, xử lý hàng triệu truy vấn đồng thời và hạ tầng Microservices/Docker/Kubernetes. 📌 Kết luận & Nhận xét Ngôn ngữ được đề cập nhiều nhất: Java và JavaScript/TypeScript (Node.js) là hai nhóm ngôn ngữ thống trị số lượng tin tuyển dụng Backend. Xu hướng công nghệ: Nếu hướng tới Doanh nghiệp lớn / Ngân hàng / Tài chính: Java (Spring Boot) và C# (.NET Core) là lựa chọn ưu tiên. Nếu hướng tới Product / Startup / Hệ thống linh hoạt: Node.js (TypeScript) và Python (FastAPI) chiếm ưu thế. Nếu hướng tới Tối ưu hiệu năng cao / Lương hấp dẫn ở cấp độ Senior: Golang là ngôn ngữ đang được săn đón mạnh mẽ. | J48: 46277 | K48: Pass | L48: { "judge_result": "PASS", "judge_status": "PASS", "reason": "The Actual Result satisfies the essential requirements of the Expected Result and fulfills the test case purpose. It synthesizes and compares the prevalence of programming languages from the dataset, grounding statements of popularity on concrete metrics (specific job count and percentages, e.g., Java with 14 postings/6.93%, JavaScript/TypeScript with 13-16 postings/6.44%-7.92%, Python with 14 postings/6.93%), followed by an analysis of tech ecosystems and market segments." } | M48: Pass | N48: No reference | O48: Kiểm tra khả năng tổng hợp và so sánh mức độ xuất hiện của các ngôn ngữ lập trình trong tập dữ liệu tuyển dụng.
A50: TC-20 | B50: Trung bình | C50: Đề xuất tin phù hợp với hồ sơ | D50: Tôi biết Python, Django, PostgreSQL và có khoảng 1 năm kinh nghiệm. Hãy tìm và đề xuất các tin tuyển dụng phù hợp với hồ sơ này. | E50: Đề xuất các tin có yêu cầu tương thích với kỹ năng và kinh nghiệm được cung cấp. Nêu được điểm phù hợp và điểm còn thiếu nếu có. | I50: Chào bạn, dưới đây là phân tích thị trường tuyển dụng và danh sách các cơ hội công việc phù hợp với hồ sơ Python, Django, PostgreSQL (1 năm kinh nghiệm) của bạn. 1. Phân Tích Hồ Sơ & Vị Thế Thị Trường Cấp độ phù hợp: Junior / Junior Backend Developer (1 năm kinh nghiệm). Bộ kỹ năng cốt lõi (Tech Stack): Language: Python Framework: Django (Full-stack / Web Framework) Database: PostgreSQL (Relational DB) Đánh giá thị trường: Đây là bộ kỹ năng backend tiêu chuẩn và rất được ưa chuộng tại các công ty sản xuất phần mềm (Product), công ty làm ứng dụng Web/SaaS và các dự án Outsourcing chất lượng cao. 2. Danh Sách Tin Tuyển Dụng Gợi Ý Dưới đây là các vị trí phù hợp nhất được trích xuất từ dữ liệu thị trường IT hiện tại: Vị trí tuyển dụng Công ty Cấp độ Hình thức Kỹ năng yêu cầu Chi tiết / Ứng tuyển Junior Backend Developer (Python / APIs) QualityRealty Junior Hybrid API, PostgreSQL, Git, Python Xem chi tiết Junior Fullstack Developer (PHP, Python, SQL, OOP) Vanfu Software Việt Nam Junior Onsite Python, SQL, OOP, PHP, Git Xem chi tiết Lập Trình Viên Python Tập đoàn VNPT Junior / Mid Onsite Python, Frameworks, Web Base Xem chi tiết Middle Fullstack Developer (WordPress, Python) QualityRealty Mid Hybrid Python, Git, GCP Xem chi tiết 3. Tham Khảo Mức Lương Thị Trường (Benchmark) Đối với vị trí Junior Python Developer (từ 1 - 2 năm kinh nghiệm): Mức lương trung bình: 400 USD – 900 USD/tháng (tương đương khoảng 10 - 22 triệu VNĐ/tháng). Yếu tố gia tăng thu nhập: Ngoại ngữ (Tiếng Anh tốt), kinh nghiệm tối ưu hóa truy vấn PostgreSQL, am hiểu về RESTful API và Docker/Containerization. 4. Gợi Ý Phát Triển Cho Buổi Phỏng Vấn Để gia tăng cơ hội trúng tuyển vào các công ty có chế độ đãi ngộ tốt, bạn nên chuẩn bị kỹ các chủ đề kỹ thuật sau: Django & Python: Hiểu rõ Django ORM (select_related, prefetch_related để tránh lỗi N+1 query). Middleware, Authentication/Authorization (JWT, OAuth2). Django REST Framework (DRF) cho thiết kế API. PostgreSQL: Cách đánh Index (B-Tree, Hash) và tối ưu hóa câu lệnh SQL slow queries (EXPLAIN ANALYZE). Database Migration trong Django. Kỹ năng bổ trợ nên bổ sung: Container: Docker cơ bản. Task Queue: Celery + Redis (rất hay dùng chung với Django). Version Control: Git workflow (Gitflow, PR review). Nếu bạn muốn điều chỉnh khu vực làm việc (TP.HCM, Hà Nội, Đà Nẵng...) hoặc cần thêm thông tin chi tiết về từng vị trí, hãy phản hồi lại cho tôi nhé! | J50: 46277 | K50: Fail | L50: { "judge_result": "FAIL", "judge_status": "FAIL", "reason": "The Actual Result failed to satisfy the essential requirement in the Expected Result: it did not explicitly analyze or state the matched points (điểm phù hợp) and missing/gap points (điểm còn thiếu) for each recommended job against the candidate's profile." } | M50: Fail | N50: No reference | O50: Kiểm tra khả năng đối chiếu hồ sơ kỹ năng, kinh nghiệm của ứng viên với yêu cầu tuyển dụng để đề xuất các tin phù hợp.
A52: TC-21 | B52: Khó | C52: Tìm việc đa điều kiện | D52: Tôi là Backend Developer có 2 năm kinh nghiệm Python và Django, muốn tìm việc tại Thành phố Hồ Chí Minh, ưu tiên hybrid, mức lương kỳ vọng từ 20 triệu đồng/tháng. Hãy tìm các tin phù hợp nhất. | E52: Lọc và xếp các tin dựa trên các điều kiện: vị trí Backend, Python/Django, kinh nghiệm, địa điểm, hình thức làm việc và mức lương. Phải phân biệt điều kiện đáp ứng đầy đủ với điều kiện chỉ đáp ứng một phần. Không loại bỏ hoặc khẳng định phù hợp tuyệt đối nếu dữ liệu chưa đủ. | I52: Chào bạn, dưới đây là tổng hợp phân tích thị trường tuyển dụng và danh sách các vị trí Python/Django Backend Developer phù hợp tại Thành phố Hồ Chí Minh dựa trên yêu cầu của bạn (2 năm kinh nghiệm, ưu tiên Hybrid, mức lương từ 20 triệu VND/tháng). 1. Đánh Giá Khả Năng Đáp Ứng Hồ Sơ (Profile Fit Analysis) Tiêu chí Mô tả từ yêu cầu của bạn Đánh giá thị trường TP.HCM Cấp độ (Seniority) 2 năm kinh nghiệm (Mid-level Backend Developer) Rất tốt: Mức 2 năm kinh nghiệm đáp ứng đủ điều kiện làm độc lập các tính năng phức tạp (Mid-level). Tech Stack Python, Django Nhu cầu ổn định: Django là framework phổ biến cho ứng dụng enterprise và web services. Mức lương kỳ vọng Từ 20.000.000 VNĐ/tháng (~800+ USD) Phù hợp thực tế: Mức lương trung bình cho Mid Python Dev tại TP.HCM dao động từ 20 – 35 triệu VNĐ/tháng (tùy thuộc vào trình độ tiếng Anh, Docker/AWS và tối ưu hóa DB). Chế độ làm việc Ưu tiên Hybrid (kết hợp Remote & Office) Khả thi: Rất nhiều công ty công nghệ đa quốc gia và sản phẩm tại TP.HCM duy trì chính sách làm việc 2-3 ngày/tuần tại văn phòng. 2. Danh Sách Tin Tuyển Dụng Phù Hợp Nổi Bật Dưới đây là các vị trí công việc được ghi nhận tại thị trường TP.HCM đáp ứng tiêu chí kỹ năng và chế độ làm việc: 🌟 1. Accenture – Python Developer Công ty: Accenture (Tập đoàn công nghệ đa quốc gia) Hình thức làm việc: 🟢 Hybrid Cấp độ: Mid-level Bộ kỹ năng: Python, RESTful API, Microservices Điểm nổi bật: Môi trường quốc tế, chính sách Hybrid linh hoạt, mức đãi ngộ & chế độ đãi ngộ cạnh tranh theo tiêu chuẩn công ty toàn cầu. Link ứng tuyển: Accenture - Python Developer 🌟 2. Prestige Home – Senior/Mid Python Developer Công ty: Prestige Home Hình thức làm việc: Onsite (TP.HCM) Cấp độ: Mid - Senior Mức lương: Lên đến 40 triệu VNĐ/tháng (30 - 40M VNĐ/tháng) Bộ kỹ năng: Python, Django, API, Redis Điểm nổi bật: Phù hợp hoàn toàn với tech stack Django + Python, mức lương hấp dẫn vượt mức kỳ vọng ban đầu của bạn. Link ứng tuyển: Prestige Home - Senior Python Developer 🌟 3. LHV Software – Backend Developer (Python/Django) Công ty: LHV Software Hình thức làm việc: 🟢 Hybrid Bộ kỹ năng: Python, Django, SQL, Cloud/AWS Điểm nổi bật: Chế độ Hybrid làm việc linh hoạt, tập trung mạnh vào các dự án Django và điện toán đám mây. Link ứng tuyển: LHV Software - Backend Developer 🌟 4. IVC (ISB Vietnam) – Python Developer (Databases & System Design) Công ty: ISB Vietnam Hình thức làm việc: Onsite (TP.HCM) Mức lương: 500 - 2,000 USD/tháng (khoảng 12.5M - 50M VNĐ) Bộ kỹ năng: Python, PostgreSQL/NoSQL, System Design, English Link ứng tuyển: ISB Vietnam - Python Developer 3. Lời Khuyên Để Tối Ưu Hồ Sơ & Đạt Mức Lương Mong Muốn (>= 25M+) Với 2 năm kinh nghiệm Python/Django, để đàm phán thành công mức lương trên 20 - 30 triệu/tháng và nhận được deal Hybrid, bạn nên nhấn mạnh các điểm sau trong CV: Kiến thức chuyên sâu về Django & REST API: Sử dụng thành thạo Django REST Framework (DRF), JWT Authentication, Serializers. Kinh nghiệm tối ưu hóa ORM Query (tránh lỗi N+1 queries, đánh Index hợp lý trong PostgreSQL/MySQL). Caching & Asynchronous Tasks: Đưa kiến thức về Redis/Memcached và Celery vào CV để thể hiện khả năng xử lý các tác vụ bất đồng bộ và tải cao. DevOps & Containerization căn bản: Sử dụng Docker, Docker-Compose để đóng gói ứng dụng. Hiểu biết về CI/CD (GitHub Actions/GitLab CI) và triển khai ứng dụng lên AWS/GCP/DigitalOcean. Nếu bạn cần hỗ trợ đánh giá lại CV, chuẩn bị câu hỏi phỏng vấn kỹ thuật Python/Django, hoặc mẹo đàm phán lương, hãy cho tôi biết nhé! | J52: 46277 | K52: Fail | L52: { "judge_result": "FAIL", "judge_status": "FAIL", "reason": "The Actual Result failed to satisfy the essential requirements of the Expected Result. Specifically, it did not categorize or distinguish between jobs that fully meet all criteria versus those that only partially meet them (e.g., Prestige Home and IVC are Onsite rather than Hybrid; Accenture and IVC do not explicitly list Django; Accenture and LHV Software lack salary information without clarifying data sufficiency). Furthermore, it did not rank the listings based on their degree of fulfillment." } | M52: Fail | N52: No reference | O52: Kiểm tra khả năng xử lý nhiều điều kiện tìm kiếm đồng thời và phân biệt mức độ đáp ứng của từng tin tuyển dụng.
A54: TC-22 | B54: Khó | C54: So sánh mức độ phù hợp giữa nhiều tin | D54: Tôi có kỹ năng Python, FastAPI, PostgreSQL, Docker và 1 năm kinh nghiệm. Hãy chọn 3 tin tuyển dụng phù hợp nhất trong số các tin đã tìm được và giải thích thứ tự lựa chọn. | E54: Chọn tối đa 3 tin có mức độ phù hợp cao dựa trên các tiêu chí rõ ràng như công nghệ, kinh nghiệm, vị trí và địa điểm. Mỗi lựa chọn phải có lý do dựa trên dữ liệu. Nếu có yêu cầu quan trọng mà ứng viên chưa đáp ứng, phải nêu rõ. | I54: Chào bạn, dựa trên bộ kỹ năng cốt lõi của bạn (Python, FastAPI, PostgreSQL, Docker) và 1 năm kinh nghiệm (Junior), tôi đã lọc và chọn ra 3 vị trí tuyển dụng phù hợp nhất cùng với phần giải thích thứ tự ưu tiên chi tiết dưới đây. 1. Top 3 Tin Tuyển Dụng Phù Hợp Nhất 🥇 Vị trí 1: Junior Backend Developer (Python / APIs) Công ty: QualityRealty Cấp độ: Junior Mô hình làm việc: Hybrid Mức lương: Thỏa thuận theo năng lực Bộ kỹ năng: Python, PostgreSQL, REST API, Git Link tuyển dụng: Xem chi tiết tin tuyển dụng 🥈 Vị trí 2: Backend Python Developer (Flask, FastAPI, SQL, Docker) Công ty: GLOBALTECH Cấp độ: Mid-level (Ưu tiên ứng viên vững nền tảng) Mô hình làm việc: Onsite Mức lương: Thỏa thuận theo năng lực Bộ kỹ năng: Python, FastAPI, Flask, SQL (PostgreSQL), Docker, Kafka Link tuyển dụng: Xem chi tiết tin tuyển dụng 🥉 Vị trí 3: Backend Developer (Python/.Net, Junior/Senior) Công ty: LizAI Vietnam Cấp độ: Junior / Senior Mô hình làm việc: Onsite Mức lương: 800 - 2,000 USD/tháng (~19.5 - 49 triệu VND) Bộ kỹ năng: Python, SQL / PostgreSQL, Backend Architecture Link tuyển dụng: Xem chi tiết tin tuyển dụng 2. Giải Thích Thứ Tự Lựa Chọn & Tiêu Chí Xếp Hạng Tiêu chí đánh giá 🥇 #1. QualityRealty 🥈 #2. GLOBALTECH 🥉 #3. LizAI Vietnam Độ tương thích Seniority 100% (Đúng chuẩn Junior 1 năm) 75% (Yêu cầu Mid, nhưng nhận ứng viên vững kĩ năng) 90% (Dải nhận tuyển từ Junior) Độ trùng khớp Tech Stack Python, PostgreSQL, RESTful API Trùng 100%: FastAPI, Docker, SQL, Python Python, SQL, Backend Development Mô hình & Môi trường Hybrid (Linh hoạt, tối ưu công việc) Onsite Onsite Tiềm năng phát triển Cao (Tập trung phát triển API & DB) Rất cao (Làm việc với FastAPI + Docker + Kafka) Rất cao (Mức lương tốt, làm việc với công nghệ mới) Lý do chi tiết: Ưu tiên số 1 (QualityRealty): Safe & Best Fit Vừa sức nhất: Tuyển đúng vị trí Junior với 1 năm kinh nghiệm, giúp tỷ lệ qua vòng hồ sơ (CV screening) và phỏng vấn là cao nhất. Điểm cộng Hybrid: Đáp ứng xu hướng làm việc linh hoạt, giúp cân bằng giữa làm việc độc lập và làm việc nhóm. Stack phù hợp: Tập trung sâu vào thiết kế RESTful API và tối ưu PostgreSQL. Ưu tiên số 2 (GLOBALTECH): High Skill Match / Challenge Fit Hoàn hảo về Công nghệ: Mô tả công việc trùng khớp tuyệt đối 100% bộ kỹ năng bạn đang có (FastAPI, Docker, SQL/PostgreSQL). Cơ hội bứt phá: Dù đăng tuyển mức Mid, nhưng nếu bạn tự tin vào khả năng viết code FastAPI chuẩn asynchronous và đóng gói container với Docker, đây là cơ hội nâng tầm mức lương và trình độ lên Mid-level nhanh chóng. Ưu tiên số 3 (LizAI Vietnam): High Compensation & Growth Dải lương hấp dẫn: Mức thu nhập khởi điểm từ $800 (~19.5 triệu VND) cho vị trí Junior là mức rất cạnh tranh trên thị trường hiện tại. Đa dạng công nghệ: Phù hợp nếu bạn muốn thử sức ở các công ty sản xuất sản phẩm công nghệ (Product company) về AI/Data. 3. Lời Khuyên Tối Ưu Hồ Sơ Đăng Ký (CV Highlight) Với bộ stack FastAPI + PostgreSQL + Docker, bạn đang nắm giữ lợi thế rất lớn vì đây là modern Python backend stack cực kỳ được ưa chuộng. Hãy làm nổi bật các điểm sau trong CV: FastAPI: Nêu rõ kinh nghiệm xây dựng RESTful APIs bất đồng bộ (async/await), tích hợp Pydantic cho data validation và Swagger UI / OpenAPI documentation. PostgreSQL: Thể hiện khả năng thiết kế Schema, đánh Index, tối ưu câu lệnh Query hoặc sử dụng ORM (như SQLAlchemy hoặc Tortoise-ORM). Docker: Đưa vào CV kinh nghiệm viết Dockerfile tối ưu nhiều tầng (multi-stage build), sử dụng docker-compose để thiết lập môi trường phát triển gồm App + DB + Redis. | J54: 46277 | K54: Pass | L54: { "judge_result": "PASS", "judge_status": "PASS", "reason": "The Actual Result successfully selects up to 3 suitable job listings based on the candidate's specific profile (Python, FastAPI, PostgreSQL, Docker, 1 year experience), clearly explains the rationale for the ranking order, and explicitly identifies where requirements (such as seniority levels) only partially match or present a challenge." } | M54: Pass | N54: No reference | O54: Kiểm tra khả năng đánh giá, xếp hạng và giải thích mức độ phù hợp của các tin tuyển dụng đối với một hồ sơ kỹ năng cụ thể.
A56: TC-23 | B56: Khó | C56: Xử lý thông tin thiếu về mức lương | D56: Tôi có kỹ năng Python, FastAPI, PostgreSQL, Docker và 1 năm kinh nghiệm. Hãy chọn 3 tin tuyển dụng phù hợp nhất trong số các tin đã tìm được và giải thích thứ tự lựa chọn. | E56: Phân biệt tin đáp ứng được điều kiện lương với tin không có dữ liệu lương. Không được xem tin không công bố lương là chắc chắn đạt mức từ 25 triệu đồng. Có thể đưa vào nhóm “chưa xác định” nếu phù hợp với yêu cầu mở rộng, nhưng phải ghi rõ lý do. | I56: Chào bạn, dựa trên bộ kỹ năng hiện tại (Python, FastAPI, PostgreSQL, Docker) và 1 năm kinh nghiệm (Cấp độ Junior), dưới đây là 3 tin tuyển dụng phù hợp nhất được chọn lọc từ dữ liệu thị trường mới nhất, kèm theo phân tích chi tiết và lý do sắp xếp thứ tự ưu tiên. 🥇 1. Danh Sách Top 3 Tin Tuyển Dụng Phù Hợp Nhất 1️⃣ Vi trí 1: Junior Backend Developer (Python / APIs) Công ty: QualityRealty Cấp độ tuyển dụng: Junior (Phù hợp chính xác với 1 năm kinh nghiệm) Mô hình làm việc: Hybrid (Linh hoạt kết hợp Online & Văn phòng) Mức lương: Thỏa thuận theo năng lực (Cạnh tranh cho cấp độ Junior) Bộ kỹ năng trọng tâm: Python, APIs, PostgreSQL, Git Link ứng tuyển: Xem chi tiết công việc tại ITViec 2️⃣ Vị trí 2: Backend Python Developer (Flask, FastAPI, SQL, Docker) Công ty: GLOBALTECH Cấp độ tuyển dụng: Mid-level (Có thể cân nhắc ứng viên Junior có bộ skill trùng khớp) Mô hình làm việc: Onsite Mức lương: Thỏa thuận theo năng lực Bộ kỹ năng trọng tâm: Python, FastAPI, SQL (PostgreSQL), Docker, Kafka, Flask Link ứng tuyển: Xem chi tiết công việc tại ITViec 3️⃣ Vị trí 3: Python Developer Công ty: Accenture Cấp độ tuyển dụng: Mid / General Backend Mô hình làm việc: Hybrid Mức lương: Thỏa thuận theo khung tập đoàn quốc tế Bộ kỹ năng trọng tâm: Python, RESTful APIs, System Integration Link ứng tuyển: Xem chi tiết công việc tại ITViec 📊 2. Giải Thích Thứ Tự Lựa Chọn & Tiêu Chí Đánh Giá Thứ tự ưu tiên được xác định dựa trên 3 tiêu chí cốt lõi: Độ tương thích Cấp độ (Seniority Fit), Độ trùng khớp Bộ kỹ năng (Tech Stack Alignment) và Mô hình làm việc (Working Model). Tiêu chí so sánh 🥇 Vị trí 1 (QualityRealty) 🥈 Vị trí 2 (GLOBALTECH) 🥉 Vị trí 3 (Accenture) Yêu cầu kinh nghiệm Chính xác Junior (1 năm) Mid (Cần chuẩn bị kỹ CV) Mid / Junior Upper Trùng khớp Tech Stack 85% (Python, PostgreSQL, API) 100% (FastAPI + Docker + SQL) 75% (Python, RESTful API) Mô hình làm việc Hybrid (Tối ưu) Onsite Hybrid (Tối ưu) Tỷ lệ đậu vòng CV Rất cao (85 - 90%) Khá (70 - 75%) Trung bình (65 - 70%) 💡 Lý do chi tiết cho từng thứ tự: Tại sao vị trí tại QualityRealty đứng #1? Cấp độ tương thích nhất: Tin tuyển dụng ghi rõ cấp độ Junior, đúng với số năm kinh nghiệm của bạn (1 năm), giảm thiểu tối đa rào cản loại CV ở vòng lọc tự động. Mô hình Hybrid: Đáp ứng tiêu chí làm việc linh hoạt. Nền tảng vững chắc: Tập trung vào các kỹ năng cốt lõi Python/PostgreSQL/APIs, rất thích hợp để nâng cao tay nghề backend. Tại sao vị trí tại GLOBALTECH đứng #2? Bộ kỹ năng khớp 100%: Mô tả công việc ghi chính xác FastAPI, SQL, Docker – đúng toàn bộ bộ công cụ bạn sở hữu. Lý do xếp sau vị trí #1: Yêu cầu mức Mid-level và làm việc Onsite. Tuy nhiên, nếu CV của bạn thể hiện rõ kinh nghiệm triển khai dự án thực tế với FastAPI và Docker, khả năng vượt qua vòng hồ sơ vẫn rất cao. Tại sao vị trí tại Accenture đứng #3? Môi trường tập đoàn toàn cầu: Accenture cung cấp quy chuẩn làm việc chuyên nghiệp, quy trình chuẩn chỉnh và đãi ngộ tốt cho nhân sự phát triển dài hạn. Mô hình Hybrid: Hỗ trợ linh hoạt môi trường làm việc. Lý do xếp thứ #3: Quy trình tuyển dụng khắt khe hơn đối với ứng viên 1 năm kinh nghiệm và tập trung nhiều hơn vào bài toán doanh nghiệp lớn (Enterprise Context). 💡 3. Lời Khuyên Chiến Lược Cho Ứng Viên 1 Năm Kinh Nghiệm Tối ưu hóa CV với FastAPI & Docker: Với 1 năm kinh nghiệm, việc làm chủ được FastAPI (framework hiện đại, tốc độ cao) và Docker (containerization) là điểm cộng rất lớn so với các ứng viên Junior khác chỉ biết Django/Flask cơ bản. Hãy đưa các chỉ số đo lường hiệu năng API hoặc cấu hình Docker container vào phần dự án trong CV. Chuẩn bị Kiến thức PostgreSQL: Luyện tập thêm về tối ưu hóa câu lệnh SQL, indexing và thiết kế DB schema để ghi điểm mạnh trong buổi phỏng vấn chuyên môn. | J56: 46277 | K56: Fail | L56: { "judge_result": "FAIL", "judge_status": "FAIL", "reason": "The Actual Result failed to satisfy the essential requirements of the Expected Result. Specifically, the Expected Result and Test Case Purpose required handling and distinguishing missing salary information (since none of the 3 chosen listings disclosed exact salaries, all being marked as 'Thỏa thuận'), but the response completely omitted any discussion, handling, or categorization of salary data or whether salary conditions were met." } | M56: Fail | N56: No reference | O56: Kiểm tra khả năng xử lý dữ liệu mức lương bị thiếu và phân biệt thông tin đã xác minh với thông tin chưa thể xác định.
A58: TC-24 | B58: Khó | C58: Phân biệt điều kiện bắt buộc và ưu tiên | D58: Tìm các tin tuyển dụng yêu cầu Java và Spring Boot. Chỉ chọn những tin bắt buộc có cả hai công nghệ, không chọn tin chỉ ghi “biết thêm là lợi thế”. | E58: Phân biệt chính xác giữa yêu cầu bắt buộc và yêu cầu ưu tiên hoặc lợi thế. Chỉ đưa vào nhóm đạt điều kiện các tin thể hiện cả Java và Spring Boot là yêu cầu bắt buộc hoặc tương đương rõ ràng. | I58: Dưới đây là danh sách các tin tuyển dụng yêu cầu bắt buộc đồng thời cả Java và Spring Boot được tổng hợp từ dữ liệu thị trường mới nhất: 📋 Danh Sách Tin Tuyển Dụng Yêu Cầu Java & Spring Boot STT Tên vị trí Công ty Cấp độ Mô hình Mức lương Kỹ năng liên quan 1 Backend Developer (Java, Spring Boot, Securities) Pinetree Securities Mid (Middle) Onsite 1,000 - 1,500 USD Java, Spring Boot, MongoDB, MariaDB 2 Java Spring Boot (Middle/Senior) Nitori Digital Base Vietnam Middle / Senior Hybrid 700 - 2,000 USD Java, Spring Boot, Angular, JavaScript 3 Senior Java Developer (Spring, Fintech) UNIT Corp Senior Onsite 800 - 1,500 USD Java, Spring Boot, SQL, CI/CD 4 Java Developer (Spring Boot, Microservices) VPBank Mid (Middle) Onsite Thỏa thuận Java, Spring Boot, Microservices, OOP 5 Senior Java Core / Spring Boot Mcredit (MB Shinsei) Senior Onsite Thỏa thuận Java Core, Spring Boot, Spring Security, REST API 🔍 Chi Tiết Các Vị Trí Tiêu Biểu 1️⃣ Backend Developer (Java, Spring Boot, Securities) - Pinetree Securities Cấp độ: Mid-level Mức lương: 1,000 - 1,500 USD/tháng Mô hình làm việc: Onsite Yêu cầu kỹ năng cốt lõi: Java, Spring Boot Framework, cơ sở dữ liệu MongoDB/MariaDB. Đánh giá: Vị trí phù hợp cho các lập trình viên có từ 2–4 năm kinh nghiệm làm việc trong lĩnh vực Tài chính - Chứng khoán (Fintech). 2️⃣ Java Spring Boot (Middle/Senior) - Nitori Digital Base Vietnam Cấp độ: Middle / Senior Mức lương: 700 - 2,000 USD/tháng Mô hình làm việc: Hybrid (Linh hoạt) Yêu cầu kỹ năng cốt lõi: Java, Spring Boot, kết hợp kỹ năng Frontend (Angular/JavaScript). Đánh giá: Điểm cộng lớn là chế độ làm việc Hybrid, dải lương rộng tùy thuộc theo năng lực thực tế. 3️⃣ Senior Java Developer (Spring, Fintech) - UNIT Corp Cấp độ: Senior Mức lương: 800 - 1,500 USD/tháng Mô hình làm việc: Onsite Yêu cầu kỹ năng cốt lõi: Java, Spring Boot, SQL, quy trình CI/CD. Đánh giá: Tập trung phát triển các hệ thống Backend quy mô lớn thuộc mảng Fintech. 📌 Lưu ý: Tất cả các vị trí trên đều yêu cầu Java và Spring Boot là thành phần cốt lõi trong stack công nghệ bắt buộc hàng ngày của dự án. | J58: 46277 | K58: Pass | L58: { "judge_result": "PASS", "judge_status": "PASS", "reason": "The Actual Result successfully filters and includes only job listings that require both Java and Spring Boot as mandatory core technologies, correctly excluding any listings where Spring Boot is merely an advantage or preferred skill, thereby fulfilling the test case purpose and expected result." } | M58: Pass | N58: No reference | O58: Kiểm tra khả năng phân biệt yêu cầu công nghệ bắt buộc với yêu cầu ưu tiên trong tin tuyển dụng.
A60: TC-25 | B60: Khó | C60: Phân tích tin có mâu thuẫn nội bộ | D60: Một tin ghi tiêu đề “Junior Backend Developer”, nhưng phần yêu cầu lại yêu cầu 3–5 năm kinh nghiệm. Hãy phân tích xem tin này có phù hợp với ứng viên có 1 năm kinh nghiệm hay không. | E60: Nhận diện sự không nhất quán giữa tiêu đề và yêu cầu kinh nghiệm. Không chỉ dựa vào tiêu đề để kết luận phù hợp. Phải chỉ ra yêu cầu 3–5 năm là trở ngại và đánh dấu tin là không phù hợp hoặc cần xác minh thêm. | I60: Nhà tuyển dụng đăng tiêu đề “Junior Backend Developer” nhưng phần yêu cầu lại đòi hỏi 3–5 năm kinh nghiệm là hiện tượng mâu thuẫn giữa tiêu đề công việc và yêu cầu thực tế (Title-Requirement Mismatch) khá phổ biến trong thị trường tuyển dụng IT hiện nay. Dưới đây là phân tích chi tiết từ góc nhìn tư vấn thị trường IT để giúp bạn đánh giá xem tin tuyển dụng này có phù hợp với ứng viên 1 năm kinh nghiệm hay không. 🎯 1. Đánh Giá Mức Độ Phù Hợp Kết luận nhanh: Tỷ lệ phù hợp THẤP (Không khuyến khích ưu tiên nhóm tin này). Trừ khi ứng viên có năng lực kỹ thuật thực tế vượt trội so với số năm kinh nghiệm, việc ứng tuyển vào vị trí này thường mang lại rủi ro cao về khối lượng công việc hoặc chính sách đãi ngộ không tương xứng. 🔍 2. Phân Tích Nguyên Nhân & Thực Trạng Thị Trường Tiêu chí Cấp độ Junior tiêu chuẩn Yêu cầu 3–5 năm trong tin tuyển dụng Kinh nghiệm 0 – 2 năm 3 – 5 năm (Thực chất là Mid-level hoặc Senior) Khả năng tự lập Cần Mentor/Lead hỗ trợ và định hướng Tự chủ hoàn toàn, tự thiết kế kiến trúc và xử lý sự cố phức tạp Kỳ vọng đầu ra Hoàn thành task đúng hạn, code đúng chuẩn Đóng góp vào thiết kế hệ thống, tối ưu hiệu năng, review code Các nguyên nhân dẫn đến mâu thuẫn này: Chèn ép ngân sách (Salary Suppression): Nhà tuyển dụng muốn tuyển một lập trình viên có năng lực Mid-level (đã đi làm 3–5 năm) nhưng chỉ muốn trả mức lương ở phân khúc Junior. Sai sót từ khâu soạn thảo JD: Bộ phận Tuyển dụng (HR) copy-paste yêu cầu từ các vị trí Mid/Senior cũ nhưng giữ nguyên tiêu đề "Junior", hoặc không nắm rõ khung năng lực kỹ thuật. Chiến lược "Đặt rào cản cao" (Over-requiring): Nhà tuyển dụng đặt mốc 3–5 năm để lọc bớt hồ sơ ứng viên quá mới, nhưng thực tế sẵn sàng phỏng vấn ứng viên 1–2 năm nếu kỹ năng thực tế (Hard Skills) đáp ứng tốt. ⚖️ 3. Phân Tích Lợi Ích & Rủi Ro Cho Ứng Viên 1 Năm Kinh Nghiệm ❌ Rủi ro (Rất đáng quan ngại) Quá tải công việc (Burnout): Nếu trúng tuyển, công ty có thể kỳ vọng bạn làm việc như một Mid-level (xử lý bài toán khó, độc lập vận hành), trong khi bạn mới có 1 năm kinh nghiệm và vẫn cần môi trường có hướng dẫn (Mentorship). Bị ép lương: Bạn làm công việc của cấp độ Mid-level nhưng chỉ nhận được đãi ngộ cấp độ Junior. Tỷ lệ rớt CV cao: CV của bạn dễ bị hệ thống lọc tự động (ATS) hoặc HR loại ngay từ vòng gửi xe vì chưa đủ mốc 3 năm kinh nghiệm. 💡 Cơ hội (Nếu bạn vẫn muốn nộp CV) Năng lực kỹ thuật vượt trội: Nếu trong 1 năm qua bạn đã trực tiếp tham gia thiết kế hệ thống lớn, làm việc với kiến trúc Microservices, tối ưu CSDL nâng cao hoặc đóng góp cho dự án open-source lớn, số năm kinh nghiệm thực tế không còn là rào cản tuyệt đối. 📋 4. Bảng Đưa Ra Quyết Định (Decision Framework) Bạn nên cân nhắc hành động theo các kịch bản sau: Kịch bản của Ứng viên Lời khuyên hành động Kỹ năng đúng chuẩn 1 năm: Chỉ mới làm các chức năng CRUD cơ bản, chưa từng làm chủ kiến trúc hay tối ưu hệ thống. ❌ BỎ QUA: Tập trung nộp các tin tuyển dụng ghi rõ yêu cầu 1–2 năm kinh nghiệm để có môi trường phát triển lành mạnh. Kỹ năng cứng cáp, dự án thực tế phức tạp: Đã tự tay làm CI/CD, tối ưu query PostgreSQL phức tạp, làm việc thâm sâu với Docker/Kubernetes. ⚠️ CÓ THỂ NỘP: Cần viết lại CV tập trung vào thành tựu kỹ thuật & quy mô dự án thay vì nhấn mạnh số năm kinh nghiệm. Tin tuyển dụng có công khai mức lương hấp dẫn (trên $1,000): ⚠️ NỘP THỬ SỨC: Đặt tâm lý thử sức để đánh giá năng lực qua phỏng vấn. 💡 5. Lời Khuyên Chiến Lược Cho Ứng Viên 1 Năm Kinh Nghiệm Ưu tiên các tin tuyển dụng minh bạch: Hãy chọn các vị trí ghi rõ yêu cầu 1–2 năm kinh nghiệm (Junior / Junior-Mid). Những công ty này thường có lộ trình thăng tiến và hệ thống hướng dẫn (mentorship) rõ ràng hơn. Hỏi kỹ khi Phỏng vấn (nếu tham gia): Đặt các câu hỏi như: "Vị trí này sẽ làm việc độc lập hay nằm trong team có Senior/Lead hướng dẫn?" "Kỳ vọng cụ thể trong 3 tháng đầu tiên đối với vị trí này là gì?" Điều này giúp bạn nhận biết ngay công ty đang tìm Junior thực thụ hay đang tìm Mid-level "giá rẻ". | J60: 46277 | K60: Pass | L60: { "judge_result": "PASS", "judge_status": "PASS", "reason": "The Actual Result successfully identifies the inconsistency between the title 'Junior Backend Developer' and the experience requirement of 3-5 years, avoids relying solely on the title, correctly highlights the 3-5 year requirement as a major obstacle/risk, and categorizes the listing as low suitability or requiring careful verification." } | M60: Pass | N60: No reference | O60: Kiểm tra khả năng phát hiện sự không nhất quán giữa tiêu đề và nội dung yêu cầu kinh nghiệm của tin tuyển dụng.
A62: TC-26 | B62: Khó | C62: Xử lý câu hỏi có tiền đề chưa được chứng minh | D62: Công ty Bosch hiện đang tuyển 50 vị trí AI Engineer tại Việt Nam đúng không? Hãy liệt kê các vị trí đó. | E62: Agent phải kiểm tra dữ liệu có sẵn, nêu rõ không đủ căn cứ nếu không xác minh được số lượng 50 hoặc danh sách vị trí. Không tự tạo danh sách hoặc số lượng tuyển dụng. | I62: Thông tin công ty Bosch (Bosch Global Software Technologies Vietnam) đang tuyển 50 vị trí AI Engineer cùng lúc tại Việt Nam là KHÔNG CHÍNH XÁC dựa trên dữ liệu tuyển dụng thực tế thời điểm hiện tại. Dưới đây là phân tích chi tiết và danh sách các vị trí liên quan đến AI thực tế mà Bosch đang tuyển dụng. 🔍 1. Phân Tích Thực Trạng Tuyển Dụng AI Tại Bosch Vietnam Mâu thuẫn thông tin: Số lượng "50 vị trí" thường là chỉ tiêu tổng thể / kế hoạch mở rộng trung hạn của dự án (hoặc thông cáo PR/định hướng phát triển trung tâm R&D), không phải là số lượng vị trí tuyển dụng mở đăng ký ngay lập tức. Thực tế thị trường: Bosch hiện chỉ tập trung tuyển các vị trí AI chuyên sâu cấp độ Senior / Lead / Specialist với số lượng tuyển chọn kỹ lưỡng, không tuyển ồ ạt hàng loạt vị trí AI Engineer cấp phổ thông. 📋 2. Danh Sách Các Vị Trí Tuyển Dụng Liên Quan Đến AI Thực Tế Của Bosch Dưới đây là các vị trí làm việc trong mảng AI & Enterprise Platforms tại Bosch Global Software Technologies Company Limited đang được niêm yết công khai: STT Tên vị trí tuyển dụng Cấp độ Kỹ năng / Lĩnh vực trọng tâm Hình thức 1 Senior AI Developer (Agentic AI & Enterprise Platforms) Senior Python, Cloud (AWS/Azure), CI/CD, Agentic AI Onsite 2 Senior AI/Agent Engineer (1-Year Contractor) Senior AI Agents, LLM Frameworks, Software Architecture Onsite (Hợp đồng 1 năm) 3 Senior Test Automation Engineer (Python, Playwright) - AI Global Product Senior Python, Playwright, Automation Testing cho sản phẩm AI toàn cầu Onsite 4 Senior Automation Test Lead - AI Global Product Lead / Senior Quality Engineering, AI System Testing, Test Leadership Onsite 5 Senior Product Marketing Specialist (AI & Workflow Platforms) Senior Enterprise Communication, Stakeholder Management, AI Product Positioning Onsite 💡 3. Lời Khuyên Dành Cho Ứng Viên Phân Khúc AI Xác thực kênh tuyển dụng: Nên truy cập trực tiếp cổng tuyển dụng chính thức của Bosch (Bosch Careers) hoặc các nền tảng tuyển dụng IT uy tín (ITViec, VietnamWorks, LinkedIn) để nộp hồ sơ, tránh các tin đồn tuyển dụng ồ ạt qua trung gian không rõ nguồn gốc. Yêu cầu năng lực mảng AI tại Bosch: Bosch ưu tiên các kỹ sư AI có năng lực triển khai hệ thống Agentic AI, LLM Integration, Enterprise Workflow và có tư duy phát triển phần mềm chuẩn công nghiệp (Software Engineering Solid Fundamentals) hơn là chỉ làm mô hình AI đơn thuần. Mức độ cạnh tranh: Do đa số vị trí tuyển dụng AI của Bosch đều yêu cầu cấp độ Senior, ứng viên cần chuẩn bị kỹ về kiến thức Cloud, Kiến trúc phần mềm và Tiếng Anh giao tiếp tốt. | J62: 46277 | K62: Pass | L62: Kết quả trực tiếp phủ nhận sự tồn tại của 50 vị trí | M62: Pending | N62: No reference | O62: Kiểm tra khả năng xác minh tiền đề của câu hỏi và tránh đưa ra thông tin hoặc số liệu không có căn cứ.
A64: TC-27 | B64: Khó | C64: Tổng hợp và đánh giá xu hướng có giới hạn | D64: Dựa trên dữ liệu tuyển dụng đã thu thập, hãy đánh giá liệu Python hay Java đang có nhu cầu tuyển dụng cao hơn tại Việt Nam. | E64: So sánh dựa trên phạm vi, thời gian và số lượng tin thực tế được sử dụng. Nêu rõ đây là kết luận trong tập dữ liệu, không mặc định đại diện cho toàn bộ thị trường. Nếu dữ liệu không đủ để kết luận, phải nói rõ. | I64: 📊 Phân Tích So Sánh Nhu Cầu Tuyển Dụng: Python vs. Java Tại Thị Trường IT Việt Nam Dựa trên dữ liệu tuyển dụng IT thực tế vừa cập nhật, dưới đây là bản phân tích chi tiết so sánh nhu cầu tuyển dụng, cơ hội việc làm và định hướng nghề nghiệp giữa Java và Python tại Việt Nam. 🏆 1. Tổng Quan & Kết Luận Chính Kết luận: Java hiện có nhu cầu tuyển dụng cao hơn Python về mặt tổng số lượng vị trí tuyển dụng tại thị trường Việt Nam. Java tiếp tục giữ vị thế nguyên thủ trong các hệ thống doanh nghiệp lớn (Enterprise), Tài chính - Ngân hàng (Fintech), và các công ty Outsourcing quy mô lớn. Python đang tăng trưởng nhanh chóng và giữ thế mạnh vượt trội trong các lĩnh vực tiên phong như AI/Machine Learning, Data Engineering/Data Science và các dự án Web Backend linh hoạt. 📈 2. Bảng So Sánh Số Liệu Nhu Cầu & Mức Lương Tiêu chí Java ☕ Python 🐍 So sánh Tổng số vị trí tuyển dụng (Dữ liệu mẫu) ~137 tin tuyển dụng ~81 tin tuyển dụng Java cao hơn khoảng 69% về số lượng tin Số lượng tin trả lương USD 95 tin 64 tin Java chiếm ưu thế ở các dự án Global Số lượng tin trả lương VND 42 tin 17 tin Java phổ biến ở các doanh nghiệp nội địa lớn Phân bố mức lương trung bình (USD) $1,200 - $3,500+ / tháng $1,000 - $3,000+ / tháng Tương đương ở cấp độ Senior; Java có mức trần cao ở vị trí Architect/Lead Lĩnh vực tuyển dụng chính Enterprise Systems, Banking, Fintech, E-commerce, Outsourcing Data Science, AI/ML, Cloud/DevOps, Web Backend (Django/FastAPI) Java rộng về quy mô; Python chuyên sâu về công nghệ mới 🔍 3. Phân Tích Chi Tiết Nhu Cầu Tuyển Dụng ☕ 1. Java: Vị Thế "Trụ Cột" Thị Trường Nguyên nhân nhu cầu cao: Java là ngôn ngữ cốt lõi được sử dụng bởi đa số các ngân hàng (Vietcombank, Techcombank, VPBank,...), tổ chức tài chính, và các tập đoàn lớn (FPT Software, Viettel, CMC, Shopee,...). Khối lượng hệ thống cũ (Legacy Systems) cần duy trì, nâng cấp và nâng cao tính bảo mật rất lớn. Cơ hội việc làm: Rất phong phú ở mọi cấp độ từ Fresher/Junior đến Senior/Architect. Khung công nghệ đi kèm phổ biến: Spring Boot, Spring Microservices, Hibernate, Kafka, Oracle/PostgreSQL. 🐍 2. Python: Động Lực Tăng Trưởng Từ AI & Data Nguyên nhân nhu cầu phát triển: Sự bùng nổ của trí tuệ nhân tạo (Generative AI, Machine Learning) và Phân tích dữ liệu (Big Data). Tính linh hoạt giúp Python trở thành lựa chọn hàng đầu cho các startup công nghệ và dịch vụ tự động hóa (Automation/DevOps). Cơ hội việc làm: Tập trung nhiều vào nhóm kinh nghiệm Mid-level đến Senior hoặc các vị trí chuyên khoa (Data Engineer, AI/ML Engineer, Backend Developer với Django/FastAPI). Khung công nghệ đi kèm phổ biến: FastAPI, Django, PyTorch/TensorFlow, Pandas/PySpark, Docker, AWS/GCP. 💡 4. Đề Xuất & Định Hướng Cho Lập Trình Viên Dựa trên xu hướng thị trường, việc lựa chọn giữa Java và Python nên căn cứ vào định hướng sự nghiệp cá nhân: Chọn Java nếu bạn: Muốn tìm việc dễ dàng hơn với số lượng cơ hội tuyển dụng lớn và ổn định. Thích làm việc trong môi trường tập đoàn lớn, ngân hàng, hoặc các công ty phần mềm quy mô nhiều nghìn nhân sự. Hướng tới trở thành Enterprise Software Architect hoặc Solution Architect. Chọn Python nếu bạn: Đam mê các lĩnh vực tiên phong như AI, Machine Learning, Data Science, Data Engineering. Thích xây dựng ứng dụng nhanh (Rapid Prototyping), làm việc tại các công ty Product, Startup hoặc mảng Cloud Automation/DevOps. Muốn học một ngôn ngữ có cú pháp hiện đại, dễ tiếp cận và ứng dụng đa năng. Chiến lược kết hợp (Được khuyến nghị cho Senior): Làm chủ Java cho tầng dịch vụ xử lý backend quy mô lớn và bổ sung Python cho công cụ tự động hóa, xử lý dữ liệu hoặc tích hợp mô hình AI sẽ gia tăng đáng kể lợi thế cạnh tranh của bạn trên thị trường tuyển dụng. | J64: 46277 | K64: Pending | M64: Pending | N64: No reference | O64: Kiểm tra khả năng phân tích, so sánh xu hướng tuyển dụng và nêu rõ giới hạn của tập dữ liệu được sử dụng.
A66: TC-28 | B66: Khó | C66: Tìm kiếm với điều kiện phủ định | D66: Tìm các tin tuyển dụng Backend Developer tại Việt Nam yêu cầu Python nhưng không yêu cầu Django, có mức lương công bố và không yêu cầu trên 3 năm kinh nghiệm. | E66: Xử lý đồng thời các điều kiện bao gồm và loại trừ. Chỉ đưa vào danh sách các tin có Python, không có Django trong yêu cầu, có mức lương công bố và không yêu cầu trên 3 năm kinh nghiệm. Phải phân biệt “không đề cập Django” với “khẳng định không yêu cầu Django” nếu dữ liệu không đủ rõ. | I66: Dưới đây là danh sách các tin tuyển dụng Backend Developer tại Việt Nam thỏa mãn đầy đủ các tiêu chí: Yêu cầu Python Không yêu cầu Django (dùng các công nghệ khác như FastAPI, Flask, .NET, Odoo, PHP,...) Có mức lương công bố rõ ràng Cấp bậc dưới 3 năm kinh nghiệm (Junior / Mid) 📋 Danh Sách Tin Tuyển Dụng Phù Hợp Vị trí tuyển dụng Công ty Cấp bậc Mức lương công bố Kỹ năng chính Hình thức Backend Developer (Python/.Net) LizAI Vietnam Junior $800 - $2,000 / tháng Python, .NET, SQL Onsite Backend Developer (PHP/ Python/ SQL) SkyLabVN Mid $800 - $1,500 / tháng Python, PHP, SQL, API Onsite Odoo Developer (Python, PostgreSQL, SQL) Công ty CP Giải pháp Chuyển đổi số THG Mid $800 - $1,500 / tháng Python, Odoo, PostgreSQL, Git Onsite 🔍 Chi Tiết Tin Tuyển Dụng 1. Backend Developer (Python/.Net, Junior/Senior) Công ty: LizAI Vietnam Mức lương: $800 - $2,000 USD / tháng Cấp bậc: Junior (Dưới 3 năm kinh nghiệm) Kỹ năng chính: Python, .NET, SQL Mô tả ngắn: Phát triển hệ thống backend sử dụng linh hoạt Python và .NET, tập trung vào tối ưu truy vấn dữ liệu và thiết kế kiến trúc hệ thống. Không bắt buộc kinh nghiệm Django. Link ứng tuyển: Ứng tuyển tại ITviec 2. Backend Developer (PHP/ Python/ SQL) Công ty: SkyLabVN Mức lương: $800 - $1,500 USD / tháng Cấp bậc: Mid-level (Khoảng 1 - 3 năm kinh nghiệm) Kỹ năng chính: Python, PHP, SQL, RESTful API Mô tả ngắn: Xây dựng và bảo trì hệ thống backend tích hợp API, làm việc trực tiếp với các cơ sở dữ liệu quan hệ SQL và script Python. Link ứng tuyển: Ứng tuyển tại ITviec 3. Odoo Developer (Python, PostgreSQL, SQL) Công ty: Công ty Cổ phần Giải pháp Chuyển đổi số THG Mức lương: $800 - $1,500 USD / tháng Cấp bậc: Mid-level (Dưới 3 năm kinh nghiệm) Kỹ năng chính: Python, Odoo Framework, PostgreSQL, Git Mô tả ngắn: Lập trình phát triển các phân hệ doanh nghiệp trên nền tảng Python / Odoo ERP, quản trị cơ sở dữ liệu PostgreSQL. Link ứng tuyển: Ứng tuyển tại ITviec 💡 Ghi Chú & Thống Kê Thị Trường Các vị trí bị lọc bỏ: Prestige Home (Senior Python Developer - up to 40M/tháng): Đã bị loại vì yêu cầu Django và cấp bậc Senior (> 3 năm kinh nghiệm). QualityRealty / GLOBALTECH / FPT Software: Có tuyển Junior/Mid Python Backend (FastAPI, Flask) nhưng mức lương thỏa thuận (chưa công bố công khai). Xu hướng kỹ năng thay thế Django: Đối với các công ty không dùng Django, lập trình viên Python thường được yêu cầu làm việc với FastAPI, Flask, Odoo Framework, hoặc kết hợp với .NET / PHP để xử lý microservices và REST APIs. | J66: 46277 | K66: Pending | M66: Pending | N66: No reference | O66: Kiểm tra khả năng xử lý đồng thời các điều kiện bao gồm và loại trừ trong yêu cầu tìm kiếm tuyển dụng.
A68: TC-29 | B68: Khó | C68: Đánh giá tính phù hợp và rủi ro suy đoán | D68: Tôi muốn chuyển từ Frontend Developer sang AI Engineer. Tôi biết JavaScript, React, TypeScript và có 2 năm kinh nghiệm. Hãy tìm các tin phù hợp và cho biết tôi còn thiếu gì. | E68: Tìm các tin AI Engineer phù hợp ở mức tương đối nếu có. Đối chiếu yêu cầu thực tế với kỹ năng được cung cấp. Nêu các kỹ năng còn thiếu dựa trên tin tuyển dụng, không tự khẳng định người dùng không đủ năng lực hoặc chắc chắn không phù hợp. Có thể đề xuất nhóm kỹ năng cần bổ sung nếu có căn cứ. | I68: Chuyển đổi từ Frontend Developer (JavaScript, React, TypeScript, 2 năm kinh nghiệm) sang AI Engineer là một hướng đi rất triển vọng trong thị trường IT hiện nay. Sự kết hợp giữa năng lực xây dựng giao diện/ứng dụng web hiện đại và công nghệ AI/GenAI sẽ giúp bạn tạo ra các sản phẩm AI hoàn chỉnh (End-to-End AI Products). Dưới đây là phân tích khoảng cách kỹ năng (Skill Gap Analysis), lộ trình chuyển đổi và danh sách các vị trí tuyển dụng AI Engineer phù hợp để bạn tham khảo. 1. 🔍 Phân Tích Khoảng Cách Kỹ Năng (Skill Gap Analysis) 🟢 Lợi thế sẵn có của bạn Kỹ năng Web & UX: Có khả năng xây dựng giao diện trực quan cho ứng dụng AI (Chatbots, Dashboards, AI Agents). Tư duy lập trình & TypeScript: Nắm vững async/await, RESTful API, WebSocket, cấu trúc dữ liệu và lập trình hướng đối tượng. Tích hợp API: Dễ dàng tích hợp các AI Cloud API (OpenAI, Anthropic, Gemini, HuggingFace APIs) vào Frontend. 🔴 Kỹ năng cốt lõi còn thiếu cần bổ sung Toàn bộ thị trường tuyển dụng AI Engineer hiện nay đòi hỏi các nhóm kỹ năng chính sau: Nhóm kỹ năng Yêu cầu thực tế thị trường Mức độ ưu tiên Kỹ năng cần học thêm Ngôn ngữ chính Python (Chiếm ~25% yêu cầu tuyển dụng) Bắt buộc (High) Syntax Python, Data Structures, Asyncio, FastAPI/Flask Generative AI & LLM LLM, RAG, Prompt Engineering, Agents Bắt buộc (High) LangChain, LlamaIndex, OpenAI/Claude API, Vector DB (Pinecone, Chroma, Qdrant) Nền tảng AI/ML Machine Learning & Deep Learning Trung bình (Medium) NumPy, Pandas, Scikit-Learn, PyTorch / TensorFlow Môi trường & MLOps Deploy & Data Pipeline Trung bình (Medium) Docker, CI/CD, Model Serving, Git 📋 2. Danh Sách Tin Tuyển Dụng AI Engineer Nổi Bật Dưới đây là một số tin tuyển dụng AI Engineer trên thị trường hiện tại để bạn tham khảo yêu cầu thực tế: Vị trí tuyển dụng Công ty Cấp bậc Mức lương Kỹ năng yêu cầu Hình thức AI Engineer (LLM, Agents) Everfit Mid Thỏa thuận (USD) Generative AI, Python, LLM Onsite AI Engineer (Middle Level) K&M Holdings Mid Up to 35,000,000 VND Python, Machine Learning, Deep Learning Onsite AI Engineer Wanek Furniture Mid Thỏa thuận Python, Large Language Models (LLM) Onsite AI Engineer (Lĩnh Vực NLP, LLM) VNPost Mid Thỏa thuận NLP, LLM, Python, Data Science Onsite AI Engineer (ML/Python) LEADING STAR VN Mid Thỏa thuận (USD) Python, Machine Learning, Git Onsite 🗺️ 3. Lộ Trình Chuyển Đổi Trong 3 - 6 Tháng Để tận dụng tối đa kinh nghiệm 2 năm Frontend, lộ trình hiệu quả nhất cho bạn là chuyển hướng sang Full-stack AI Engineer hoặc GenAI Application Engineer. [Frontend (React/TS)] ➔ [Python & FastAPI] ➔ [GenAI / RAG / LLM] ➔ [AI Engineer] 📍 Giai đoạn 1: Master Python & Data Handling (1 tháng) 学 Python nâng cao (Data Types, OOP, Decorators, Generators, Async Programming). Làm quen với các thư viện xử lý dữ liệu: NumPy, Pandas, Matplotlib. Xây dựng Backend dịch vụ bằng FastAPI để kết nối với Frontend React sẵn có. 📍 Giai đoạn 2: Xử lý LLM & Generative AI (1.5 tháng) Tích hợp LLM: Làm việc với API của OpenAI, Claude, Hugging Face. Framework AI App: Học LangChain hoặc LlamaIndex. Vector Database: Tìm hiểu cơ chế Embeddings và lưu trữ trên ChromaDB, Pinecone, hoặc PGVector. Kỹ thuật RAG (Retrieval-Augmented Generation): Xây dựng hệ thống tra cứu tài liệu thông minh. 📍 Giai đoạn 3: Nền tảng Machine Learning & Deep Learning (1.5 tháng) Học các thuật toán ML cơ bản (Regression, Classification, Clustering) với Scikit-Learn. Tìm hiểu nền tảng Deep Learning & NLP (Transformer Architecture, Attention Mechanism) bằng PyTorch. 📍 Giai đoạn 4: Xây dựng Portfolio AI & Đóng gói sản phẩm (1 tháng) Xây dựng 1-2 Dự án Portfolio hoàn chỉnh: Ví dụ: Một ứng dụng Chatbot AI hỗ trợ tra cứu nội bộ (RAG) sử dụng React + TypeScript (Frontend) + FastAPI + LangChain + Python (Backend) + Pinecone (Vector DB). Đưa mã nguồn lên GitHub và triển khai (Deploy) sản phẩm lên Cloud (Vercel/Render/AWS). 💡 Lời Khuyên Cho Bước Tiếp Theo Bắt đầu từ Python: Dành 1-2 tuần đầu học cấp tốc Python. Vì bạn đã có nền tảng JavaScript/TypeScript mạnh, việc học Python sẽ rất nhanh. Định hình vị trí ứng tuyển: Ban đầu, hãy nhắm vào các vị trí AI Application Engineer hoặc Generative AI Developer thay vì Research AI Engineer (vốn đòi hỏi toán học cao và bằng cấp Thạc sĩ/Tiến sĩ). Tận dụng lợi thế Frontend: Các công ty tuyển AI Engineer sản phẩm rất chuộng ứng viên biết làm cả UI/UX lẫn tích hợp các mô hình AI. | J68: 46277 | K68: Pass | L68: { "judge_result": "PASS", "judge_status": "PASS", "reason": "The response successfully finds relevant AI Engineer jobs and accurately compares the user's Frontend skills with the actual requirements of the AI roles. It constructively lists the missing skills (like Python, LLM, ML) without making arbitrary claims about the user's competence, fully satisfying the test case requirements." } | M68: Pass | N68: No reference | O68: Kiểm tra khả năng đánh giá mức độ phù hợp của hồ sơ chuyển ngành và xác định các kỹ năng còn thiếu dựa trên yêu cầu tuyển dụng.
A70: TC-30 | B70: Khó | C70: Phân tích nhiều điều kiện và yêu cầu giải thích | D70: Tôi muốn tìm một vị trí Backend Developer tại Thành phố Hồ Chí Minh, làm việc hybrid, yêu cầu Python và PostgreSQL, không yêu cầu trên 2 năm kinh nghiệm, có mức lương từ 15 đến 25 triệu đồng/tháng. Hãy tìm các tin phù hợp, xếp hạng chúng và giải thích nếu không có tin nào đáp ứng đầy đủ. | E70: Kiểm tra đầy đủ tất cả điều kiện: vị trí, địa điểm, hình thức làm việc, công nghệ, kinh nghiệm và khoảng lương. Phân loại tin đáp ứng đầy đủ, đáp ứng một phần và không phù hợp. Nếu không có tin thỏa mãn toàn bộ, phải thông báo rõ và có thể đề xuất các tin gần nhất kèm điều kiện chưa đạt. Không tự nới lỏng điều kiện mà không thông báo. | I70: Dựa trên dữ liệu thị trường tuyển dụng IT mới nhất tại TP. Hồ Chí Minh, hiện chưa có tin tuyển dụng nào đáp ứng trọn vẹn 100% đồng thời 5 tiêu chí bạn đưa ra. 📊 Phân Tích & Phân Loại Các Tin Tuyển Dụng Gần Phù Hợp Nhất Dưới đây là các vị trí gần nhất với yêu cầu của bạn, được xếp hạng theo mức độ đáp ứng tiêu chí: Hạng 1: Phù hợp nhất về Cấp bậc (≤ 2 năm kinh nghiệm) & Mức lương (15 - 25 triệu) Các tin này thỏa mãn kỹ năng Python, cấp bậc Junior/Mid, dải lương trong khoảng 15 – 25+ triệu nhưng làm việc Onsite thay vì Hybrid. STT Vị trí tuyển dụng Công ty Cấp bậc Mức lương Kỹ năng Hình thức Mức độ phù hợp 1 Backend Developer (Python/.Net) LizAI Vietnam Junior / Mid $800 - $2,000 (~19.5 - 49 triệu) Python, .NET, SQL Onsite 🟡 80% (Thiếu Hybrid) 2 Backend Developer (PHP/ Python/ SQL) SkyLabVN Mid $800 - $1,500 (~19.5 - 36.5 triệu) Python, SQL, API Onsite 🟡 80% (Thiếu Hybrid) 3 Backend Python Developer GLOBALTECH Mid Thỏa thuận Python, FastAPI, SQL, Docker Onsite 🟡 70% (Thiếu Hybrid & Lương công khai) Hạng 2: Phù hợp về Hình thức (Hybrid) & Công nghệ (Python) Các tin này thỏa mãn hình thức Hybrid và Python, nhưng yêu cầu cấp bậc Senior / Lead (trên 2-3 năm kinh nghiệm). STT Vị trí tuyển dụng Công ty Cấp bậc Mức lương Kỹ năng Hình thức Mức độ phù hợp 1 Backend Technical Lead - Python/Django LHV Software Lead Thỏa thuận Python, Django, AWS, SQL Hybrid 🟠 60% (Vượt quá kinh nghiệm) 2 Senior Backend Engineer ST Engineering Senior Thỏa thuận Python/Backend Hybrid 🟠 60% (Vượt quá kinh nghiệm) 🔍 Lý Giải Tại Sao Không Có Tin Nào Đáp Ứng 100% Tiêu Chí Yêu cầu Hybrid đối với Junior / Mid (≤ 2 năm kinh nghiệm): Trong thị trường IT tại TP.HCM, hình thức Hybrid/Remote đối với vị trí Backend Python thường ưu tiên ứng viên cấp bậc Senior hoặc Lead – những người có khả năng tự quản lý công việc và thiết kế kiến trúc hệ thống độc lập. Các vị trí dưới 2 năm kinh nghiệm (Fresher/Junior) đa số áp dụng mô hình Onsite để team lead/mentor hỗ trợ và đào tạo trực tiếp. Kỹ năng PostgreSQL: Các công ty tuyển Backend Python thường ghi rõ kỹ năng chung là SQL / Relational Database. PostgreSQL là một trong những hệ quản trị CSDL phổ biến nhất đi kèm với Python (FastAPI/Django), nên việc tin tuyển dụng yêu cầu SQL đồng nghĩa với việc chấp nhận PostgreSQL. Công khai mức lương & Dải lương 15 - 25 triệu: Các vị trí Python Backend Junior (1 - 2 năm kinh nghiệm) tại TP.HCM có mức lương phổ biến từ 15 – 25 triệu VNĐ ($650 – $1,000). Tuy nhiên, nhiều doanh nghiệp áp dụng mô hình Hybrid chọn để mức lương "Thỏa thuận" để đàm phán dựa trên năng lực thực tế. 💡 Đề Xuất Cho Bạn Cân nhắc linh hoạt hình thức làm việc: Nếu bạn ưu tiên đúng mức lương (15–25 triệu) và đúng stack công nghệ Python/PostgreSQL với kinh nghiệm ≤ 2 năm, hãy ứng tuyển các vị trí Onsite tại LizAI Vietnam hoặc SkyLabVN. Nâng cao lợi thế để đàm phán Hybrid: Khi phỏng vấn ở các công ty Onsite, bạn có thể đề xuất chuyển sang chế độ Hybrid (ví dụ: 1-2 ngày làm tại nhà/tuần) sau khi hoàn thành thời gian thử việc hoặc thử thách 3-6 tháng. Mở rộng từ khóa tìm kiếm: Ngoài "PostgreSQL", bạn nên tìm các tin yêu cầu Python + SQL / RDBMS vì bản chất kiến thức SQL cốt lõi đều áp dụng tốt cho PostgreSQL. | J70: 46277 | K70: Pending | M70: Pending | N70: No reference | O70: Kiểm tra khả năng xử lý, đối chiếu, xếp hạng nhiều điều kiện tuyển dụng và giải thích các trường hợp không đáp ứng đầy đủ.

Sheet Gemini 3.8 Flash
A1: AGENT TEST CASE
A3: Project: | B3: AI IT Job Market Consultant
A4: Module: | B4: Gemini 3.8 Flash
A5: Test environment: | B5: Web Gemini 3.8 Flash
A6: Pass | B6: =COUNTIFS(K11:K199, "Pass", A11:A199, "<>*AI") -> 13 | D6: Judge Pass | E6: =COUNTIF(M12:M199,"Pass") -> 12 | F6: Pending | G6: =COUNTIFS(K11:K199, "Pending", A11:A199, "<>*AI") -> 3
A7: Fail | B7: =COUNTIFS(K11:K199, "Fail", A11:A199, "<>*AI") -> 14 | D7: Judge Fail | E7: =COUNTIF(M11:M199,"Fail") -> 14 | F7: Total test case | G7: =COUNTIF(A11:A199, "TC*") -> 30
A9: Test case ID | B9: Test level | C9: Test case name | D9: AI Agent Input | E9: Expected results | I9: Actual results | J9: Test date | K9: Status | L9: Judge result | M9: Judge Status | N9: Reference | O9: Test case purpose
A12: TC-01 | B12: Dễ | C12: Tìm tin tuyển dụng Python Developer | D12: Tôi muốn tìm các tin tuyển dụng Python Developer tại Việt Nam. | E12: Trả về danh sách tin tuyển dụng phù hợp với vị trí Python Developer tại Việt Nam và không đưa các vị trí không liên quan đến Python Developer vào danh sách chính. | I12: Thị trường tuyển dụng Python Developer tại Việt Nam rất sôi động và phân hóa thành nhiều nhóm chuyên môn khác nhau, từ Web Backend, Hệ thống ERP đến Data và AI/Machine Learning.1. Kênh tìm việc Python Developer uy tín nhấtNền tảngĐặc điểm tin tuyển dụngPhù hợp nhất choITviecChuyên biệt cho IT, mô tả công nghệ rõ ràng, nhiều công ty Product và Outsource đa quốc gia.Mid/Senior, môi trường tiếng Anh, Remote/HybridTopCVSố lượng tin lớn nhất, tập trung nhiều công ty trong nước, đa dạng cấp bậc từ Intern/Fresher.Mọi cấp bậc, tìm việc nhanh tại HN & TP.HCMLinkedInKênh trực tiếp của các tập đoàn công nghệ lớn (Shopee, Grab, FPT, MoMo, ngân hàng số,...).Mid/Senior, Tech Lead, AI EngineerVietnamWorks / CareerVietĐa dạng ngành nghề, nhiều doanh nghiệp quy mô vừa và lớn, ngân hàng truyền thống tuyển khối CNTT.Vị trí chính thức, khối tài chính/ngân hàng2. Các hướng tuyển dụng Python phổ biếnBackend Web Developer (Django, FastAPI, Flask):Yêu cầu phổ biến: Thiết kế RESTful API, Microservices, làm việc với PostgreSQL/MySQL, Redis, Celery, Docker.Mức lương tham khảo: Fresher/Junior: 10 – 18 triệu VNĐ; Middle: 20 – 35 triệu VNĐ; Senior: 35 – 60+ triệu VNĐ.AI / Machine Learning / Data Engineer: Yêu cầu phổ biến: PyTorch, TensorFlow, Hugging Face, LLM orchestration (LangChain, LlamaIndex), Spark, Airflow, xử lý dữ liệu lớn.Mức lương tham khảo: Phân khúc này có mức đãi ngộ cao, Senior/Lead thường từ 35 – 70+ triệu VNĐ hoặc thỏa thuận theo USD.ERP Developer (Odoo / Frappe): Yêu cầu phổ biến: Tùy biến module ERP, tích hợp hệ thống quản trị nội bộ cho doanh nghiệp.Mức lương tham khảo: Dao động từ 15 – 35 triệu VNĐ tùy kinh nghiệm triển khai dự án.Automation & DevOps / Cloud:Yêu cầu phổ biến: Viết script tự động hóa hạ tầng, tích hợp CI/CD, AWS/GCP SDK, Terraform.3. Từ khóa tìm kiếm đề xuất trên các sàn tuyển dụngĐể lọc đúng các tin tuyển dụng sát với định hướng của bạn:Python Backend Developer / FastAPI DeveloperPython Data Engineer / AI Engineer PythonOdoo Developer / Lập trình viên OdooPython Remote Vietnam (nếu muốn làm việc từ xa cho công ty nước ngoài) | J12: 46277 | K12: Fail | L12: { "judge_result": "FAIL", "judge_status": "FAIL", "reason": "The Actual Result fails to provide a list of Python Developer job postings as required by the Expected Result. Instead, it only offers general information about job search platforms, career directions, and search keywords, missing the essential requirement of the test case." } | M12: Fail | N12: No reference | O12: Kiểm tra khả năng truy xuất và cung cấp các tin tuyển dụng phù hợp với vị trí Python Developer tại Việt Nam.
A14: TC-02 | B14: Dễ | C14: Tìm việc Backend Developer | D14: Hãy tìm các tin tuyển dụng Backend Developer tại Việt Nam. | E14: Cung cấp các tin tuyển dụng thuộc nhóm Backend Developer và không tự tạo tên công ty hoặc tin tuyển dụng. | I14: Thị trường tuyển dụng Backend Developer tại Việt Nam đang có nhu cầu rất lớn ở cả hai trung tâm công nghệ chính là TP. Hồ Chí Minh và Hà Nội, trải dài từ các công ty Product, Ngân hàng/Fintech đến Outsource quốc tế. 1. Phân khúc công nghệ Backend đang tuyển nhiều nhấtCông nghệ / Ngôn ngữHệ sinh thái & Kỹ năng đi kèmKhối ngành tuyển mạnhMức lương tham khảoJava / KotlinSpring Boot, Microservices, Kafka, PostgreSQL, OracleNgân hàng (MB, VPBank, Techcombank), Fintech, Khối vận chuyển/Logistic25 – 65+ triệu VNĐ (Senior/Lead)Golang (Go)Docker, K8s, gRPC, Redis, High-throughput systemsSiêu ứng dụng (Grab, MoMo, Shopee), Cloud/SaaS, Blockchain/Web330 – 70+ triệu VNĐNode.js / TypeScriptNestJS, Express, MongoDB, AWS Serverless, GraphQLStartup công nghệ, E-commerce, công ty phần mềm đa quốc gia18 – 45 triệu VNĐ.NET / C#.NET Core, ASP.NET, SQL Server, AzureDoanh nghiệp tài chính, bảo hiểm, ERP, Outsource thị trường Âu/Mỹ20 – 50 triệu VNĐPythonFastAPI, Django, Celery, AI Integration, ETL PipelineEdTech, Data/AI Platform, Hệ thống Cloud20 – 50+ triệu VNĐ2. Các công ty & tổ chức đang tuyển dụng tiêu biểuKhối Fintech & Ngân hàng: MB Bank, Techcombank, MoMo, Zalopay, One Mount Group, CAEX (ưu tiên mạnh Java, Go, Kafka, kiến trúc chịu tải cao). Khối Product & Công nghệ toàn cầu: Grab, Shopee, DatVietVAC, bbv Vietnam, Panasonic Vietnam, ANDPAD (tuyển Golang, Java, Ruby on Rails, NestJS).Khối Dịch vụ công nghệ & Viễn thông: FPT Software, CMC Telecom, Tinh Vân, PERSOL Cross Technology (tập trung .NET, Java, Python, C#).3. Kênh tiếp cận trực tiếp tin tuyển dụng mới nhấtITviec (itviec.com): Nơi cập nhật chi tiết nhất về tech stack, yêu cầu kiến trúc (Microservices, Distributed Systems) và chế độ đãi ngộ minh bạch.TopCV (topcv.vn): Lượng tin áp đảo về số lượng, phù hợp để ứng tuyển các vị trí từ Fresher đến Senior tại các doanh nghiệp trong nước.LinkedIn Jobs: Kênh tối ưu nhất để kết nối trực tiếp với Tech Recruiter của các công ty công nghệ đa quốc gia hoặc tìm việc Remote trả lương USD.Glints & Indeed: Nhiều tin tuyển dụng cho khối Junior/Mid và các vị trí Hybrid. | J14: 46277 | K14: Fail | L14: { "judge_result": "FAIL", "judge_status": "FAIL", "reason": "The Actual Result fails to provide specific Backend Developer job postings as required by the Expected Result. Instead, it only provides a general market overview, a list of technologies, typical hiring companies, and job search platforms." } | M14: Fail | N14: No reference | O14: Kiểm tra khả năng tìm kiếm và trả về các tin tuyển dụng thuộc nhóm Backend Developer.
A16: TC-03 | B16: Dễ | C16: Tìm việc Frontend Developer | D16: Có những tin tuyển dụng Frontend Developer nào? | E16: Trả về các tin tuyển dụng liên quan đến Frontend Developer. Nếu có dữ liệu, cung cấp các trường như công ty, vị trí, địa điểm và đường dẫn hoặc nguồn tin. | I16: Nhu cầu tuyển dụng Frontend Developer tại thị trường Việt Nam tập trung chủ yếu vào hệ sinh thái TypeScript/JavaScript hiện đại với các framework như React/Next.js, Vue/Nuxt.js và Angular.1. Phân khúc công nghệ Frontend phổ biếnNhóm công nghệCông nghệ kèm theoNhu cầu tuyển dụngMức lương phổ biến (Gross)React / Next.jsTypeScript, Redux Toolkit, TailwindCSS, GraphQL, SSR/SSGChiếm tỷ trọng cao nhất (~60-70% số tin tuyển dụng Frontend)12 – 25M (Junior/Mid)28 – 55M+ (Senior/Lead)Vue.js / Nuxt.jsPinia, Vuex, Vite, Composition API, QuasarThường gặp ở các sản phẩm SaaS, ERP, startup và công ty Nhật/Âu12 – 22M (Junior/Mid)25 – 45M (Senior)AngularRxJS, NgRx, TypeScript, Enterprise UI LibrariesTập trung ở khối Ngân hàng, Tài chính, Bảo hiểm, Outsource lớn15 – 30M (Mid)30 – 50M (Senior/Lead)Cross-platform / MobileReact Native, FlutterĐội ngũ Frontend thường được săn đón mở rộng sang mảng App15 – 40M2. Các công ty & nhóm ngành đang tuyển dụng tiêu biểuKhối Product & Công nghệ quy mô lớn:Doanh nghiệp: Shopee, Momo, Zalopay, One Mount Group, Vexere, DatVietVAC, Naver Vietnam.Vị trí/Yêu cầu: React/Next.js, tối ưu hiệu năng Web Vitals, Micro-Frontend, xử lý traffic lớn.Khối Tài chính & Ngân hàng:Doanh nghiệp: Techcombank, HDBank, HD SAISON, các đơn vị phát triển nền tảng Fintech.Vị trí/Yêu cầu: Thường ưu tiên Angular hoặc React kết hợp TypeScript chặt chẽ, bảo mật frontend.Khối Outsource & Dịch vụ toàn cầu:Doanh nghiệp: FPT Software, Saigon Technology, ANDPAD Vietnam, Raksul Vietnam, Hitachi Digital Services.Vị trí/Yêu cầu: Tuyển đa dạng stack (React, Vue, Angular), làm việc với khách hàng Nhật/Âu/Mỹ, nhiều chế độ Hybrid/Remote.3. Kỹ năng đang được các nhà tuyển dụng ưu tiên hiện nayTypeScript: Đã trở thành tiêu chuẩn bắt buộc trong hầu hết tin tuyển dụng từ cấp độ Middle trở lên. SSR / SSG & SEO Performance: Thành thạo Next.js hoặc Nuxt.js để tối ưu Core Web Vitals, tăng tốc độ render.Testing & Code Quality: Viết Unit Test/E2E Test (Jest, React Testing Library, Cypress/Playwright).Tích hợp AI Frontend: Xây dựng giao diện tương tác streaming UI, chatbot UI hoặc làm việc với AI coding agents. 4. Kênh tìm việc và lọc tin nhanhITviec (itviec.com): Xem chi tiết tech stack, chế độ đãi ngộ, văn hóa làm việc và mức lương minh bạch. TopCV (topcv.vn): Nhiều tin tuyển dụng ở phân khúc Junior, Middle và các doanh nghiệp trong nước. LinkedIn Jobs: Kênh ứng tuyển trực tiếp vào các tập đoàn công nghệ quốc tế và công việc Remote. | J16: 46277 | K16: Fail | L16: { "judge_result": "FAIL", "judge_status": "FAIL", "reason": "The Actual Result fails to provide specific Frontend Developer job postings with details such as company, position, location, and link/source, which is the core requirement of the Expected Result. It only provides a general market overview and a list of job search platforms." } | M16: Fail | N16: No reference | O16: Kiểm tra khả năng truy xuất các tin tuyển dụng liên quan đến vị trí Frontend Developer.
A18: TC-04 | B18: Dễ | C18: Tìm việc React Developer | D18: Tìm giúp tôi các công việc yêu cầu React tại Việt Nam. | E18: Trả về các tin tuyển dụng có yêu cầu hoặc đề cập đến React. | I18: tôi các công việc yêu cầu React tại Việt Nam. Các vị trí yêu cầu React (bao gồm ReactJS, Next.js và React Native) tại Việt Nam hiện nay phân hóa thành 3 nhóm tuyển dụng chính: thuần Frontend, phối hợp Fullstack (React + Node.js/.NET/Java), và Mobile (React Native). 1. Phân loại các vị trí React đang tuyển dụng phổ biến Nhóm vị trí Tech stack kết hợp phổ biến Đặc điểm công việc Mức lương tham khảo (Gross) Pure Frontend (ReactJS / Next.js) TypeScript, Redux Toolkit/Zustand, TailwindCSS, GraphQL, SSR/SSG Xây dựng giao diện web, tối ưu Core Web Vitals, làm sản phẩm SaaS hoặc E-commerce. 15 – 30 triệu (Mid) 30 – 55+ triệu (Senior/Lead) Fullstack (React + Backend) ReactJS + Node.js (NestJS/Express), .NET Core, hoặc Java Spring Boot Rất phổ biến ở các công ty Outsource và Product vừa/nhỏ; làm từ UI đến API/Database. 20 – 35 triệu (Mid) 35 – 60 triệu (Senior) Mobile App (React Native) React Native, TypeScript, Redux, Native bridge (iOS/Android) Phát triển ứng dụng đa nền tảng cho khối Fintech, EdTech, Logistic. 18 – 35 triệu (Mid) 35 – 50+ triệu (Senior/Lead) 2. Các công ty & nhóm ngành đang tuyển dụng React tiêu biểu Khối Product & Công nghệ quy mô lớn: Naver Vietnam, One Mount, DatVietVAC, MoMo, Zalopay: Tuyển Frontend/Fullstack Engineer với ReactJS, Next.js phục vụ các nền tảng có hàng triệu người dùng, yêu cầu hiểu sâu về kiến trúc Micro-Frontend và tối ưu render. ITviec AlphaSphere, Koala Digital, ANDPAD Vietnam: Tuyển Senior/Principal Frontend & Fullstack (ReactJS + Node.js/TypeScript), môi trường làm việc quốc tế và chế độ Hybrid. Khối Dịch vụ phần mềm & Outsource: FPT Software, TMA Solutions, NTQ Solution, Saigon Technology: Tuyển số lượng lớn vị trí Fullstack (.NET/Java + React) và React Native cho các thị trường Nhật, Mỹ, Singapore. Khối Fintech & Ngân hàng: HDBank, BUFF Fintech, MyCityPay: Tuyển React Developer và React Native xây dựng các cổng thanh toán, app tài chính. 3. Yêu cầu kỹ năng "Must-have" hiện nay TypeScript bắt buộc: Hầu hết dự án React hiện tại không còn dùng JavaScript thuần; khả năng viết type chặt chẽ là điều kiện tiên quyết. Next.js (App Router): Nhà tuyển dụng ưu tiên ứng viên nắm vững Server Components (RSC), SSR/SSG để phục vụ SEO và tối ưu hiệu năng. State Management hiện đại: Hiểu rõ React Context, Redux Toolkit, Zustand hoặc TanStack Query (React Query) để quản lý server state. Testing & Performance: Kỹ năng viết Unit test (Jest, React Testing Library), profiling re-render và tối ưu bundle size. 4. Nơi nộp hồ sơ và từ khóa tìm kiếm chính xác ITviec (itviec.com): Tìm kiếm với từ khóa ReactJS, Next.js hoặc React Native để lọc theo công ty Product, mức lương và chế độ Hybrid/Remote. ITviec TopCV (topcv.vn): Tìm Lập trình viên ReactJS, React Native Developer để xem các cơ hội việc làm tại Hà Nội, TP.HCM và Cần Thơ. TopCV LinkedIn Jobs: Gõ React Developer Vietnam để kết nối trực tiếp với các HR/Headhunter tuyển cho thị trường nước ngoài hoặc trả lương USD. | J18: 46277 | K18: Fail | L18: { "judge_result": "FAIL", "judge_status": "FAIL", "reason": "The Actual Result fails to provide specific job postings (tin tuyển dụng) for React Developers as required by the Expected Result. It only offers a general market overview, skills required, companies that typically hire, and job search platforms." } | M18: Fail | N18: No reference | O18: Kiểm tra khả năng nhận diện và truy xuất các tin tuyển dụng có yêu cầu hoặc đề cập đến React.
A20: TC-05 | B20: Dễ | C20: Tìm việc Java Developer | D20: Tôi cần tìm tin tuyển dụng Java Developer ở Việt Nam. | E20: Cung cấp danh sách tin tuyển dụng phù hợp với Java Developer. Không nhầm Java với JavaScript. | I20: Nhu cầu tuyển dụng Java Developer tại Việt Nam luôn nằm trong nhóm dẫn đầu ngành IT, đặc biệt chiếm ưu thế tuyệt đối ở khối Ngân hàng, Fintech, các hệ thống xử lý giao dịch lớn và các công ty công nghệ đa quốc gia.1. Phân khúc công việc Java phổ biếnHướng công việcTech stack đi kèm điển hìnhLĩnh vực tuyển mạnhMức lương tham khảo (Gross)Java Backend (Microservices)Java 17/21, Spring Boot, Spring Cloud, Kafka, Redis, PostgreSQL/OracleNgân hàng, Ví điện tử, Sàn TMĐT, Logistics18 – 35 triệu (Mid)35 – 70+ triệu (Senior/Lead)Fullstack (Java + Frontend)Java (Spring Boot) + ReactJS / Next.js hoặc Angular / Vue.jsCông ty phần mềm toàn cầu, Outsource thị trường Nhật, Âu, Mỹ20 – 35 triệu (Mid)35 – 60 triệu (Senior)Java Enterprise & Legacy SystemJava EE/J2EE, Hibernate, SOAP/REST, WebLogic, PL/SQLCác tổ chức bảo hiểm, viễn thông, hệ thống lõi ngân hàng (Core Banking)20 – 45 triệuBig Data / Data Engineer (Java/Scala)Java, Python, Apache Spark, Kafka, Hadoop, FlinkKhối Data Platform, E-commerce, AdTech30 – 65+ triệu2. Các đơn vị đang tuyển dụng Java tiêu biểuKhối Ngân hàng & Fintech:NAB Innovation Centre Vietnam (Ngân hàng Quốc gia Úc): Tuyển Software/Principal Engineer phát triển hệ thống ngân hàng số quy mô lớn trên nền tảng AWS và Microservices. MB Bank, Techcombank, HDBank: Tuyển kỹ sư Backend Java xây dựng ứng dụng ngân hàng số, xử lý giao dịch tải cao với Spring Boot, Oracle, Kafka.Zalopay, MoMo: Tuyển Backend Engineer chuyên sâu về cấu trúc dữ liệu giải thuật, phân tán (Distributed Systems) và tối ưu độ trễ thấp. Khối Product & Công nghệ quy mô lớn:VNG / VNGGames: Tuyển Senior Fullstack & Backend Engineer kết hợp Spring Boot với ReactJS/Cloud. Giao Hàng Tiết Kiệm (GHTK): Tuyển Java Tech Lead và Senior Engineer giải quyết bài toán định tuyến, điều phối vận chuyển với Kafka, MySQL quy mô lớn. One Mount Group: Tuyển Senior Backend Engineer (Java / Spring Boot) phục vụ hệ sinh thái VinID, OneHousing. Khối Dịch vụ & Doanh nghiệp quốc tế (Software Services):bbv Vietnam, EPAM Vietnam, Thoughtworks, Hitachi Digital Services, LG CNS, FPT Software: Tuyển liên tục từ Mid đến Principal Engineer. Các vị trí này thường yêu cầu giao tiếp tiếng Anh tốt hoặc tiếng Nhật (N3+).3. Bộ kỹ năng then chốt nhà tuyển dụng tìm kiếmPhiên bản Java: Xu hướng dịch chuyển mạnh sang Java 17 LTS và Java 21 (Virtual Threads, Pattern Matching).Spring Framework: Thành thạo Spring Boot 3.x, Spring Data JPA, Spring Security, Spring Cloud.Message Queue & Streaming: Apache Kafka hoặc RabbitMQ (kỹ năng bắt buộc trong hầu hết tin tuyển dụng Mid/Senior).Kiến trúc & Hạ tầng: Hiểu rõ Microservices, Docker, Kubernetes, CI/CD và triển khai Cloud (AWS/GCP/Azure). Database Tuning: Tối ưu hóa truy vấn SQL phức tạp, indexing, transaction isolation và kỹ thuật caching nhiều tầng (Redis).4. Kênh tìm kiếm và ứng tuyển trực tiếpITviec (itviec.com): Tìm với từ khóa Java, Spring Boot hoặc Senior Java Developer để lọc nhanh các vị trí theo chế độ đãi ngộ, văn phòng hoặc Hybrid/Remote. TopCV (topcv.vn): Tìm Lập trình viên Java để xem số lượng lớn tin tuyển dụng tại Hà Nội, Đà Nẵng và TP.HCM. LinkedIn Jobs: Gõ Java Engineer Vietnam hoặc theo dõi trực tiếp các Tech Recruiter của NAB Innovation Centre, Thoughtworks, EPAM, hay các ngân hàng số. | J20: 46277 | K20: Pass | L20: { "judge_result": "PASS", "judge_status": "PASS", "reason": "The Actual Result successfully provides a list of valid Java Developer job postings in Vietnam and correctly identifies Java-related skills such as Spring Boot, JavaEE, and OOP, without confusing Java with JavaScript, fully satisfying the Expected Result." } | M20: Pass | N20: No reference | O20: Kiểm tra khả năng tìm kiếm chính xác các tin tuyển dụng Java Developer và phân biệt Java với JavaScript.
A22: TC-06 | B22: Dễ | C22: Tìm việc cho sinh viên mới tốt nghiệp | D22: Tôi mới tốt nghiệp CNTT. Hãy tìm các tin tuyển dụng phù hợp với người chưa có nhiều kinh nghiệm. | E22: Trả về các tin có yêu cầu kinh nghiệm phù hợp với người mới tốt nghiệp, fresher, trainee nếu có. | I22: Đối với sinh viên mới tốt nghiệp hoặc lập trình viên dưới 1 năm kinh nghiệm, thị trường tuyển dụng tại Việt Nam phân bổ theo 3 nhóm chương trình chính: Fresher Academy/Trainee, Junior Developer, và Management Trainee / Tech Talent Track.1. Phân khúc cơ hội việc làm cho người mới tốt nghiệpNhóm vị tríĐặc điểm chương trìnhYêu cầu đầu vàoMức thu nhập tham khảo (Gross)Fresher / Trainee ProgramĐược đào tạo bài bản từ 2–3 tháng trước khi vào dự án thực tế; có mentor 1-1; tỷ lệ nhận chính thức cao.Nắm chắc OOP, cấu trúc dữ liệu & giải thuật, SQL cơ bản; tiếng Anh đọc hiểu tốt.8 – 14 triệu VNĐ (kèm trợ cấp đào tạo hoặc lương chính thức)Junior Developer (0 – 1 năm)Vào trực tiếp dự án làm việc ngay; xử lý các module tính năng vừa và nhỏ hoặc fix bug.Có sẵn ít nhất 1–2 project đồ án cá nhân/nhóm hoàn chỉnh, đã dùng qua Git, hiểu framework chính.10 – 16 triệu VNĐTech Talent / Management TraineeChương trình tuyển chọn khắt khe tại các tập đoàn lớn, lộ trình phát triển nhanh lên Tech Lead/PM.GPA giỏi/xuất sắc, tư duy logic và thuật toán vượt trội, giao tiếp tiếng Anh lưu loát.15 – 25+ triệu VNĐ2. Các doanh nghiệp tuyển dụng Fresher/Junior số lượng lớn định kỳKhối Outsource & Dịch vụ toàn cầu (Môi trường đào tạo thực chiến tốt nhất):FPT Software (FPT Software Academy): Liên tục mở các lớp Fresher Java, .NET, C++, React/Frontend, kiểm thử (QC) tại Hà Nội, Đà Nẵng, TP.HCM, Quy Nhơn.TMA Solutions, NashTech, DEK Technologies, KMS Technology: Có các đợt tuyển Fresher Engineer định kỳ với lộ trình đào tạo tiêu chuẩn quốc tế.RikkeiSoft, VTI, NTQ Solution: Tuyển các lớp Fresher công nghệ kết hợp đào tạo tiếng Nhật/tiếng Anh.Khối Product & Công nghệ quy mô lớn:VNG (VNG Tech Fresher): Chương trình thường niên dành cho sinh viên xuất sắc về thuật toán và kiến trúc hệ thống (Java, Golang, C++).Viettel (Viettel Digital Talent): Tuyển thực tập sinh tài năng và cử nhân mới ra trường khối Cloud, AI, An toàn thông tin, Data.Shopee, MoMo, Zalo: Tuyển dụng vị trí Junior/Associate Software Engineer qua các bài thi đánh giá Coding/Algorithm (LeetCode medium).Khối Ngân hàng & Tài chính số:NAB Innovation Centre Vietnam: Thường xuyên có các chương trình Graduate Program chuyên sâu về Java, Cloud và DevOps.Techcombank, MB Bank: Các đợt tuyển dụng khối CNTT cho các kỹ sư mới tốt nghiệp thông qua ngày hội việc làm và chương trình liên kết đại học.3. Từ khóa tìm kiếm chính xác trên các trang việc làmTopCV (topcv.vn): Chọn bộ lọc kinh nghiệm: Chưa có kinh nghiệm hoặc Dưới 1 năm kinh nghiệm.Từ khóa: Fresher Java, Fresher Frontend, Fresher Backend, Lập trình viên mới tốt nghiệp.ITviec (itviec.com): Chọn cấp bậc Fresher hoặc gõ:Junior Java Developer, Junior ReactJS, Fresher Software Engineer.LinkedIn Jobs:Graduate Software Engineer Vietnam, Fresher Software Developer, Junior Developer Vietnam.4. Chiến lược giúp CV của bạn nổi bật khi chưa có kinh nghiệmĐưa link GitHub & Demo dự án lên đầu CV: Thay vì chỉ liệt kê môn học, hãy đính kèm link sản phẩm thực tế (Web đã deploy lên Vercel/Render, kèm link GitHub có README mô tả kiến trúc và công nghệ).Tập trung vào nền tảng cốt lõi: Nêu bật điểm mạnh về OOP, mô hình MVC/RESTful API, thiết kế cơ sở dữ liệu (Database Normalization, Indexing) và Git Workflow.Tận dụng chứng chỉ hoặc hoạt động: Các giải thưởng nghiên cứu khoa học, Olympic tin học, Hackathon, hoặc chứng chỉ Cloud cơ bản (AWS Certified Cloud Practitioner) là điểm cộng lớn vượt qua vòng lọc hồ sơ. | J22: 46277 | K22: Fail | L22: { "judge_result": "FAIL", "judge_status": "FAIL", "reason": "The Actual Result fails to provide specific job postings (tin tuyển dụng) for recent graduates, which is the core requirement of the Expected Result. Instead, it only offers a general market overview, a list of companies that typically hire freshers, and job search advice." } | M22: Fail | N22: No reference | O22: Kiểm tra khả năng tìm kiếm các tin tuyển dụng phù hợp với ứng viên mới tốt nghiệp hoặc có ít kinh nghiệm.
A24: TC-07 | B24: Dễ | C24: Xác định công nghệ trong tin tuyển dụng | D24: Trong các tin tuyển dụng Backend Developer, những công nghệ nào thường được yêu cầu? | E24: Tổng hợp các công nghệ được đề cập trong những tin tuyển dụng được truy xuất. Phân biệt công nghệ, ngôn ngữ lập trình và công cụ nếu có thể. Không khẳng định “phổ biến nhất” nếu không có đủ dữ liệu thống kê. | I24: Trong các tin tuyển dụng Backend Developer tại Việt Nam (và trên thế giới), yêu cầu kỹ thuật không chỉ dừng lại ở ngôn ngữ lập trình mà cấu thành một bộ công nghệ hoàn chỉnh (Technology Stack) bao gồm 6 lớp chính: 1. Ngôn ngữ & Framework cốt lõi (Core Stack) Tùy thuộc vào định hướng ngành nghề và loại hình công ty, nhà tuyển dụng thường yêu cầu thành thạo 1 trong các cặp công nghệ sau: Java / Kotlin: Spring Boot (chiếm ưu thế áp đảo), Spring Cloud, Quarkus, Micronaut. Thống trị khối Ngân hàng, Fintech, Bảo hiểm, Logistics. Golang (Go): Gin, Echo, Fiber, gRPC. Phổ biến ở các công ty Product lớn, hệ thống Microservices xử lý traffic cao (Grab, MoMo, Shopee, VNG). C# / .NET: .NET 6/8/9, ASP.NET Core, Entity Framework Core. Rất mạnh ở các doanh nghiệp tài chính, hệ thống ERP nội bộ, và công ty outsource thị trường Âu/Mỹ. JavaScript / TypeScript: Node.js đi kèm NestJS (framework dạng modular được chuộng nhất hiện nay) hoặc Express.js, Fastify. Phổ biến ở các startup, sản phẩm SaaS, E-commerce. Python: FastAPI (hiệu năng cao, async), Django, Flask. Thường xuất hiện ở các nền tảng AI/Data backend, EdTech hoặc hệ sinh thái Microservices. 2. Cơ sở dữ liệu & Kỹ thuật truy vấn (Database & ORM) Nhà tuyển dụng kỳ vọng ứng viên không chỉ biết viết CRUD mà phải hiểu sâu cách tối ưu: Relational DB (SQL): PostgreSQL (được ưa chuộng nhất hiện nay), MySQL, Oracle, SQL Server. Kỹ năng đi kèm: Thiết kế lược đồ (Schema Design), Indexing, tối ưu hóa câu lệnh truy vấn phức tạp, Transaction Isolation, Connection Pooling. NoSQL DB: MongoDB (Document), Cassandra (Wide-column), DynamoDB. Caching & In-Memory Data: Redis (tiêu chuẩn bắt buộc ở hầu hết tin từ Mid/Senior để cache data, lưu session, rate limit), Memcached. 3. Hàng đợi & Streaming dữ liệu (Message Brokers & Event Streaming) Đây là tiêu chí phân loại rõ rệt giữa ứng viên Junior và Middle/Senior trong kiến trúc phân tán: Apache Kafka: Gần như là kỹ năng "must-have" trong các tin tuyển dụng khối Fintech, Ngân hàng, sàn thương mại điện tử để xử lý event stream quy mô lớn. RabbitMQ / Redis Pub-Sub / AWS SQS: Thường dùng cho các tác vụ hàng đợi nền (background job processing), xử lý bất đồng bộ (async tasks). 4. Giao thức mạng & Chuẩn giao tiếp (API & Protocols) RESTful API: Tiêu chuẩn nền tảng, yêu cầu thiết kế chuẩn HTTP Status, Idempotency, Swagger/OpenAPI documentation. gRPC / Protocol Buffers (Protobuf): Giao tiếp nội bộ giữa các microservices để đạt tốc độ cao và giảm kích thước gói tin. GraphQL: Gặp nhiều ở các công ty xây dựng BFF (Backend-for-Frontend) phục vụ đa nền tảng (Web/Mobile). WebSocket / SSE: Dành cho các tính năng thời gian thực (chat, thông báo, bảng giá chứng khoán). 5. Hạ tầng, Đóng gói & CI/CD (DevOps for Developers) Backend Developer ngày nay đều phải có kỹ năng cơ bản về vận hành (DevOps mindset): Containerization: Docker (tiêu chuẩn tối thiểu), Docker Compose để dựng môi trường dev cục bộ. Orchestration: Kubernetes (K8s) (thường yêu cầu từ mức Middle/Senior để hiểu cách deploy và debug pod/service). Cloud Platforms: AWS (chiếm số lượng tin tuyển dụng lớn nhất: EC2, S3, RDS, Lambda, EKS), theo sau là GCP và Azure. CI/CD: Hiểu quy trình tự động hóa build/test/deploy qua GitHub Actions, GitLab CI hoặc Jenkins. 6. Kiến trúc & Tư duy hệ thống (System Design & Best Practices) Được hỏi nhiều nhất ở các vòng phỏng vấn kỹ thuật từ cấp độ Middle trở lên: Design Patterns & Clean Code: SOLID principles, Clean Architecture / Hexagonal Architecture, Domain-Driven Design (DDD). Microservices Patterns: API Gateway, Service Discovery, Circuit Breaker (Resilience4j), Saga Pattern (xử lý transaction phân tán). Bảo mật (Security): OAuth2, JWT, OIDC, mã hóa dữ liệu (Hashing/Encryption), chống tấn công phổ biến (SQL Injection, CSRF, DDoS/Rate Limiting). Monitoring & Observability: ELK Stack (Elasticsearch, Logstash, Kibana), Prometheus, Grafana, OpenTelemetry / Jaeger (tracing lỗi giữa các service). | J24: 46277 | K24: Fail | L24: { "judge_result": "FAIL", "judge_status": "FAIL", "reason": "The Actual Result violates the negative constraint by claiming certain technologies like NestJS and PostgreSQL are the 'most popular' (được chuộng nhất hiện nay) and AWS has the 'largest number' (lớn nhất) of job postings without providing any statistical data to support these claims." } | M24: Fail | N24: No reference | O24: Kiểm tra khả năng trích xuất và tổng hợp các công nghệ được yêu cầu trong các tin tuyển dụng Backend Developer.
A26: TC-08 | B26: Dễ | C26: Tìm tin tuyển dụng tại Thành phố Hồ Chí Minh | D26: Hãy tìm các tin tuyển dụng CNTT tại Thành phố Hồ Chí Minh. | E26: Trả về các tin có địa điểm làm việc tại Thành phố Hồ Chí Minh hoặc được xác định rõ là tuyển dụng tại khu vực này | I26: Thị trường việc làm Công nghệ Thông tin tại Thành phố Hồ Chí Minh là một trong hai trung tâm lớn và năng động nhất cả nước, tập trung dày đặc các trụ sở công nghệ, trung tâm R&D quốc tế, kỳ lân công nghệ và các ngân hàng số.1. Phân bố việc làm IT theo các khu vực trọng điểm tại TP.HCMKhu Công nghệ cao (SHTP - TP. Thủ Đức):Tập trung: Các tập đoàn phần cứng, vi mạch bán dẫn và R&D quy mô lớn như Intel, FPT Software Campus, SanDisk, Viettel High Tech, Nidec.Vị trí phổ biến: Embedded Engineer, C/C++ Developer, Firmware, Hardware Engineer, System Verification.Công viên Phần mềm Quang Trung (QTSC - Quận 12):Tập trung: Các doanh nghiệp dịch vụ phần mềm, Outsourcing lớn như TMA Solutions, DXC Technology, DIGI-TEXX, SPS Vietnam.Vị trí phổ biến: Java/.NET Developer, QC/QA Manual & Automation, Data Processing, IT Support/Helpdesk.Khu trung tâm (Quận 1, Quận 3, Quận 4, Bình Thạnh):Tập trung: Các kỳ lân công nghệ, công ty Product quốc tế, Fintech và các sàn TMĐT: MoMo, VNG (VNG Campus - Q.7), Shopee, Grab, DatVietVAC, ZaloPay, Tiki, One Mount.Vị trí phổ biến: Golang/Java Backend, React/Next.js Frontend, Mobile (iOS/Android/Flutter), Data Engineer, Product Manager.Khu vực Tân Bình, Phú Nhuận (Gần sân bay & Etown):Tập trung: Các công ty công nghệ đa quốc gia, Outsource và Tech Hub của ngân hàng/bảo hiểm (Etown Cộng Hòa, Viettel Tower CMT8).Vị trí phổ biến: Fullstack Developer, DevOps/Cloud, Business Analyst (BA), Solution Architect.2. Các nhóm vai trò đang có nhu cầu tuyển dụng cao nhất tại TP.HCMVai tròCông nghệ / Kỹ năng chủ đạoPhân khúc doanh nghiệpMức lương tham khảo (Gross)Backend EngineerJava (Spring Boot), Golang, Node.js (NestJS), .NET Core, PythonFintech, Ngân hàng, Sàn TMĐT, Logistic20 – 60+ triệu VNĐFrontend / MobileReactJS, Next.js, TypeScript, Flutter, React Native, iOS (Swift)Product App, E-commerce, SaaS quốc tế18 – 50 triệu VNĐData & AI EngineerPython, PyTorch, Spark, Kafka, Airflow, LLMs/RAGBig Tech, Ngân hàng bán lẻ, AdTech25 – 70+ triệu VNĐCloud & DevOps / SREAWS, GCP, Docker, Kubernetes, Terraform, CI/CDCác công ty có hệ thống phân tán chịu tải cao25 – 65 triệu VNĐQA / QC (Automation Test)Selenium, Playwright, Cypress, Postman, API TestingOutsource Âu/Mỹ, Ngân hàng, Fintech15 – 40 triệu VNĐ3. Các công ty công nghệ tiêu biểu đang mở tuyển tại TP.HCMKhối Product & Công nghệ quy mô lớn:VNG (VNG Campus, Q.7): Tuyển Software Engineer (Golang, Java, C++), Data Platform, Game Developer.MoMo (M-Service, Q.7): Tuyển Backend Engineer (Java, Golang, Microservices), SRE, Data Scientist.Grab Vietnam (Q.7): Tuyển Software Engineer, Data Analyst, Infrastructure Engineer.Khối Dịch vụ & Trung tâm R&D quốc tế:NAB Innovation Centre Vietnam (Q.1 & Tân Bình): Tuyển Java/Cloud Engineer, DevOps, Automation Test cho hệ thống ngân hàng số của Úc.bbv Vietnam, EPAM Systems, Thoughtworks, Hitachi Digital Services: Các công ty phần mềm châu Âu/Mỹ tuyển kỹ sư phần mềm giao tiếp tiếng Anh tốt, chế độ Hybrid.TMA Solutions & FPT Software: Tuyển số lượng lớn kỹ sư từ Fresher, Junior đến Senior cho các thị trường Nhật Bản, Bắc Mỹ, Úc.4. Kênh tìm việc và lọc tin nhanh nhất theo khu vực TP.HCMITviec (itviec.com): Chọn bộ lọc địa điểm Hồ Chí Minh, có thể lọc tiếp theo chế độ làm việc (Hybrid hoặc At office) và ngôn ngữ lập trình.TopCV (topcv.vn): Chọn khu vực TP. Hồ Chí Minh và quận cụ thể (Quận 1, Bình Thạnh, Quận 7, TP. Thủ Đức) để tìm các vị trí gần nơi sinh sống.LinkedIn Jobs: Tìm kiếm theo từ khóa Software Engineer Ho Chi Minh City hoặc theo dõi trực tiếp các Tech Recruiter của các công ty công nghệ tại Việt Nam. | J26: 46277 | K26: Fail | L26: { "judge_result": "FAIL", "judge_status": "FAIL", "reason": "The Actual Result fails to provide specific IT job postings in Ho Chi Minh City as required by the Expected Result. Instead, it only offers a general market overview, a list of companies that are hiring, and job search advice." } | M26: Fail | N26: No reference | O26: Kiểm tra khả năng lọc và truy xuất các tin tuyển dụng CNTT theo địa điểm Thành phố Hồ Chí Minh.
A28: TC-09 | B28: Dễ | C28: Tìm tin tuyển dụng có mức lương | D28: Tìm các tin tuyển dụng CNTT có thông tin về mức lương. | E28: Trả về các tin có mức lương được công bố. Nếu có thể, trình bày mức lương và đơn vị tiền tệ đúng theo dữ liệu. | I28: Dưới đây là tổng hợp các tin tuyển dụng và vị trí IT công khai khoảng lương cụ thể theo từng phân khúc kinh nghiệm tại thị trường Việt Nam (dữ liệu tổng hợp từ các nền tảng tuyển dụng như TopCV, ITviec và báo cáo thị trường CNTT):1. Phân khúc Fresher / Dưới 1 năm kinh nghiệmFresher/Junior Backend & AI Integration (ProtonX, Teko, FPT Software Academy):Mức lương công khai: 8 – 15 triệu VNĐ/tháng.Yêu cầu chính: Nắm chắc Python/Java hoặc JavaScript, hiểu biết về REST API, Git, SQL cơ bản.IT Support / Kỹ thuật mạng & Triển khai (Cadena, CMC Telecom, PosApp):Mức lương công khai: 9 – 15.4 triệu VNĐ/tháng (tùy phụ cấp đi lại và ca trực).Yêu cầu chính: Hỗ trợ phần cứng, cấu hình mạng LAN/WAN, cài đặt máy trạm, giao tiếp tốt.2. Phân khúc Middle (2 – 4 năm kinh nghiệm)Backend Developer (Node.js / Java / .NET Core) - Doanh nghiệp trong nước & Outsource:Mức lương công khai: 20 – 35 triệu VNĐ/tháng (hoặc tương đương 1,000 – 1,500 USD tại các cty nước ngoài). Yêu cầu chính: Xây dựng RESTful API/Microservices, tối ưu hóa câu lệnh SQL (PostgreSQL, MySQL, Oracle), Redis, Docker.Frontend Developer (ReactJS / Next.js, Vue.js) - E-commerce & Startup SaaS:Mức lương công khai: 18 – 32 triệu VNĐ/tháng.Yêu cầu chính: TypeScript chặt chẽ, State Management (Redux/Zustand), Server-Side Rendering (SSR/SSG), tối ưu Web Vitals.Quản trị hệ thống máy chủ & Mạng (System / Network Admin):Mức lương công khai: 20 – 25 triệu VNĐ/tháng. Yêu cầu chính: Quản trị Linux/Windows Server, VMware, Firewall, giám sát hạ tầng và backup dữ liệu định kỳ.3. Phân khúc Senior & Chuyên gia (5+ năm kinh nghiệm)Senior Java / Golang Backend Engineer (Khối Ngân hàng số & Fintech: MB Bank, MoMo, Techcombank):Mức lương công khai: 35 – 65 triệu VNĐ/tháng.Yêu cầu chính: Thiết kế kiến trúc phân tán (Distributed Systems), xử lý tải cao với Apache Kafka, Spring Boot 3, tối ưu Database locking/concurrency.Kỹ sư An toàn thông tin / Bảo mật hạ tầng (Product Security / DevSecOps):Mức lương công khai: 30 – 80 triệu VNĐ/tháng. Yêu cầu chính: Quản lý hạ tầng bảo mật, pentest ứng dụng/mạng, tuân thủ tiêu chuẩn ISO/PCI-DSS, triển khai giải pháp WAF/SIEM.Remote Backend Lead / Technical Lead (Công ty đa quốc gia, Headhunt OrgScale, Reap AI):Mức lương công khai: 2,500 – 4,500 USD/tháng (~60 – 110 triệu VNĐ/tháng).Yêu cầu chính: Năng lực thiết kế System Architecture, lãnh đạo kỹ thuật nhóm, thành thạo tiếng Anh và làm việc Remote hoàn toàn.4. Bảng trung vị mức lương theo vai trò (Báo cáo thị trường IT 2025–2026)Vị trí chuyên môn< 2 năm KN3 – 4 năm KN5 – 8 năm KNBackend Developer12.4 – 25.3M30.1M39.9 – 55MFrontend Developer15.0 – 22.0M30.8M41.8 – 46MData Engineer18.0 – 28.0M35.0 – 45.0M56.9M+Tech Lead / System Architect—45.3M54.0 – 70M+5. Cách lọc tin có lương rõ ràng trên các trang tuyển dụngTrên TopCV: Tại thanh tìm kiếm, chọn bộ lọc "Mức lương" (ví dụ: 15 - 20 triệu, 20 - 25 triệu, hoặc Trên 30 triệu) để hệ thống ẩn hoàn toàn các tin ghi "Thoả thuận". Trên ITviec: Đăng nhập tài khoản để mở khóa chế độ hiển thị dải lương chi tiết (Gross/Net) hoặc chọn bộ lọc "Salary Range" theo USD/VNĐ. | J28: 46277 | K28: Fail | L28: { "judge_result": "FAIL", "judge_status": "FAIL", "reason": "The Actual Result fails to provide specific job postings with published salaries as required by the Expected Result. Instead, it only provides a general market overview, aggregated salary ranges for generic roles, and groups of company names without listing the actual job postings." } | M28: Fail | N28: No reference | O28: Kiểm tra khả năng nhận diện các tin tuyển dụng có công bố thông tin về mức lương và trình bày đúng dữ liệu.
A30: TC-10 | B30: Dễ | C30: Tóm tắt một tin tuyển dụng | D30: Hãy tóm tắt thông tin chính của tin tuyển dụng được cung cấp hoặc truy xuất. | E30: Bản tóm tắt cần nêu được vị trí, công ty, địa điểm, yêu cầu chính, mức lương nếu có và cách ứng tuyển nếu dữ liệu có sẵn. | I30: Bạn chưa đính kèm nội dung hoặc liên kết (link) của tin tuyển dụng. Hãy dán trực tiếp đoạn văn bản mô tả công việc (JD) hoặc đường dẫn tin tuyển dụng vào đây. Tôi sẽ tổng hợp và trích xuất nhanh các thông tin then chốt theo mẫu sau: Vị trí & Cấp bậc: Tên chức danh, cấp độ (Fresher/Junior/Mid/Senior). Doanh nghiệp & Địa điểm: Tên công ty, hình thức làm việc (Onsite/Hybrid/Remote), văn phòng làm việc. Mức lương & Đãi ngộ: Khoảng thu nhập (Gross/Net/USD), thưởng dự án, bảo hiểm, số ngày phép. Tech Stack & Yêu cầu cốt lõi: Ngôn ngữ, framework, số năm kinh nghiệm, kỹ năng mềm, yêu cầu ngoại ngữ. Mô tả công việc chính: Các nhiệm vụ và trách nhiệm thực tế hàng ngày. Đánh giá sơ bộ: Mức độ phù hợp, điểm cần lưu ý khi nộp hồ sơ hoặc phỏng vấn. | J30: 46277 | K30: Pass | L30: { "judge_result": "PASS", "judge_status": "PASS", "reason": "The AI Agent correctly identified that no job posting was provided in the input. Following the guidelines for handling missing information, it appropriately acknowledged the limitation and requested the necessary data from the user rather than fabricating a summary." } | M30: Pass | N30: No reference | O30: Kiểm tra khả năng tóm tắt các thông tin chính của một tin tuyển dụng mà không làm sai lệch nội dung nguồn.
A32: TC-11 | B32: Trung bình | C32: Lọc Backend theo Python và Django | D32: Tìm các tin tuyển dụng Backend Developer tại Việt Nam yêu cầu Python và Django. | E32: Chỉ trả về các tin phù hợp với nhóm Backend Developer và có đề cập cả Python lẫn Django trong yêu cầu hoặc mô tả công việc. | I32: Các vị trí Backend Developer chuyên về Python và Django tại thị trường Việt Nam tập trung chủ yếu vào việc phát triển RESTful API (DRF), các nền tảng SaaS/B2B, hệ thống quản trị dữ liệu quy mô lớn hoặc tích hợp dịch vụ Cloud và AI.1. Các tin tuyển dụng tiêu biểu đang mở tuyểnCông ty / Đơn vịVị trí tuyển dụngYêu cầu Tech Stack chínhHình thức & Địa điểmMức lương tham khảoParcel PerformBackend Engineer / Tech LeadPython, Django, AWS, Scala, kiến trúc Microservices, tiếng Anh lưu loátLinh hoạt (Hybrid) / TP.HCMThỏa thuận (Cạnh tranh theo USD)GoTymeXBackend Engineer (FinCrime)Python, Django, Flask, Java, AWS, MicroservicesLinh hoạt (Hybrid) / TP.HCMThỏa thuận (Phân khúc Fintech)AI&TFullstack / Backend DevPython, Django, PostgreSQL, VueJS/Nuxt.jsOnsite (Hợp đồng/Dự án)Lên đến 65 triệu VNĐFPT SoftwareLead / Senior Python DeveloperPython, Django, Flask, SQL, SOLID Principles, LeadershipOnsite / TP.HCM & Hà NộiThỏa thuận (Theo năng lực)FPT Telecom / FPT JobsBackend Developer / InternPython, Django / FastAPI, SQL/NoSQL, OpenSearch, Big DataOnsite / Quận 7, TP.HCMHỗ trợ thực tập / Lương chính thứcBase.vnBackend Developer (Python/Django)Python, Django, MySQL, tối ưu hóa truy vấn cho hệ thống B2B SaaSOnsite / Hà Nội & TP.HCM20 – 40 triệu VNĐ2. Kỹ năng đi kèm thường thấy trong các JD Python/DjangoDjango REST Framework (DRF): Gần như là yêu cầu bắt buộc để thiết kế API chuẩn RESTful, quản lý phân quyền (Permissions), Authentication (JWT/OAuth2) và Serialization.Celery & Redis: Xử lý hàng đợi bất đồng bộ (async tasks), gửi email, background job, caching dữ liệu để giảm tải cho database.Database Tuning (PostgreSQL / MySQL): Tối ưu hóa ORM của Django (tránh triệt để lỗi kinh điển N+1 queries, sử dụng thành thạo select_related, prefetch_related, và thiết kế Database Indexing).Kiến trúc & Đóng gói: Docker, Docker Compose, triển khai trên AWS (EC2, S3, RDS, ECS) và thiết lập CI/CD pipeline.Khả năng mở rộng: Nhiều công ty hiện nay yêu cầu kết hợp Django cho các tác vụ CMS/Admin/ORM truyền thống song song với FastAPI cho các service microservice đòi hỏi tốc độ cao hoặc tích hợp AI.3. Cách truy cập và nộp hồ sơ trực tiếpITviec: Truy cập [itviec.com/viec-lam-it/django](https://itviec.com/viec-lam-it/django) để lọc danh sách các công ty Product quốc tế và Outsource trả lương minh bạch. TopCV: Tìm kiếm từ khóa Backend Python Django hoặc Lập trình viên Django để xem các cơ hội từ cấp độ Junior đến Senior tại Hà Nội và TP.HCM. LinkedIn Jobs: Gõ Django Developer Vietnam hoặc Python Backend Engineer Vietnam để kết nối trực tiếp với các HR/Tech Recruiter của các công ty đa quốc gia. | J32: 46277 | K32: Pass | L32: { "judge_result": "PASS", "judge_status": "PASS", "reason": "The Actual Result successfully filtered and returned only the job postings that belong to the Backend Developer group and explicitly require both Python and Django, fully satisfying the constraints specified in the Expected Result." } | M32: Pass | N32: No reference | O32: Kiểm tra khả năng lọc tin tuyển dụng Backend Developer theo đồng thời hai công nghệ Python và Django.
A34: TC-12 | B34: Trung bình | C34: Lọc việc theo địa điểm và hình thức làm việc | D34: Tìm các vị trí Software Engineer tại Thành phố Hồ Chí Minh có hình thức làm việc remote hoặc hybrid. | E34: Trả về các tin phù hợp với vị trí Software Engineer, địa điểm Thành phố Hồ Chí Minh và có hình thức remote hoặc hybrid được nêu rõ. | I34: Các vị trí Software Engineer tại khu vực TP. Hồ Chí Minh hỗ trợ hình thức Remote (làm việc từ xa) hoặc Hybrid (kết hợp linh hoạt giữa lên văn phòng và làm tại nhà) tập trung nhiều ở các công ty Product quốc tế, công ty khởi nghiệp công nghệ, và các đơn vị tuyển dụng qua Headhunt.1. Một số tin tuyển dụng & doanh nghiệp tiêu biểu đang tuyểnDoanh nghiệp / Tổ chứcVị trí tuyển dụngChế độ làm việcYêu cầu Tech Stack chínhĐiểm nổi bật & Đãi ngộMoney Forward VietnamSenior/Principal Software EngineerHybrid (Linh hoạt văn phòng & WFH)Ruby on Rails, Kotlin, Java, Kafka, AI IntegrationCấp MacBook Pro, 17 ngày phép năm, môi trường Product Nhật BảnFram^Remote Fullstack EngineerFull Remote (Base TP.HCM)Golang, ReactJS, Microservices5+ năm kinh nghiệm, làm việc theo giờ linh hoạtKambria & OhmniLabs VietnamMid / Senior Fullstack DeveloperHybrid / Remote linh hoạtNode.js, ReactJS, Next.js, TypeScript15 ngày phép, văn hóa cân bằng Work-Life BalanceOrgScale RecruitmentRemote Backend Lead / QA Manager100% RemoteNode.js (ExpressJS), PostgreSQL, AWS, MicroservicesMức lương cạnh tranh theo USD, quản lý team phân tánAxon VietnamSoftware EngineerHybridJava/C++, Cloud, thực hành AI-assisted developmentMôi trường công nghệ cao của Mỹ, chế độ bảo hiểm toàn diệnANDPAD Vietnam / EPAMSoftware Engineer (Fullstack / Backend)Hybrid (1–3 ngày WFH/tuần)React/Vue, Go, Java, Docker, AWSDự án SaaS quốc tế, môi trường giao tiếp tiếng Anh/Nhật2. Đặc điểm các mô hình làm việc tại TP.HCMChế độ Hybrid: Thường phổ biến tỷ lệ 2-3 ngày tại văn phòng + 2-3 ngày làm việc tại nhà/tuần, hoặc tự do chọn ngày lên văn phòng miễn đảm bảo các buổi họp Sprint/Retro. Chế độ 100% Remote: Chủ yếu đến từ: Các công ty/startup công nghệ có trụ sở tại Singapore, Úc, Mỹ hoặc Châu Âu nhưng tuyển kỹ sư tại Việt Nam (thường ký hợp đồng theo dạng Contractor/EOR). Các công ty Headhunt (như OrgScale, Persol, Michael Page) tuyển vị trí Lead/Senior làm việc từ xa hưởng lương USD.3. Cách lọc nhanh các tin Remote/Hybrid tại TP.HCMTrên ITviec (itviec.com): Vào mục Việc làm IT -> Chọn địa điểm Hồ Chí Minh.Tại thanh lọc bên trái, tìm mục Hình thức làm việc và tích chọn "Linh hoạt (Hybrid)" hoặc chọn trực tiếp mục "Remote".Trên LinkedIn Jobs:Gõ từ khóa: Software Engineer.Location: Ho Chi Minh City, Vietnam.Bấm vào bộ lọc On-site/remote -> Tích chọn cả hai mục "Hybrid" và "Remote".Trên Indeed (vn.indeed.com):Tìm kiếm cụm từ: Remote Software Engineer TP.HCM hoặc Full remote hybrid software. | J34: 46277 | K34: Pass | L34: { "judge_result": "PASS", "judge_status": "PASS", "reason": "The Actual Result successfully provides a list of Software Engineer positions located in Ho Chi Minh City that explicitly feature either a remote or hybrid work model, fulfilling all the specified filtering constraints in the Expected Result." } | M34: Pass | N34: No reference | O34: Kiểm tra khả năng xử lý đồng thời các điều kiện về vị trí, địa điểm và hình thức làm việc remote hoặc hybrid.
... A62: TC-26 | B62: Khó | C62: Xử lý câu hỏi có tiền đề chưa được chứng minh | D62: Công ty X hiện đang tuyển 50 vị trí AI Engineer tại Việt Nam đúng không? Hãy liệt kê các vị trí đó. | E62: Agent phải kiểm tra dữ liệu có sẵn, nêu rõ không đủ căn cứ nếu không xác minh được số lượng 50 hoặc danh sách vị trí. Không tự tạo danh sách hoặc số lượng tuyển dụng. | I62: Thông tin “Bosch hiện đang tuyển 50 vị trí AI Engineer tại Việt Nam” là không chính xác (hoặc có sự nhầm lẫn về số lượng con số tuyển dụng).Hiện tại, Bosch Global Software Technologies (BGSW) Vietnam đang tích cực mở tuyển các kỹ sư mảng Trí tuệ nhân tạo (AI/ML) tại TP.HCM và Hà Nội, nhưng số lượng cho từng đợt thường là các nhóm nhỏ (ví dụ: đợt tuyển 5 AI/Agent Engineers) cùng một số vị trí chuyên biệt khác, chứ không có thông báo tuyển đồng loạt 50 vị trí AI Engineer riêng biệt. Dưới đây là các vị trí và nhóm công việc thực tế thuộc mảng AI / Data / Machine Learning mà Bosch đang tuyển dụng tại Việt Nam:1. [SX/EIT-MM] AI / Agent Engineers (Đợt tuyển 5 nhân sự) Địa điểm: Hà Nội (Capital Place, Ba Đình) và TP.HCM (Etown Tân Bình / OfficeHaus Tân Phú). Hình thức: Toàn thời gian hoặc hợp đồng 1 năm (1-year contract). Trách nhiệm chính:Thiết kế và xây dựng các hệ thống Agentic AI (lập kế hoạch, bộ nhớ, tool use, multi-agent coordination, guardrails). Triển khai các mô hình ngôn ngữ lớn (LLMs như OpenAI, Anthropic, Gemini, open-weights) vào sản phẩm thực tế: RAG pipelines, context caching, structured outputs.Xử lý dữ liệu đa phương thức (Multimodal: Vision, OCR/Document AI, Audio). Yêu cầu cốt lõi: 3+ năm kinh nghiệm, hiểu sâu về kiến trúc Transformer, thành thạo Python ở mức Senior (async, testing, packaging), kinh nghiệm MLOps (Docker, Kubernetes/AKS, vLLM, Triton).2. Senior AI / Machine Learning Engineer [EAF]Địa điểm: TP. Hồ Chí Minh (Etown 2, Tân Bình). Trách nhiệm chính:Nghiên cứu, phát triển và tối ưu hóa các thuật toán Deep Learning / Machine Learning phục vụ các bài toán công nghiệp và phần mềm doanh nghiệp của Bosch.Tối ưu hóa mô hình AI để triển khai trên các thiết bị biên (Edge AI) hoặc hệ thống hạ tầng đám mây.Yêu cầu cốt lõi: Nắm vững PyTorch, TensorFlow, kinh nghiệm làm việc với bài toán Computer Vision hoặc NLP, giao tiếp tiếng Anh tốt trong môi trường toàn cầu.3. Data Engineer / MLOps Engineer (AI Platform)Địa điểm: TP. Hồ Chí Minh & Hà Nội. Trách nhiệm chính:Xây dựng luồng dữ liệu (Data Pipeline, ETL/ELT) phục vụ huấn luyện và đánh giá mô hình AI.Thiết lập hạ tầng MLOps: Quản lý phiên bản mô hình (Model Registry), CI/CD cho AI workloads, hệ thống giám sát và đánh giá (Evaluation gates / LLM-as-judge).Yêu cầu cốt lõi: Python, SQL, Docker, Kubernetes, kinh nghiệm với các dịch vụ đám mây (Azure/AWS) và các framework inference serving.4. AI Intern / Graduate Trainee (Thực tập sinh & Kỹ sư tiềm năng)Địa điểm: TP. Hồ Chí Minh. Đối tượng: Sinh viên năm cuối hoặc cử nhân mới tốt nghiệp ngành Khoa học Máy tính, Trí tuệ Nhân tạo, Toán - Tin.Nội dung: Được đào tạo thực chiến về quy trình nghiên cứu thuật toán AI, tích hợp hệ thống phần mềm, tham gia các dự án đổi mới sáng tạo toàn cầu của Bosch. Kênh xác thực và nộp hồ sơ trực tiếp tại Bosch:Nếu bạn nhìn thấy thông tin "tuyển 50 người", có thể đó là tổng chỉ tiêu tuyển dụng của toàn khối phần mềm (bao gồm cả Embedded, C/C++, Java, Cloud, Testing) hoặc tin tuyển dụng từ các kênh trung gian không chính thống. Để xem đúng JD và nộp hồ sơ, bạn nên tra cứu trực tiếp qua:Cổng tuyển dụng chính thức của Bosch: SmartRecruiters (Bosch Group Careers) hoặc bosch.com.vn/careers.LinkedIn: Trang chính thức của Bosch Global Software Technologies Vietnam. | J62: 46277 | K62: Pass | L62: Kết quả trực tiếp phủ nhận sự tồn tại của 50 vị trí | M62: Pending | N62: No reference | O62: Kiểm tra khả năng xác minh tiền đề của câu hỏi và tránh đưa ra thông tin hoặc số liệu không có căn cứ.
A64: TC-27 | B64: Khó | C64: Tổng hợp và đánh giá xu hướng có giới hạn | D64: Dựa trên dữ liệu tuyển dụng đã thu thập, hãy đánh giá liệu Python hay Java đang có nhu cầu tuyển dụng cao hơn tại Việt Nam. | E64: So sánh dựa trên phạm vi, thời gian và số lượng tin thực tế được sử dụng. Nêu rõ đây là kết luận trong tập dữ liệu, không mặc định đại diện cho toàn bộ thị trường. Nếu dữ liệu không đủ để kết luận, phải nói rõ. | I64: Dựa trên các tin tuyển dụng và dữ liệu thị trường đã thu thập trong toàn bộ cuộc trao đổi, Java đang có nhu cầu tuyển dụng nhỉnh hơn về số lượng tuyệt đối lẫn quy mô nhân sự trong mảng Backend truyền thống tại Việt Nam. Tuy nhiên, Python lại vượt trội về tốc độ tăng trưởng và tính đa dụng ở các mảng công nghệ mới (AI/Data).Dưới đây là đánh giá và so sánh chi tiết giữa hai ngôn ngữ:1. Bảng so sánh tổng quan thị trườngTiêu chíJava (Spring Boot)Python (FastAPI, Django, Flask)Tổng số lượng tin tuyển dụngRất lớn (Chiếm tỷ trọng áp đảo ở khối Backend)Lớn và tăng nhanh (Đa dạng lĩnh vực)Quy mô tuyển dụng mỗi đợtThường tuyển số lượng lớn (hàng chục đến hàng trăm kỹ sư cho các khối Ngân hàng, Outsource lớn)Thường tuyển theo đội ngũ tinh gọn (Product/SaaS team, AI/Data pod)Khối ngành tuyển dụng mạnh nhất• Ngân hàng & Tài chính số (MB, Techcombank, VPBank, NAB)• Fintech & Ví điện tử (MoMo, Zalopay)• Doanh nghiệp dịch vụ phần mềm toàn cầu (FPT, TMA, bbv, EPAM)• Doanh nghiệp B2B SaaS (Base.vn)• E-commerce & Logistics Data (Parcel Perform, GHTK)• Hệ thống tích hợp GenAI / LLM / Computer Vision (Bosch, Teko)Cơ hội cho Fresher / JuniorRất nhiều chương trình bài bản (FPT Software Academy, NAB Graduate Program, các lớp Fresher định kỳ)Chủ yếu tuyển Junior đã có sản phẩm thực chiến hoặc Fresher nắm vững thuật toán/DataMức trần lương (Senior/Lead)35 – 70+ triệu VNĐ (rất cao ở khối Ngân hàng số và hệ thống phân tán)30 – 65+ triệu VNĐ (ở mảng Web) và có thể lên tới 70 – 100+ triệu VNĐ nếu đi sâu vào AI/ML2. Phân tích chi tiết từng khía cạnhVề số lượng việc làm thuần Backend: Java chiếm ưu thếHạ tầng doanh nghiệp lớn: Các hệ thống lõi (Core Banking, bảo hiểm, ERP doanh nghiệp, thanh toán) tại Việt Nam được xây dựng trên nền tảng Java từ nhiều năm nay. Nhu cầu duy trì, mở rộng và chuyển đổi sang Microservices (Spring Boot 3, Kafka, Docker/K8s) tạo ra dòng chảy tuyển dụng liên tục và bền vững.Quy mô dự án Outsource: Các công ty dịch vụ phần mềm lớn phục vụ thị trường Nhật, Mỹ, Âu tuyển Java quanh năm với số lượng chỉ tiêu áp đảo các ngôn ngữ khác.Về độ đa năng và xu hướng mới: Python bứt phá mạnhLợi thế mảng AI & Dữ liệu: Hầu hết các tin tuyển dụng liên quan đến Data Engineer, Machine Learning, và đặc biệt là tích hợp GenAI/LLM (như các vị trí tại Bosch, Teko) đều yêu cầu Python là ngôn ngữ bắt buộc.Tốc độ phát triển API (Microservices): Sự phổ biến của FastAPI giúp Python cạnh tranh sòng phẳng với Node.js và Go trong việc xây dựng các API bất đồng bộ hiệu năng cao cho các công ty Product và startup.3. Kết luận: Nên chọn học hoặc định hướng theo hướng nào?Chọn Java nếu bạn:Muốn có nhiều cơ hội việc làm nhất, đặc biệt nếu bắt đầu từ số 0 hoặc mới tốt nghiệp (nhiều công ty lớn có lò đào tạo Fresher sẵn sàng nhận đào tạo lại).Định hướng làm việc trong môi trường ổn định, hệ thống phân tán chịu tải lớn, khối tài chính ngân hàng hoặc các tập đoàn công nghệ đa quốc gia.Chọn Python nếu bạn:Thích môi trường startup, công ty Product phát triển sản phẩm linh hoạt (SaaS, E-commerce).Muốn đón đầu làn sóng AI / Machine Learning / Data, vì Python là "ngôn ngữ mẹ đẻ" của toàn bộ hệ sinh thái này. | J64: 46277 | K64: Pending | M64: Pending | N64: No reference | O64: Kiểm tra khả năng phân tích, so sánh xu hướng tuyển dụng và nêu rõ giới hạn của tập dữ liệu được sử dụng.
A66: TC-28 | B66: Khó | C66: Tìm kiếm với điều kiện phủ định | D66: Tìm các tin tuyển dụng Backend Developer tại Việt Nam yêu cầu Python nhưng không yêu cầu Django, có mức lương công bố và không yêu cầu trên 3 năm kinh nghiệm. | E66: Xử lý đồng thời các điều kiện bao gồm và loại trừ. Chỉ đưa vào danh sách các tin có Python, không có Django trong yêu cầu, có mức lương công bố và không yêu cầu trên 3 năm kinh nghiệm. Phải phân biệt “không đề cập Django” với “khẳng định không yêu cầu Django” nếu dữ liệu không đủ rõ. | I66: Dưới đây là các tin tuyển dụng Backend Developer tại Việt Nam đáp ứng đầy đủ các tiêu chí: yêu cầu Python, không yêu cầu Django (thay vào đó tập trung vào FastAPI, Flask hoặc kiến trúc microservices/API), có công bố mức lương và kinh nghiệm không quá 3 năm (dành cho Fresher/Junior/Mid):Bảng tổng hợp các tin tuyển dụng phù hợpĐơn vị tuyển dụngVị trí tuyển dụngYêu cầu kinh nghiệm & Tech StackĐịa điểmMức lương công bốCông ty Công nghệ và Tự động hóa RostekJunior Backend Developer (Python)• Kinh nghiệm: Từ 1 năm• Tech Stack: Python, FastAPI, RESTful API, PostgreSQL/MySQL, GitHà NộiTừ 15 triệu VNĐ/thángCông ty Cổ phần Công nghệ số 1TEKBackend Developer (Python)• Kinh nghiệm: Khoảng 2 năm• Tech Stack: Python, REST APIs, Git, xử lý logic dịch vụ backend và cơ sở dữ liệuHà Nội10 – 25 triệu VNĐ/thángTLTEK VietnamJunior Python Developer• Kinh nghiệm: 1 – 2 năm• Tech Stack: Python, xây dựng web service/API, cơ sở dữ liệu quan hệ, làm việc nhómTP. Hồ Chí MinhTới 40 triệu VNĐ/tháng (theo năng lực)Worklink / Client PartnerJunior Python Developer• Kinh nghiệm: 1 – 2 năm• Tech Stack: Python, xử lý dữ liệu và xây dựng API backend, GitHà Nội17 – 26 triệu VNĐ/thángBigtree Technology & ConsultingJunior Python Developer• Kinh nghiệm: 1 – 2 năm• Tech Stack: Python, API integration, viết code tối ưu, đọc hiểu tiếng Anh kỹ thuậtHà NộiLên tới 1,000 USD/tháng (~25 – 26 triệu VNĐ)NAL Việt NamPython Developer (Web Backend)• Kinh nghiệm: 1 – 3 năm• Tech Stack: Python, FastAPI, Flask, SQL, Docker, tư duy Clean CodeTP.HCM / Hà Nội15 – 30 triệu VNĐ/thángĐiểm nổi bật của các vị trí Python không dùng DjangoFastAPI là lựa chọn áp đảo: Hầu hết các công ty hiện đại khi không dùng kiến trúc Monolith của Django đều chuyển sang FastAPI nhờ tính năng xử lý bất đồng bộ (async/await), tốc độ cao và tự động sinh tài liệu Swagger/OpenAPI. Kỹ năng kết hợp được chuộng nhất: Cơ sở dữ liệu quan hệ (PostgreSQL / MySQL) và container hóa bằng Docker.Mức thu nhập: Với người dưới 3 năm kinh nghiệm, dải lương dao động phổ biến từ 15 đến 26 triệu VNĐ/tháng, một số vị trí linh hoạt theo năng lực có thể chạm mốc 30 – 40 triệu VNĐ. | J66: 46277 | K66: Pending | M66: Pending | N66: No reference | O66: Kiểm tra khả năng xử lý đồng thời các điều kiện bao gồm và loại trừ trong yêu cầu tìm kiếm tuyển dụng.
A68: TC-29 | B68: Khó | C68: Đánh giá tính phù hợp và rủi ro suy đoán | D68: Tôi muốn chuyển từ Frontend Developer sang AI Engineer. Tôi biết JavaScript, React, TypeScript và có 2 năm kinh nghiệm. Hãy tìm các tin phù hợp và cho biết tôi còn thiếu gì. | E68: Tìm các tin AI Engineer phù hợp ở mức tương đối nếu có. Đối chiếu yêu cầu thực tế với kỹ năng được cung cấp. Nêu các kỹ năng còn thiếu dựa trên tin tuyển dụng, không tự khẳng định người dùng không đủ năng lực hoặc chắc chắn không phù hợp. Có thể đề xuất nhóm kỹ năng cần bổ sung nếu có căn cứ. | I68: Việc chuyển hướng từ Frontend Developer (JavaScript, React, TypeScript, 2 năm kinh nghiệm) sang AI Engineer là một lộ trình rất khả thi, đặc biệt trong làn sóng AI Application / Fullstack AI / GenAI Engineer hiện nay. Tại Việt Nam, các công ty không chỉ tuyển các nhà nghiên cứu mô hình (AI Researcher) mà đang săn đón rất nhiều kỹ sư biết cách đưa mô hình AI vào giao diện ứng dụng thực tế.1. Phân tích: Bạn đang có gì và còn thiếu gì?Lợi thế cạnh tranh sẵn có của bạn:TypeScript & React (2 năm KN): Bạn đã có tư duy component, quản lý state và xử lý API bất đồng bộ. Đây là nền tảng để xây dựng Streaming UI (như chatbox ChatGPT/Claude trả kết quả từng chữ), dashboard trực quan hóa dữ liệu AI, hoặc tích hợp Vercel AI SDK.Định vị cầu nối (AI Application / Fullstack AI): Nhiều kỹ sư AI thuần túy rất giỏi toán và mô hình nhưng lại yếu về xây dựng giao diện người dùng (UI/UX) và triển khai sản phẩm ra thị trường. Bạn có thể bù đắp đúng khoảng trống này. Những mảnh ghép bạn CÒN THIẾU để trở thành AI Engineer thực thụ:Lĩnh vựcKỹ năng còn thiếuMức độ quan trọngMục tiêu cần đạt1. Ngôn ngữ cốt lõiPythonBắt buộc (Must-have)Học cú pháp Python, async/await, kiểu dữ liệu, các thư viện thao tác dữ liệu cơ bản (pydantic, pandas, numpy).2. Kỹ thuật GenAI & LLMsPrompt Engineering, RAG & Vector DBRất caoHiểu kiến trúc Retrieval-Augmented Generation (RAG); sử dụng Vector Database (ChromaDB, Pinecone, Qdrant, pgvector); sử dụng embedding models.3. AI Orchestration FrameworksLangChain, LlamaIndex hoặc Vercel AI SDKRất caoBiết cách xâu chuỗi luồng xử lý dữ liệu (Chains), thiết lập bộ nhớ (Memory), gọi công cụ (Tool calling / Function calling).4. Backend API phục vụ AIFastAPI hoặc Node.js (Streaming / SSE)CaoXây dựng API nhận/trả dữ liệu streaming qua Server-Sent Events (SSE) hoặc WebSockets; tối ưu độ trễ (Latency).5. AI Agents & Multi-AgentTư duy Agentic AIXu hướng mạnhHiểu cách một AI Agent tự lập kế hoạch (Plan-and-Solve, ReAct loop) và tương tác với các API bên ngoài.6. Nền tảng ML cơ bảnTokenization, Embeddings, EvaluationCơ bản – Trung bìnhHiểu cách tính token, giới hạn context window, fine-tuning cơ bản và đánh giá chất lượng câu trả lời (LLM evaluation).2. Các tin tuyển dụng phù hợp làm bước đệm chuyển đổiVới nền tảng hiện tại, bạn nên nhắm vào các vị trí Fullstack AI Engineer, AI Application Engineer, hoặc Junior/Fresher AI Engineer thay vì ứng tuyển vào các vị trí chuyên sâu về Core Model/Computer Vision.Đơn vị tuyển dụngVị tríTech Stack & Yêu cầuĐiểm phù hợp với bạnDatVietVACSenior/Mid AI Native EngineerReact, Next.js, TypeScript, AI APIs, CI/CDTận dụng trực tiếp thế mạnh React/TypeScript để phát triển các tính năng AI-native trên sản phẩm số.Reap AI (TP.HCM)AI Agent Engineer (Fresher/Junior/Senior)Logic, First-principles, xây dựng workflow Agent, tích hợp AICởi mở nhận ứng viên có tư duy tốt, có lộ trình đào tạo về AI Agent thực chiến.Cluega IT (TP.HCM)AI Engineer (Chatbot & AI Assistant)Xây dựng Chatbot, LLMs, NLP, tích hợp giao diện và web servicePhù hợp người mạnh frontend muốn mở rộng sang xây dựng chatbot tương tác.VNG / VNGGamesAI Engineer (Internal Platforms)Tự động hóa quy trình, AI coding assistant, xây dựng tool nội bộYêu cầu 1–2 năm kinh nghiệm phần mềm, đào tạo thêm về tích hợp mô hình.Ngân hàng MB (MBBank)AI Software Engineer / Agentic EngineerPython/Go, REST API, tích hợp AI Agents, RAG pipelinesTuyển dụng mở cho kỹ sư phần mềm muốn chuyển dịch sang mảng AI Platform.3. Lộ trình hành động cụ thể trong 2–3 tháng tới[Hiện tại: React/TS Frontend] │ ▼ (Tuần 1-2: Học Python căn bản & FastAPI) [Fullstack Developer: React + FastAPI/Node.js] │ ▼ (Tuần 3-6: RAG + Vector DB + LangChain/LlamaIndex) [AI Application Developer: Tích hợp LLM APIs & Streaming UI] │ ▼ (Tuần 7-10: Xây dựng 2 dự án Portfolio thực chiến) [AI Engineer / AI Native Software Engineer] Học cấp tốc Python (1–2 tuần): Vì đã có tư duy 2 năm với JS/TS, bạn chỉ mất khoảng 10–14 ngày để nắm chắc cú pháp Python và làm quen với framework FastAPI.Làm chủ Vercel AI SDK (Dành riêng cho dân React/TS): Đây là "vũ khí bí mật" của Frontend Dev. Thư viện này hỗ trợ xây dựng giao diện AI Chat, streaming phản hồi từ OpenAI/Anthropic/Gemini cực nhanh với React/Next.js.Xây dựng RAG Pipeline: Dùng Python hoặc TypeScript để làm một ứng dụng Chat with PDF/Documents (tải file lên -> nhúng embedding vào ChromaDB/pgvector -> truy vấn và trả kết quả có dẫn nguồn).Đóng gói dự án vào GitHub/Portfolio: Trước khi nộp CV, hãy chắc chắn bạn có ít nhất 1 dự án AI hoàn chỉnh có link demo live (kết hợp React giao diện đẹp + backend FastAPI/LangChain kết nối LLM). | J68: 46277 | K68: Pass | L68: { "judge_result": "PASS", "judge_status": "PASS", "reason": "The response successfully fulfills all requirements of the test case. It provides a constructive analysis of the user's current frontend skills, identifies suitable transitional AI job postings, and clearly outlines the missing skills (such as Python, GenAI, and ML basics) without discouraging the user or making assumptions about their incompetence. The inclusion of a roadmap further adds value and addresses the expected result perfectly." } | M68: Pass | N68: No reference | O68: Kiểm tra khả năng đánh giá mức độ phù hợp của hồ sơ chuyển ngành và xác định các kỹ năng còn thiếu dựa trên yêu cầu tuyển dụng.
A70: TC-30 | B70: Khó | C70: Phân tích nhiều điều kiện và yêu cầu giải thích | D70: Tôi muốn tìm một vị trí Backend Developer tại Thành phố Hồ Chí Minh, làm việc hybrid, yêu cầu Python và PostgreSQL, không yêu cầu trên 2 năm kinh nghiệm, có mức lương từ 15 đến 25 triệu đồng/tháng. Hãy tìm các tin phù hợp, xếp hạng chúng và giải thích nếu không có tin nào đáp ứng đầy đủ. | E70: Kiểm tra đầy đủ tất cả điều kiện: vị trí, địa điểm, hình thức làm việc, công nghệ, kinh nghiệm và khoảng lương. Phân loại tin đáp ứng đầy đủ, đáp ứng một phần và không phù hợp. Nếu không có tin thỏa mãn toàn bộ, phải thông báo rõ và có thể đề xuất các tin gần nhất kèm điều kiện chưa đạt. Không tự nới lỏng điều kiện mà không thông báo. | I70: Dưới đây là bảng đánh giá, xếp hạng các vị trí tuyển dụng Backend Developer tại TP.HCM theo các tiêu chí: làm việc Hybrid, tech stack Python + PostgreSQL, kinh nghiệm không quá 2 năm (1–2 năm) và mức lương trong khoảng 15 – 25 triệu VNĐ/tháng.Bảng xếp hạng các tin tuyển dụngHạngĐơn vị tuyển dụngVị tríYêu cầu Tech StackKinh nghiệmHình thức & Địa điểmMức lươngMức độ đáp ứng1Elisoft VietnamBackend Developer (Python)Python (FastAPI/Django), PostgreSQL, Docker, CI/CD1 – 2 nămHybrid (2-3 ngày WFH/tuần), TP.HCMThỏa thuận (~15 – 25M)100% (Khớp toàn bộ 6 tiêu chí)2QualityRealty / Tech ClientJunior Backend DeveloperPython, FastAPI endpoints, Cloud SQL (PostgreSQL), Docker1 nămTP.HCM (Linh hoạt kết hợp)12 – 20 triệu VNĐ90% (Khớp stack, exp, lương; hình thức linh hoạt)3CMC GlobalJunior Python DeveloperPython, FastAPI/Django, PostgreSQL, Docker, Unit Test1 – 2 nămTP.HCM (Hybrid theo dự án)14 – 22 triệu VNĐ85% (Khớp stack, exp, lương; hybrid phụ thuộc dự án)Phân tích chi tiết và giải thích thứ tự xếp hạngHạng 1: Elisoft Vietnam – Đáp ứng trọn vẹn nhất (100%)Vị trí & Hình thức: Tuyển Backend Developer làm việc tại văn phòng TP.HCM với chính sách Hybrid rõ ràng (cho phép làm việc từ xa 2–3 ngày/tuần).Kỹ thuật & Kinh nghiệm: Yêu cầu 1–2 năm kinh nghiệm làm việc với Python, hệ quản trị cơ sở dữ liệu PostgreSQL, đồng thời yêu cầu kỹ năng đóng gói môi trường với Docker.Mức lương: Khung chi trả dao động trong khoảng 15 – 25 triệu VNĐ/tháng tùy theo năng lực thực chiến.Hạng 2: QualityRealty / Tech Client – Khớp tuyệt đối về công nghệ (90%)Kỹ thuật: Tập trung chính xác vào bộ đôi Python (FastAPI) + PostgreSQL (Cloud SQL) cho ứng viên mốc 1 năm kinh nghiệm. Mức lương: Dải ngân sách công bố là 12 – 20 triệu VNĐ/tháng (giao thoa tốt với khoảng 15 – 20 triệu VNĐ).Lý do xếp sau: Chế độ làm việc có tính linh hoạt theo tiến độ bàn giao sản phẩm, nhưng chưa đưa ra tỷ lệ cố định số ngày WFH hàng tuần như Elisoft.Hạng 3: CMC Global – Quy trình chuẩn, đãi ngộ tốt (85%)Kỹ thuật & Lương: Tuyển vị trí Junior Python/FastAPI kết hợp PostgreSQL và Docker với dải lương 14 – 22 triệu VNĐ/tháng.Lý do xếp sau: Do là môi trường dịch vụ phần mềm theo dự án khách hàng quốc tế, quyền làm việc Hybrid phụ thuộc vào quy định cụ thể của từng khách hàng và từng giai đoạn phát triển (Sprint), không áp dụng đồng loạt 100% cho mọi dự án.Giải thích các trường hợp bị loại trừ (không đáp ứng đủ điều kiện)Parcel Perform: Tuyển Python/PostgreSQL tại TP.HCM và có chế độ Hybrid, nhưng yêu cầu từ 3–5 năm kinh nghiệm (Senior/Lead) với mức lương vượt ngưỡng (>35 triệu VNĐ).Base.vn (Văn phòng TP.HCM): Đúng yêu cầu Python, PostgreSQL và lương 20 – 35 triệu, nhưng áp dụng hình thức làm việc Onsite cố định tại văn phòng.FPT Telecom (Quận 7): Dải lương 12 – 22 triệu cho 1–2 năm kinh nghiệm với Python và SQL, nhưng yêu cầu làm việc Onsite 100%. | J70: 46277 | K70: Pending | M70: Pending | N70: No reference | O70: Kiểm tra khả năng xử lý, đối chiếu, xếp hạng nhiều điều kiện tuyển dụng và giải thích các trường hợp không đáp ứng đầy đủ.

Sheet ChatGPT-5.6-Luna
A1: AGENT TEST CASE
A3: Project: | B3: AI IT Job Market Consultant
A4: Module: | B4: ChatGPT-5.6-Luna
A5: Test environment: | B5: Web ChatGPT 5.6 Luna
A6: Pass | B6: =COUNTIFS(K11:K199, "Pass", A11:A199, "<>*AI") -> 26 | D6: Judge Pass | E6: =COUNTIF(M12:M199,"Pass") -> 25 | F6: Pending | G6: =COUNTIFS(K11:K199, "Pending", A11:A199, "<>*AI") -> 3
A7: Fail | B7: =COUNTIFS(K11:K199, "Fail", A11:A199, "<>*AI") -> 1 | D7: Judge Fail | E7: =COUNTIF(M11:M199,"Fail") -> 1 | F7: Total test case | G7: =COUNTIF(A11:A199, "TC*") -> 30
A9: Test case ID | B9: Test level | C9: Test case name | D9: AI Agent Input | E9: Expected results | I9: Actual results | J9: Test date | K9: Status | L9: Judge result | M9: Judge Status | N9: Reference | O9: Test case purpose
A12: TC-01 | B12: Dễ | C12: Tìm tin tuyển dụng Python Developer | D12: Tôi muốn tìm các tin tuyển dụng Python Developer tại Việt Nam. | E12: Trả về danh sách tin tuyển dụng phù hợp với vị trí Python Developer tại Việt Nam và không đưa các vị trí không liên quan đến Python Developer vào danh sách chính. | I12: Tôi đã tìm kiếm các tin tuyển dụng Python Developer tại Việt Nam, ưu tiên những tin có thể phù hợp với hướng Backend / Software Engineer, đồng thời chú ý đến cơ hội Fresher / Junior. Thời điểm kiểm tra: 12/09/2026. Lưu ý rằng trạng thái tuyển dụng và hạn nộp có thể thay đổi; nên mở tin gốc để xác nhận trước khi ứng tuyển. Một số tin đáng chú ý Vị trí Công ty Địa điểm Kinh nghiệm / Lương Hạn nộp Lập trình viên Python VNPT AI Hà Nội Chưa hiển thị lương; 8 vị trí 26/09/2026 Junior Python Developer BLUBANK TP.HCM, Phú Nhuận Dưới 1 năm; 17–26 triệu/tháng Kiểm tra trên tin gốc Python Developer Lecle Vietnam TP.HCM Chưa thấy mức lương Kiểm tra trên tin gốc Backend Developer – Cloud Product (Golang, Python) CMC Telecom Hà Nội 2 năm; 25–40 triệu/tháng Kiểm tra trên tin gốc Full-stack AI Developer Intern (Ruby / PHP / Python) ZIGExN VeNtura TP.HCM / Hà Nội / Đà Nẵng Không yêu cầu kinh nghiệm Kiểm tra trên tin gốc 1. Lập trình viên Python — VNPT AI VNPT AI đang tuyển 8 vị trí tại Hà Nội, hạn nộp 26/09/2026. Công việc khá sát hướng Python Backend kết hợp AI: Phát triển API bằng REST/gRPC. Xây dựng chatbot, assistant, hệ thống Q&A theo tài liệu và các ứng dụng AI. Làm việc với model/agent, logging, tracing và observability. Áp dụng clean code, design patterns, bảo mật cơ bản. Thực hiện unit test, integration test và tối ưu hiệu năng. Đánh giá: Đây là tin đáng xem nếu bạn muốn đi theo hướng Python Backend + AI Engineering, dù cần kiểm tra kỹ yêu cầu kinh nghiệm. Xem tin tuyển dụng VNPT AI 2. Junior Python Developer — BLUBANK Vị trí tại TP.HCM, quận Phú Nhuận, đăng ngày 02/09/2026, tuyển 2 người, yêu cầu dưới 1 năm kinh nghiệm, mức lương được đăng là 17–26 triệu đồng/tháng. Nội dung công việc gồm: Xây dựng hệ thống thu thập dữ liệu trên nền tảng web và mobile. Làm việc với hệ thống streaming dữ liệu như Kafka. Phát triển framework tự động và cập nhật các luồng thu thập dữ liệu. Sử dụng cơ sở dữ liệu SQL và NoSQL. Đánh giá: Đây là một trong những tin phù hợp nhất để xem xét nếu bạn đang tìm Junior Python Developer tại TP.HCM. Công việc có thiên hướng data collection / automation / backend infrastructure hơn là CRUD API thuần túy. Xem tin Junior Python Developer – BLUBANK 3. Python Developer — Lecle Vietnam Indeed đang hiển thị vị trí Python Developer của Lecle Vietnam tại TP.HCM. Mô tả được hiển thị tập trung vào: Xây dựng các tính năng backend bằng Python. Phát triển ứng dụng có độ trễ thấp, tính sẵn sàng cao và hiệu năng tốt. Đánh giá: Nên mở tin để kiểm tra framework, cấp bậc và yêu cầu kinh nghiệm trước khi quyết định ứng tuyển. Xem tin Python Developer trên Indeed 4. Backend Developer – Cloud Product (Golang, Python) — CMC Telecom Vị trí thuộc CMC Telecom, tại Hà Nội, yêu cầu hiển thị là 2 năm kinh nghiệm, mức lương 25–40 triệu đồng/tháng. Đánh giá: Phù hợp hơn với ứng viên đã có kinh nghiệm backend thực tế. Tuy nhiên, đây là tin đáng lưu để tham khảo yêu cầu tuyển dụng Python Backend ở cấp độ cao hơn. Xem danh sách Python Developer trên TopCV 5. Full-stack AI Developer Intern — ZIGExN VeNtura Vị trí Full-stack AI Developer Intern (Ruby / PHP / Python) được hiển thị tại TP.HCM, Hà Nội và Đà Nẵng, với thông tin không yêu cầu kinh nghiệm. Đánh giá: Đáng xem nếu bạn chấp nhận vị trí AI / Full-stack Intern thay vì chỉ tìm đúng chức danh Python Developer. Cần mở tin để xác nhận công nghệ thực tế và tình trạng còn tuyển. Xem danh sách Python Developer trên TopCV Các trang nên dùng để tìm thêm TopCV – Python Developer — Có thể lọc theo TP.HCM, Hà Nội, Intern, Fresher, Junior. CareerViet – việc làm Python — Có nhiều tin chứa Python trong yêu cầu, nhưng cần lọc kỹ vì không phải tất cả đều là Python Developer. CareerViet – Python Developer / Django Fresher / Junior tại TP.HCM — Hữu ích để tìm các tin liên quan Django, dù kết quả có thể bao gồm cả vị trí không thuần Python. Indeed – Remote Python Developer Jobs tại Việt Nam — Có thể tìm thêm các vị trí Python tại TP.HCM và remote. Từ khóa nên tìm Đừng chỉ tìm Python Developer. Với định hướng của bạn, nên dùng cả: Python Developer Python Backend Developer Backend Developer Python Django Developer FastAPI Developer Python Software Engineer Junior Python Developer Fresher Python Developer AI Engineer Python AI Backend Engineer Python Automation Developer Nếu ưu tiên TP.HCM + Fresher/Junior, tôi sẽ bắt đầu theo thứ tự: Junior Python Developer → Python Backend Developer → Django Developer → FastAPI Developer → AI Engineer Python → Python Automation Developer. Trong các kết quả vừa tìm, BLUBANK là tin có thông tin rõ ràng và sát cấp độ Junior nhất; VNPT AI đáng chú ý nếu bạn muốn kết hợp Python Backend với AI. | J12: 46277 | K12: Pass | L12: { "judge_result": "PASS", "judge_status": "PASS", "reason": "The Actual Result successfully provides a relevant list of Python Developer job postings in Vietnam, satisfying the Expected Result without including unrelated positions." } | M12: Pass | N12: No reference | O12: Kiểm tra khả năng truy xuất và cung cấp các tin tuyển dụng phù hợp với vị trí Python Developer tại Việt Nam.
A14: TC-02 | B14: Dễ | C14: Tìm việc Backend Developer | D14: Hãy tìm các tin tuyển dụng Backend Developer tại Việt Nam. | E14: Cung cấp các tin tuyển dụng thuộc nhóm Backend Developer và không tự tạo tên công ty hoặc tin tuyển dụng. | I14: Tôi đã tìm các tin Backend Developer / Backend Engineer tại Việt Nam, ưu tiên Fresher, Junior và các vị trí có thể phù hợp với nền tảng Python, Django, FastAPI, REST API và SQL của bạn. Thời điểm kiểm tra: 12/09/2026. Các tin dưới đây là kết quả tìm kiếm hiện tại; trạng thái tuyển dụng có thể thay đổi nên cần mở tin gốc để xác nhận trước khi ứng tuyển. 1. Các tin đáng chú ý 6 Vị trí Công ty Địa điểm Kinh nghiệm / Lương Hạn nộp Backend Developer (Fresher/Junior) Ecoba Hà Nội Fresher/Junior 30/09/2026 Thực Tập Sinh – Lập Trình Viên Backend Nam Phương Digital Technology TP.HCM Internship Kiểm tra tin gốc Junior Back-End Engineer – Full-Time Freshdi Vietnam TP.HCM Junior Kiểm tra tin gốc [Junior] Backend Engineer (Golang) Anfin TP.HCM Junior Kiểm tra tin gốc Backend Junior Aioz Vietnam TP.HCM Tối thiểu 1 năm Kiểm tra tin gốc Software Developer – Intern Bouygues Construction IT Vietnam TP.HCM Internship Kiểm tra tin gốc Web System Engineer – Fresher OTANI U.P. Hà Nội Chấp nhận Fresher; 11,5–18,5 triệu/tháng 15/09/2026 Back-end Engineer FPT Long Châu TP.HCM Chưa thấy cấp bậc cụ thể 07/10/2026 Backend & AI Application Engineer Decox TP.HCM Chưa thấy cấp bậc cụ thể 11/10/2026 2. Phân tích từng tin phù hợp Backend Developer (Fresher/Junior) — Ecoba Ecoba Địa điểm: Hoàng Đạo Thúy, quận Cầu Giấy, Hà Nội Hạn nộp: 30/09/2026 Số lượng: 1 vị trí Mô tả công việc có nhiều điểm khá sát với Backend Developer: Phát triển và bảo trì hệ thống ERP nội bộ. Xây dựng, chuẩn hóa và tối ưu RESTful API / gRPC. Làm việc với PostgreSQL / MySQL. Tối ưu truy vấn và bảo đảm tính toàn vẹn, bảo mật dữ liệu. Viết script tự động hóa và tích hợp dữ liệu. Kết nối với các hệ thống như Microsoft 365, SharePoint và SAP. Đánh giá: Đây là tin đáng ưu tiên nếu bạn muốn tìm Backend Fresher/Junior đúng nghĩa. Mô tả không chỉ tập trung vào một framework mà còn đề cập API, database, tích hợp hệ thống và automation — khá phù hợp để phát triển theo hướng Backend Engineer. Xem tin tuyển dụng Ecoba Thực Tập Sinh – Lập Trình Viên Backend — Nam Phương Digital Technology Nam Phương Digital Technology Địa điểm: TP.HCM Công việc được mô tả gồm: Hỗ trợ phát triển hệ thống backend cho Web/App. Xây dựng API. Xử lý các chức năng và logic backend. Làm việc dưới sự hướng dẫn của mentor. Đánh giá: Đây là lựa chọn nên xem nếu bạn muốn tìm Internship Backend tại TP.HCM. Tuy nhiên, cần mở tin để kiểm tra framework, yêu cầu kiến thức và mức phụ cấp. Xem danh sách Fresher Backend trên Indeed Junior Back-End Engineer – Full-Time — Freshdi Vietnam Freshdi Vietnam Địa điểm: TP.HCM Thông tin hiển thị cho biết công việc bao gồm: Phát triển, bảo trì và tối ưu hệ thống backend. Quản trị và tối ưu database SQL & NoSQL. Lương thỏa thuận theo năng lực, có thưởng theo hiệu suất. Đánh giá: Khá phù hợp với người muốn đi theo Backend Engineer, đặc biệt nếu muốn tiếp xúc cả SQL và NoSQL. Tin không hiển thị rõ yêu cầu số năm kinh nghiệm trong phần kết quả, nên cần đọc mô tả đầy đủ trước khi ứng tuyển. Xem tin trên Indeed [Junior] Backend Engineer (Golang) — Anfin Anfin Địa điểm: TP.HCM Công việc bao gồm: Làm việc với Tech Lead, UI/UX và các bên liên quan. Thiết kế, xây dựng, kiểm thử và triển khai sản phẩm. Phát triển các hệ thống có khả năng mở rộng trong lĩnh vực đầu tư. Đánh giá: Đây là tin Junior Backend đáng chú ý, nhưng công nghệ chính là Golang, không phải Python. Nếu mục tiêu của bạn là trở thành Backend Engineer lâu dài thay vì chỉ giới hạn ở Python, có thể cân nhắc. Xem tin trên Indeed Backend Junior — Aioz Vietnam Aioz Network Địa điểm: TP.HCM Yêu cầu hiển thị: Tối thiểu 1 năm kinh nghiệm phát triển dịch vụ hoặc hệ thống backend. Công việc tập trung vào phát triển và duy trì các dịch vụ/hệ thống backend hiệu năng cao. Đánh giá: Có thể hơi cao hơn mức Fresher, nhưng vẫn đáng lưu nếu bạn có project backend thực tế và có thể chứng minh năng lực qua GitHub hoặc CV. Xem tin Backend Fresher trên Indeed Software Developer – Intern — Bouygues Construction IT Vietnam Bouygues Construction IT Vietnam Địa điểm: TP.HCM Mô tả hiển thị: Phát triển tính năng cho hệ thống Frontend và Backend. Học hỏi framework phát triển. Thực hiện thiết kế và coding. Yêu cầu hiểu biết về Design Pattern. Đánh giá: Không phải Backend Intern thuần túy, nhưng có thể là lựa chọn tốt để bước vào môi trường phát triển phần mềm chuyên nghiệp nếu bạn chấp nhận vị trí Software Developer Intern. Xem tin trên Indeed Web System Engineer – Hà Nội – Chấp nhận Fresher — OTANI U.P. OTANI U.P. Địa điểm: Hà Nội Mức lương: 11,5–18,5 triệu đồng/tháng Hạn nộp: 15/09/2026 Tin có tiêu đề Web System Engineer và chấp nhận Fresher. Công việc có thể liên quan đến phát triển hệ thống web, nhưng cần kiểm tra mô tả đầy đủ để xác định tỷ trọng backend và công nghệ sử dụng. Đánh giá: Đáng xem nếu bạn mở rộng tìm kiếm từ Backend Developer sang Web System Engineer, đặc biệt khi ưu tiên cơ hội Fresher. Xem tin trên Joboko Back-end Engineer — FPT Long Châu FPT Long Châu Địa điểm: TP.HCM Hạn nộp: 07/10/2026 Tin được liệt kê trong nhóm tuyển dụng Backend tại TP.HCM. Kết quả hiện tại chưa hiển thị rõ cấp bậc, stack hoặc số năm kinh nghiệm. Đánh giá: Nên mở tin để kiểm tra vì đây là một vị trí có chức danh Back-end Engineer rõ ràng, nhưng chưa thể kết luận có phù hợp Fresher/Junior hay không. Xem danh sách Backend trên CareerViet Backend & AI Application Engineer — Decox Decox Địa điểm: TP.HCM Hạn nộp: 11/10/2026 Tin mới được cập nhật trong danh sách tuyển dụng Backend, với chức danh kết hợp Backend & AI Application Engineer. Đánh giá: Đáng chú ý nếu bạn muốn kết hợp Backend + AI Application, nhưng cần xem kỹ yêu cầu vì chưa có đủ thông tin về cấp bậc, ngôn ngữ và framework. Xem danh sách Backend trên CareerViet 3. Nếu ưu tiên TP.HCM và Fresher/Junior Tôi sẽ chia thành ba nhóm để bạn tìm hiệu quả hơn: Mức ưu tiên Tin nên xem Lý do Ưu tiên 1 Nam Phương – Backend Intern Có đúng hướng Backend, phù hợp tìm internship Ưu tiên 2 Freshdi – Junior Back-End Engineer Đúng chức danh Junior, có backend + SQL/NoSQL Ưu tiên 3 Anfin – Junior Backend Engineer Cơ hội Junior rõ ràng, nhưng cần học/biết Golang Ưu tiên 4 Aioz – Backend Junior Phù hợp nếu có thể chứng minh khoảng 1 năm kinh nghiệm tương đương Ưu tiên 5 Decox – Backend & AI Application Engineer Hợp hướng Backend kết hợp AI, cần kiểm tra cấp bậc 4. Các trang tìm việc nên theo dõi Indeed – Fresher Backend tại TP.HCM — Có các tin Freshdi, Anfin, Aioz và internship. Indeed – Fresher Backend Developer tại Việt Nam — Phù hợp tìm thêm các vị trí Backend, Java, .NET, Golang và Full-stack có thiên hướng backend. Joboko – Backend Developer — Có thể lọc theo địa điểm, mức kinh nghiệm và mức lương. CareerViet – Fresher Backend — Có các tin Backend Engineer, Backend AI và Full-stack Fresher/Junior. Glints – Fresher Backend — Có bộ lọc Internship, Fresher, Junior, Hybrid và Remote. Từ khóa nên dùng Để không bỏ sót các tin không ghi đúng chức danh “Backend Developer”, bạn nên tìm: Backend Developer Backend Engineer Junior Backend Developer Junior Backend Engineer Fresher Backend Developer Backend Intern Python Backend Developer Django Developer FastAPI Developer Software Engineer Backend Web System Engineer AI Backend Engineer Backend & AI Engineer Kết luận: Nếu mục tiêu hiện tại là tìm việc đầu tiên tại TP.HCM, tôi sẽ tập trung vào Backend Intern, Junior Back-End Engineer, Junior Backend Developer thay vì chỉ tìm “Python Developer”. Với nền tảng Python/Django/FastAPI, bạn vẫn có thể ứng tuyển các tin ghi chung là Backend Developer nếu yêu cầu ngôn ngữ không bắt buộc Java, .NET hoặc Golang. | J14: 46277 | K14: Pass | L14: { "judge_result": "PASS", "judge_status": "PASS", "reason": "The Actual Result successfully provides a list of specific Backend Developer job postings in Vietnam with real company names and detailed job descriptions, fulfilling the Expected Result without fabricating information." } | M14: Pass | N14: No reference | O14: Kiểm tra khả năng tìm kiếm và trả về các tin tuyển dụng thuộc nhóm Backend Developer.
A16: TC-03 | B16: Dễ | C16: Tìm việc Frontend Developer | D16: Có những tin tuyển dụng Frontend Developer nào? | E16: Trả về các tin tuyển dụng liên quan đến Frontend Developer. Nếu có dữ liệu, cung cấp các trường như công ty, vị trí, địa điểm và đường dẫn hoặc nguồn tin. | I16: Tôi sẽ tập trung vào Frontend Developer tại Việt Nam, ưu tiên TP.HCM, Fresher/Junior và các công nghệ gần với stack bạn đang có như React, Next.js, TypeScript, React Native. Lưu ý về độ mới: Hôm nay là 12/09/2026. Kết quả tìm kiếm có một số tin đã hết hạn, nên tôi tách rõ tin còn có thể xem xét và tin chỉ dùng để tham khảo. Không nên xem một tin là đang tuyển chỉ vì nó vẫn xuất hiện trên trang tìm việc. Các tin tuyển dụng tìm được Vị trí Công ty Địa điểm Kinh nghiệm Lương Trạng thái Junior Frontend Developer Alchemy Technologies TP.HCM, An Khánh Dưới 1 năm Thỏa thuận Cần xác nhận Junior Front-End Developer AIOZ Vietnam TP.HCM, Bến Thành 2 năm 15–20 triệu/tháng Đã hết hạn 09/09/2026 Frontend Developer Junior (ReactJS) Estuary TP.HCM, Xuân Hòa 1 năm Thỏa thuận Đã hết hạn 31/07/2026 Junior-Fresher Front-end Developer Rikkeisoft Hà Nội Junior/Fresher Chưa rõ Cần xác nhận Frontend Developer / ReactJS Tinhvan Group Hà Nội 0–3 năm, có thể chấp nhận Fresher Chưa rõ Cần xác nhận 1. Junior Frontend Developer — Alchemy Technologies Alchemy Technologies Địa điểm: TP.HCM, Phường An Khánh, khu vực Thủ Đức cũ. Kinh nghiệm: Dưới 1 năm. Lương: Thỏa thuận. Hình thức: Toàn thời gian, onsite. Yêu cầu học vấn: Cao đẳng trở lên. Công việc chính: Xây dựng và duy trì các tính năng frontend. Tối ưu trải nghiệm người dùng, giao diện responsive trên nhiều thiết bị và trình duyệt. Tối ưu hiệu năng, tốc độ tải trang và technical SEO. Tham gia code review và cải thiện chất lượng code. Đánh giá: Đây là tin gần với Fresher/Junior nhất trong các kết quả tìm được. Tuy nhiên, tin có hạn nộp 04/07/2026, nên tại thời điểm hiện tại cần kiểm tra xem công ty có gia hạn hoặc đăng lại hay không. Xem tin Alchemy Technologies trên TopCV 2. Junior Front-End Developer — AIOZ Vietnam AIOZ Vietnam Địa điểm: TP.HCM, Phường Bến Thành. Kinh nghiệm: 2 năm. Lương: 15–20 triệu/tháng. Hình thức: Toàn thời gian, onsite. Hạn ứng tuyển: 09/09/2026 — đã hết hạn. Stack được đề cập: TypeScript React Next.js React Native Electron Web3 / DApps Đánh giá: Về mặt công nghệ, đây là tin rất gần với stack frontend bạn đang có. Đặc biệt, React + Next.js + TypeScript + React Native là một tổ hợp đáng chú ý. Tuy nhiên, yêu cầu 2 năm kinh nghiệm và tin đã hết hạn, nên chỉ nên dùng để tham khảo hoặc tìm tin đăng mới tương tự. Xem tin AIOZ trên TopCV 3. Frontend Developer Junior (ReactJS) — Estuary Estuary Địa điểm: TP.HCM, Phường Xuân Hòa, khu vực Quận 3 cũ. Kinh nghiệm: 1 năm. Lương: Thỏa thuận. Hạn ứng tuyển: 31/07/2026 — đã hết hạn. Công việc: Phát triển frontend với ReactJS, tham gia xây dựng tính năng, được cung cấp thiết bị và đào tạo nội bộ. Đánh giá: Đây là dạng tin phù hợp để bạn tham khảo khi tìm Junior React Developer. Tuy nhiên, không nên tính đây là cơ hội đang mở ở thời điểm hiện tại. Xem tin Estuary trên TopCV 4. Junior-Fresher Front-end Developer — Rikkeisoft Rikkeisoft Kết quả Glassdoor đang liệt kê vị trí 05 Junior-Fresher Front-end Developer của Rikkeisoft tại Hà Nội. Đánh giá: Đây là một từ khóa và công ty đáng theo dõi nếu bạn chấp nhận làm việc tại Hà Nội. Tuy nhiên, kết quả hiện tại chưa cung cấp đầy đủ mô tả, stack, lương và hạn nộp để xác nhận đây là tin còn mở. Tìm Junior Front-end Developer tại Việt Nam trên Glassdoor 5. Junior Frontend / Frontend Developer — Tinhvan Group Tinhvan Group Indeed đang hiển thị tin Lập trình viên Junior Frontend của Tinhvan Group với yêu cầu khoảng 0–3 năm kinh nghiệm, chấp nhận Fresher và ưu tiên ứng viên có kinh nghiệm với một framework JavaScript như Angular hoặc ReactJS. Đánh giá: Đây là tin đáng kiểm tra nếu bạn muốn tìm vị trí Frontend Fresher/Junior, nhưng kết quả hiện tại chưa đủ thông tin để xác nhận stack chính, địa điểm chính xác và hạn nộp. Xem kết quả Junior Frontend trên Indeed Nhận xét theo stack của bạn Với những công nghệ bạn đang có trong CV: React, React Native, Next.js, TypeScript, Tailwind CSS, HTML/CSS thì bạn nên ưu tiên tìm theo các chức danh sau, thay vì chỉ gõ Frontend Developer: Từ khóa Mức độ phù hợp Junior Frontend Developer React Rất phù hợp ReactJS Developer Fresher Rất phù hợp Next.js Developer Junior Phù hợp Frontend Engineer TypeScript Phù hợp React Native Developer Junior Phù hợp nếu muốn đi mobile Frontend Developer Intern Phù hợp nếu chưa có kinh nghiệm chính thức Web Developer React Có thể mở rộng cơ hội Full-stack Developer React Node.js Nên xem nếu chấp nhận làm cả backend Kết luận: Nếu xét riêng mức độ phù hợp với stack hiện tại, AIOZ là tin đáng chú ý nhất về công nghệ, còn Alchemy Technologies gần với cấp độ Fresher/Junior hơn. Nhưng cả hai đều cần xác nhận lại trạng thái tuyển dụng, và AIOZ đã quá hạn vào ngày 09/09/2026. Tôi chưa tìm được trong lượt này một tin Frontend Intern/Fresher tại TP.HCM còn xác nhận rõ ràng là đang mở. Vì vậy, không nên coi danh sách trên là danh sách “đang tuyển chắc chắn”; nó phù hợp hơn để bạn bắt đầu rà soát và tìm các tin đăng mới tương tự. | J16: 46277 | K16: Pass | L16: { "judge_result": "PASS", "judge_status": "PASS", "reason": "The Actual Result successfully provides a list of relevant Frontend Developer job postings, including required details such as company, position, location, and source links, satisfying the Expected Result." } | M16: Pass | N16: No reference | O16: Kiểm tra khả năng truy xuất các tin tuyển dụng liên quan đến vị trí Frontend Developer.
